Workbook

Sheet Cleaned Table
A1: Link | B1: Restaurant_name | C1: Review_score | D1: No_of_reviews | E1: Price_range | F1: Open_time | G1: Review | H1: Address | I1: District classification.Latitude | J1: District classification.Longitude | K1: District | L1: Ward | M1: Price_bucket | N1: Time_bucket | O1: Rank | P1: Category | Q1: Local_vs_English | R1: Cafe_options
A2: https://www.google.com/maps/place/Hoang%E2%80%99s+Kitchen+-Vietnamese+cuisine+%26+Vegan+food/data=!4m7!3m6!1s0x31752f7c28d2133d:0xf4f42c414b22791c!8m2!3d10.774218!4d106.6966059!16s%2Fg%2F11w236c_vf!19sChIJPRPSKHwvdTERHHkiS0Es9PQ?authuser=0&hl=en&rclk=1 | B2: Hoang’s Kitchen -Vietnamese cuisine & Vegan food | C2: 4.9 | D2: 19105 | E2: ₫100–200K | F2: 0.41666667 | G2: "Delicious and amazing service!" | H2: 45 Thủ Khoa Huân | I2: 10.774218 | J2: 106.69661 | K2: District 1 | L2: Bến Thành | M2: Medium | N2: Morning | O2: 1 | P2: Modern vegan / plant-based | Q2: English / international-facing | R2: No
A3: https://www.google.com/maps/place/Ben+Nghe+Street+Food/data=!4m7!3m6!1s0x31752f38d6d12d4b:0x9a6eb30ab7589d13!8m2!3d10.7773167!4d106.6977562!16s%2Fg%2F11bxgb8ltc!19sChIJSy3R1jgvdTERE51Ytwqzbpo?authuser=0&hl=en&rclk=1 | B3: Ben Nghe Street Food | C3: 4.3 | D3: 12589 | E3: ₫100–200K | G3: "Great location, large selection of types, both | H3: 134 Nam Kỳ Khởi Nghĩa | I3: 10.777317 | J3: 106.69776 | K3: District 1 | L3: Bến Thành | M3: Medium | N3: No data | O3: 2 | P3: Quick-service / noodle / banh mi vegetarian | Q3: English / international-facing | R3: No
A4: https://www.google.com/maps/place/De+Tham+Restaurant+-+Vietnamese+cuisine+%26+vegetarian+Food/data=!4m7!3m6!1s0x31752fe948e20f7f:0x5a5f1358daf89ccf!8m2!3d10.7682442!4d106.6936304!16s%2Fg%2F11why8sz0c!19sChIJfw_iSOkvdTERz5z42lgTX1o?authuser=0&hl=en&rclk=1 | B4: De Tham Restaurant - Vietnamese cuisine & vegetarian Food | C4: 4.9 | D4: 11763 | E4: ₫100–200K | F4: 0.4375 | G4: "We ordered everything here and the | H4: 258 Đề Thám | I4: 10.768244 | J4: 106.69363 | K4: District 1 | L4: Phạm Ngũ Lão | M4: Medium | N4: Morning | O4: 3 | P4: Vegetarian bistro / casual dining | Q4: English / international-facing | R4: No
A5: https://www.google.com/maps/place/Tung%27s+Restaurant+-+Vietnamese+Cuisine+%26+vegetarian+Food/data=!4m7!3m6!1s0x31752f59e15c67e9:0x7a43f830bff40c1!8m2!3d10.7726481!4d106.6964836!16s%2Fg%2F11v_25lpjr!19sChIJ6Wdc4VkvdTERwUD_C4M_pAc?authuser=0&hl=en&rclk=1 | B5: Tung's Restaurant - Vietnamese Cuisine & vegetarian Food | C5: 4.9 | D5: 11585 | E5: ₫100–200K | F5: 0.41666667 | G5: "The options were perfectly made, best mock beef I ve ever had." | H5: 230 Lê Thánh Tôn | I5: 10.772648 | J5: 106.69648 | K5: District 1 | L5: Phạm Ngũ Lão | M5: Medium | N5: Morning | O5: 4 | P5: Vegetarian bistro / casual dining | Q5: English / international-facing | R5: No
A6: https://www.google.com/maps/place/Propaganda+Vietnamese+Bistro/data=!4m7!3m6!1s0x31752f378dabe5db:0x635cd76f30bd0737!8m2!3d10.7787806!4d106.6981583!16s%2Fg%2F1pyqmjd_t!19sChIJ2-WrjTcvdTERNwe9MG_XXGM?authuser=0&hl=en&rclk=1 | B6: Propaganda Vietnamese Bistro | C6: 4.4 | D6: 4565 | E6: ₫200–300K | G6: "Very tasty options and a cute space." | H6: 21 Đ. Hàn Thuyên | I6: 10.778781 | J6: 106.69816 | K6: District 1 | L6: Bến Nghé | M6: Premium | N6: No data | O6: 7 | P6: Vegetarian bistro / casual dining | Q6: English / international-facing | R6: No
A7: https://www.google.com/maps/place/Soumaki+-+Your+Healthy+Food+Soulmate+-+L%C3%BD+T%E1%BB%B1+Tr%E1%BB%8Dng/data=!4m7!3m6!1s0x31752fd9351b8d79:0xcee998c37f0eb018!8m2!3d10.7771971!4d106.700107!16s%2Fg%2F11s3vl41pc!19sChIJeY0bNdkvdTERGLAOf8OY6c4?authuser=0&hl=en&rclk=1 | B7: Soumaki - Your Healthy Food Soulmate - Lý Tự Trọng | C7: 4.9 | D7: 3679 | E7: ₫100–200K | G7: "The was so tasty and healthy and it filled me up!" | H7: 42 Lý Tự Trọng | I7: 10.777197 | J7: 106.70011 | K7: District 1 | L7: Bến Nghé | M7: Medium | N7: No data | O7: 8 | P7: Modern vegan / plant-based | Q7: English / international-facing | R7: No
A8: https://www.google.com/maps/place/Heart+of+Darkness+Craft+Brewery/data=!4m7!3m6!1s0x31752f48f43430cd:0x51c14d0271469c87!8m2!3d10.7798149!4d106.7029294!16s%2Fg%2F11crxw6gy6!19sChIJzTA09EgvdTERh5xGcQJNwVE?authuser=0&hl=en&rclk=1 | B8: Heart of Darkness Craft Brewery | C8: 4.6 | D8: 3635 | E8: ₫200–300K | G8: "Meat-eaters, vegetarians and can all find PLENTY to eat." | H8: 31D Lý Tự Trọng | I8: 10.779815 | J8: 106.70293 | K8: District 1 | L8: Bến Nghé | M8: Premium | N8: No data | O8: 9 | P8: Vegetarian bistro / casual dining | Q8: English / international-facing | R8: No
A9: https://www.google.com/maps/place/Dahi+Handi+Indian+Restaurant/data=!4m7!3m6!1s0x31752f7a7d473e5d:0x1835902d3fa5e1ca!8m2!3d10.7761731!4d106.7048075!16s%2Fg%2F11gl12kgyd!19sChIJXT5HfXovdTERyuGlPy2QNRg?authuser=0&hl=en&rclk=1 | B9: Dahi Handi Indian Restaurant | C9: 4.8 | D9: 3412 | E9: ₫200–300K | G9: "Finger licking good and service with a smile by Johnny." | H9: 23 Đông Du | I9: 10.776173 | J9: 106.70481 | K9: District 1 | L9: Bến Nghé | M9: Premium | N9: No data | O9: 10 | P9: Vegetarian bistro / casual dining | Q9: English / international-facing | R9: No
A10: https://www.google.com/maps/place/My+Banh+Mi/data=!4m7!3m6!1s0x31752f481a3d8727:0xf40b76660ec7ebf!8m2!3d10.7791987!4d106.7005186!16s%2Fg%2F11btwr4dq9!19sChIJJ4c9GkgvdTERv37sYGa3QA8?authuser=0&hl=en&rclk=1 | B10: My Banh Mi | C10: 4.6 | D10: 3201 | E10: ₫100–200K | G10: "Excellent with | H10: 57 Nguyễn Du | I10: 10.779199 | J10: 106.70052 | K10: District 1 | L10: Bến Nghé | M10: Medium | N10: No data | O10: 11 | P10: Quick-service / noodle / banh mi vegetarian | Q10: English / international-facing | R10: No
A11: https://www.google.com/maps/place/Poke+Saigon+Ly+Tu+Trong/data=!4m7!3m6!1s0x31752f47f450b265:0xa46f765f0dea01e8!8m2!3d10.7771626!4d106.7001507!16s%2Fg%2F11g020cwyh!19sChIJZbJQ9EcvdTER6AHqDV92b6Q?authuser=0&hl=en&rclk=1 | B11: Poke Saigon Ly Tu Trong | C11: 4.8 | D11: 2821 | E11: ₫100–200K | G11: "Amazing fresh, tasty, nutritious served with a warm welcoming smile." | H11: First floor, 42 Bis Lý Tự Trọng | I11: 10.777163 | J11: 106.70015 | K11: District 1 | L11: Bến Nghé | M11: Medium | N11: No data | O11: 12 | P11: Modern vegan / plant-based | Q11: English / international-facing | R11: No
A12: https://www.google.com/maps/place/Tanishq+Indian+Vegetarian+Restaurant/data=!4m7!3m6!1s0x31752f005cdd2991:0x5e8b095e1f1ff220!8m2!3d10.7719456!4d106.6939273!16s%2Fg%2F11w9kmg0rf!19sChIJkSndXAAvdTERIPIfH14Ji14?authuser=0&hl=en&rclk=1 | B12: Tanishq Indian Vegetarian Restaurant | C12: 4.9 | D12: 2810 | E12: ₫200–300K | F12: 0.33333333 | G12: "We are and left completely full and happy." | H12: 258 Lý Tự Trọng | I12: 10.771946 | J12: 106.69393 | K12: District 1 | L12: Phạm Ngũ Lão | M12: Premium | N12: Morning | O12: 13 | P12: Vegetarian bistro / casual dining | Q12: English / international-facing | R12: No
A13: https://www.google.com/maps/place/Heal+and+Celeb+Vegan+Restaurant/data=!4m7!3m6!1s0x317529dc13f3f3b9:0xffd3cac3c0af494c!8m2!3d10.793559!4d106.686756!16s%2Fg%2F11t0rzqfyp!19sChIJufPzE9wpdTERTEmvwMPK0_8?authuser=0&hl=en&rclk=1 | B13: Heal and Celeb Vegan Restaurant | C13: 4.9 | D13: 2355 | E13: ₫100–200K | F13: 0.39583333 | G13: "Every dish was bursting with flavor, showcasing the best of cuisine." | H13: 27/1 Nguyễn Văn Nguyễn | I13: 10.793559 | J13: 106.68676 | K13: District 1 | L13: Tân Định | M13: Medium | N13: Morning | O13: 14 | P13: Modern vegan / plant-based | Q13: English / international-facing | R13: No
A14: https://www.google.com/maps/place/Hoa+T%C3%BAc+Saigon/data=!4m7!3m6!1s0x31752f4627907e63:0x228869e80686c24a!8m2!3d10.7785004!4d106.7037745!16s%2Fg%2F11g8bqp8hn!19sChIJY36QJ0YvdTERSsKGBuhpiCI?authuser=0&hl=en&rclk=1 | B14: Hoa Túc Saigon | C14: 4.5 | D14: 2353 | E14: ₫200–300K | G14: "Delicious and the understood what a gluten allergy is." | H14: 74/7 Hai Bà Trưng | I14: 10.7785 | J14: 106.70377 | K14: District 1 | L14: Bến Nghé | M14: Premium | N14: No data | O14: 15 | P14: Vegetarian bistro / casual dining | Q14: English / international-facing | R14: No
A15: https://www.google.com/maps/place/Be+An+Vegetarian+Bistro/data=!4m7!3m6!1s0x31752ffbfbe36a49:0x9c10bfad0d4fdd69!8m2!3d10.7733531!4d106.7038615!16s%2Fg%2F11fs2zs_3d!19sChIJSWrj-_svdTERad1PDa2_EJw?authuser=0&hl=en&rclk=1 | B15: Be An Vegetarian Bistro | C15: 4.8 | D15: 2220 | E15: ₫200–300K | F15: 0.41666667 | G15: "Gorgeous , lovely staff and the most delicious | H15: Saigon Garden, 99 Nguyễn Huệ | I15: 10.773353 | J15: 106.70386 | K15: District 1 | L15: Nguyễn Thái Bình | M15: Premium | N15: Morning | O15: 16 | P15: Vegetarian bistro / casual dining | Q15: English / international-facing | R15: No
A16: https://www.google.com/maps/place/G%C3%A1nh+-+Truly+Vietnamese+Cuisine/data=!4m7!3m6!1s0x31752f4934863955:0xe45e41df1006ad7a!8m2!3d10.77714!4d106.704236!16s%2Fg%2F11bxkpfpjs!19sChIJVTmGNEkvdTEReq0GEN9BXuQ?authuser=0&hl=en&rclk=1 | B16: Gánh - Truly Vietnamese Cuisine | C16: 4.5 | D16: 2197 | E16: ₫200–300K | G16: "Amazing healthy , great music and ambience" | H16: 91 Hai Bà Trưng | I16: 10.77714 | J16: 106.70424 | K16: District 1 | L16: Bến Nghé | M16: Premium | N16: No data | O16: 17 | P16: Local Vietnamese vegetarian | Q16: Mixed local + English-facing | R16: No
A17: https://www.google.com/maps/place/Au+Parc+Caf%C3%A9/data=!4m7!3m6!1s0x31752f378c9f5bf3:0x7e1388eb0419e27a!8m2!3d10.7787276!4d106.6980638!16s%2Fg%2F1hc2zh7r9!19sChIJ81ufjDcvdTEReuIZBOuIE34?authuser=0&hl=en&rclk=1 | B17: Au Parc Café | C17: 4.5 | D17: 2112 | E17: ₫200–300K | G17: "Very good - clean, healthy and fast for a full fresh meal." | H17: 23 Đ. Hàn Thuyên | I17: 10.778728 | J17: 106.69806 | K17: District 1 | L17: Bến Nghé | M17: Premium | N17: No data | O17: 19 | P17: Vegetarian cafe / light dining | Q17: English / international-facing | R17: Yes
A18: https://www.google.com/maps/place/21Grams+Vegetarian/data=!4m7!3m6!1s0x31752f616c7ba2f3:0xf25f36475c2b39b3!8m2!3d10.774103!4d106.7041327!16s%2Fg%2F11ty14p2l3!19sChIJ86J7bGEvdTERszkrXEc2X_I?authuser=0&hl=en&rclk=1 | B18: 21Grams Vegetarian | C18: 4.9 | D18: 1857 | E18: ₫100–200K | F18: 0.41666667 | G18: "All with | H18: 42 Nguyễn Huệ | I18: 10.774103 | J18: 106.70413 | K18: District 1 | L18: Bến Nghé | M18: Medium | N18: Morning | O18: 21 | P18: Vegetarian bistro / casual dining | Q18: English / international-facing | R18: No
A19: https://www.google.com/maps/place/Curry-licious+Indian+Restaurant/data=!4m7!3m6!1s0x31752ff05dc82141:0x8bf6105890ee8927!8m2!3d10.7771121!4d106.7039749!16s%2Fg%2F11x90vs602!19sChIJQSHIXfAvdTERJ4nukFgQ9os?authuser=0&hl=en&rclk=1 | B19: Curry-licious Indian Restaurant | C19: 4.9 | D19: 1815 | E19: ₫200–300K | G19: "We tried vegetarians options and all was awesome." | H19: 9 Công trường Lam Sơn | I19: 10.777112 | J19: 106.70397 | K19: District 1 | L19: Bến Nghé | M19: Premium | N19: No data | O19: 22 | P19: Vegetarian bistro / casual dining | Q19: English / international-facing | R19: No
A20: https://www.google.com/maps/place/B%C3%A1nh+M%C3%AC+The+One+%E2%80%93+Vietnamese+Sandwich+%26+Vegan+Food/data=!4m7!3m6!1s0x31752fce14c0893f:0x293d0fc78c33785e!8m2!3d10.7723259!4d106.6945746!16s%2Fg%2F11w2fr19ss!19sChIJP4nAFM4vdTERXngzjMcPPSk?authuser=0&hl=en&rclk=1 | B20: Bánh Mì The One – Vietnamese Sandwich & Vegan Food | C20: 4.9 | D20: 1600 | E20: ₫1–100,000 | G20: "Delicious, both and meat options, super friendly staff 🫶🏻" | H20: 234 Lý Tự Trọng | I20: 10.772326 | J20: 106.69457 | K20: District 1 | L20: Phạm Ngũ Lão | M20: Low | N20: No data | O20: 23 | P20: Quick-service / noodle / banh mi vegetarian | Q20: English / international-facing | R20: No
A21: https://www.google.com/maps/place/Shamballa+Vegetarian,+Restaurant+%26+Lounge+-+Sai+Gon/data=!4m7!3m6!1s0x31752fabc8d54ad3:0xc175c07deb731e0d!8m2!3d10.7795135!4d106.7026522!16s%2Fg%2F11jvbdshld!19sChIJ00rVyKsvdTERDR5z633AdcE?authuser=0&hl=en&rclk=1 | B21: Shamballa Vegetarian, Restaurant & Lounge - Sai Gon | C21: 4.7 | D21: 1452 | E21: ₫200–300K | F21: 0.375 | G21: "Amazing ambience (sitting outside) and served delicious ." | H21: 31 Lý Tự Trọng | I21: 10.779514 | J21: 106.70265 | K21: District 1 | L21: Bến Nghé | M21: Premium | N21: Morning | O21: 24 | P21: Vegetarian bistro / casual dining | Q21: English / international-facing | R21: No
A22: https://www.google.com/maps/place/IVEGAN+SUPERSHOP+BEN+THANH+-+HEALTHY+PLANT+BASED+CAFE/data=!4m7!3m6!1s0x317527178384a5e9:0x6bd0b476886d57!8m2!3d10.7716643!4d106.6950738!16s%2Fg%2F11kqq40qrz!19sChIJ6aWEgxcndTERV22IdrTQawA?authuser=0&hl=en&rclk=1 | B22: IVEGAN SUPERSHOP BEN THANH - HEALTHY PLANT BASED CAFE | C22: 4.9 | D22: 1419 | E22: ₫100–200K | F22: 0.35416667 | G22: "Delicious , cute cozy space and nice staff." | H22: 29 Lê Anh Xuân | I22: 10.771664 | J22: 106.69507 | K22: District 1 | L22: Bến Thành | M22: Medium | N22: Morning | O22: 25 | P22: Vegetarian cafe / light dining | Q22: English / international-facing | R22: Yes
A23: https://www.google.com/maps/place/Roots+Plant-based+Cafe+-+Ben+Thanh/data=!4m7!3m6!1s0x31752f2c5b5c23f9:0x37dd5beb607c8cff!8m2!3d10.7741206!4d106.6975015!16s%2Fg%2F11xcvlc9qw!19sChIJ-SNcWywvdTER_4x8YOtb3Tc?authuser=0&hl=en&rclk=1 | B23: Roots Plant-based Cafe - Ben Thanh | C23: 4.9 | D23: 1407 | E23: ₫100–200K | F23: 0.33333333 | G23: "Great in a calm stylish setting." | H23: 113-115 Lý Tự Trọng | I23: 10.774121 | J23: 106.6975 | K23: District 1 | L23: Bến Thành | M23: Medium | N23: Morning | O23: 26 | P23: Vegetarian cafe / light dining | Q23: English / international-facing | R23: Yes
A24: https://www.google.com/maps/place/Be+An+Vegetarian+Bistro/data=!4m7!3m6!1s0x31752fc59340bdeb:0xdf3513c4d4fb4ba!8m2!3d10.784419!4d106.697799!16s%2Fg%2F11kjf2bthm!19sChIJ671Ak8UvdTERurRPTTxR8w0?authuser=0&hl=en&rclk=1 | B24: Be An Vegetarian Bistro | C24: 4.8 | D24: 1365 | E24: ₫200–300K | G24: Dine-in Delivery | H24: 11B Trần Cao Vân | I24: 10.784419 | J24: 106.6978 | K24: District 1 | L24: Đa Kao | M24: Premium | N24: No data | O24: 28 | P24: Vegetarian bistro / casual dining | Q24: English / international-facing | R24: No
A25: https://www.google.com/maps/place/Be+An+Vegetarian+Bistro/data=!4m7!3m6!1s0x31752fc59340bdeb:0xdf3513c4d4fb4ba!8m2!3d10.7844192!4d106.6977993!16s%2Fg%2F11kjf2bthm!19sChIJ671Ak8UvdTERurRPTTxR8w0?authuser=0&hl=en&rclk=1 | B25: Be An Vegetarian Bistro | C25: 4.8 | D25: 1365 | E25: ₫200–300K | F25: 0.41666667 | G25: "Amazing , calming atmosphere" | H25: 11B Trần Cao Vân | I25: 10.784419 | J25: 106.6978 | K25: District 1 | L25: Đa Kao | M25: Premium | N25: Morning | O25: 27 | P25: Vegetarian bistro / casual dining | Q25: English / international-facing | R25: No
A26: https://www.google.com/maps/place/V%E1%BB%8B+Qu%C3%AA+Kitchen/data=!4m7!3m6!1s0x31752fe59e20471f:0x169be80586c609d8!8m2!3d10.7715986!4d106.6885602!16s%2Fg%2F11rg6q_gvv!19sChIJH0cgnuUvdTER2AnGhgXomxY?authuser=0&hl=en&rclk=1 | B26: Vị Quê Kitchen | C26: 4.7 | D26: 1269 | E26: ₫100–200K | F26: 0.41666667 | G26: "Delicious , amazing drinks, and great atmosphere!" | H26: 110 Sương Nguyệt Anh | I26: 10.771599 | J26: 106.68856 | K26: District 1 | L26: Bến Thành | M26: Medium | N26: Morning | O26: 29 | P26: Vegetarian bistro / casual dining | Q26: English / international-facing | R26: No
A27: https://www.google.com/maps/place/Prem+%26+Pi+Vegetarian+Bistro+-+since+2013/data=!4m7!3m6!1s0x31752f3b3c7990e9:0xccf0c5443c10be6d!8m2!3d10.786464!4d106.694317!16s%2Fg%2F11b6hqmm49!19sChIJ6ZB5PDsvdTERbb4QPETF8Mw?authuser=0&hl=en&rclk=1 | B27: Prem & Pi Vegetarian Bistro - since 2013 | C27: 4.5 | D27: 1242 | E27: ₫200–300K | F27: 0.41666667 | G27: "Beautiful atmosphere for delicious ." | H27: 187/15 Điện Biên Phủ | I27: 10.786464 | J27: 106.69432 | K27: District 1 | L27: Đa Kao | M27: Premium | N27: Morning | O27: 30 | P27: Vegetarian bistro / casual dining | Q27: English / international-facing | R27: No
A28: https://www.google.com/maps/place/Le+Corto/data=!4m7!3m6!1s0x31752f46183b600f:0x2d05f35baaca375b!8m2!3d10.7778086!4d106.7046515!16s%2Fg%2F11cms299_3!19sChIJD2A7GEYvdTERWzfKqlvzBS0?authuser=0&hl=en&rclk=1 | B28: Le Corto | C28: 4.5 | D28: 1201 | E28: ₫1,000,000+ | F28: 0.72916667 | G28: "Creative presentation, delicious ." | H28: 5D Nguyễn Siêu | I28: 10.777809 | J28: 106.70465 | K28: District 1 | L28: Bến Nghé | M28: No data | N28: Afternoon | O28: 31 | P28: Vegetarian bistro / casual dining | Q28: English / international-facing | R28: No
A29: https://www.google.com/maps/place/San+May+Cafe+%26+Vegetarian+Restaurant/data=!4m7!3m6!1s0x31752f351f00d393:0x2a4665bbd901d58f!8m2!3d10.7889806!4d106.6982583!16s%2Fg%2F1q6h_yzwz!19sChIJk9MAHzUvdTERj9UB2btlRio?authuser=0&hl=en&rclk=1 | B29: San May Cafe & Vegetarian Restaurant | C29: 4.3 | D29: 1061 | E29: ₫100–200K | F29: 0.33333333 | G29: "Delicious with lots of different and interesting options." | H29: 155 Nguyễn Văn Thủ | I29: 10.788981 | J29: 106.69826 | K29: District 1 | L29: Đa Kao | M29: Medium | N29: Morning | O29: 32 | P29: Vegetarian cafe / light dining | Q29: English / international-facing | R29: Yes
A30: https://www.google.com/maps/place/N%E1%BA%A5m+-+Vegetarian+Bistro/data=!4m7!3m6!1s0x31752ffe37d3b463:0x31b9b1ae10caf841!8m2!3d10.7888741!4d106.6916512!16s%2Fg%2F11srggl7x8!19sChIJY7TTN_4vdTERQfjKEK6xuTE?authuser=0&hl=en&rclk=1 | B30: Nấm - Vegetarian Bistro | C30: 4.9 | D30: 1025 | E30: ₫100–200K | F30: 0.41666667 | G30: "Really great , friendly staff and a calm atmosphere" | H30: 67C Đinh Công Tráng | I30: 10.788874 | J30: 106.69165 | K30: District 1 | L30: Tân Định | M30: Medium | N30: Morning | O30: 33 | P30: Vegetarian bistro / casual dining | Q30: English / international-facing | R30: No
A31: https://www.google.com/maps/place/S%C3%A0i+G%C3%B2n+Kitchen+Vina/data=!4m7!3m6!1s0x31752fa059f65bd7:0x8e9d22f08651a127!8m2!3d10.778228!4d106.6990193!16s%2Fg%2F11vz3b_sg9!19sChIJ11v2WaAvdTERJ6FRhvAinY4?authuser=0&hl=en&rclk=1 | B31: Sài Gòn Kitchen Vina | C31: 4.7 | D31: 1024 | E31: ₫100–200K | G31: "They have a great menu, good options & friendly staff." | H31: 86 Nguyễn Du | I31: 10.778228 | J31: 106.69902 | K31: District 1 | L31: Bến Thành | M31: Medium | N31: No data | O31: 34 | P31: Local Vietnamese vegetarian | Q31: Mixed local + English-facing | R31: No
A32: https://www.google.com/maps/place/7+Bridges+Craft+Beer+Taproom+%26+Restaurant+%2F+L%C3%AA+Th%C3%A1nh+T%C3%B4n/data=!4m7!3m6!1s0x31752f5b858ed635:0xf6afab1d3bbba627!8m2!3d10.7802418!4d106.7046589!16s%2Fg%2F11q26lk9hl!19sChIJNdaOhVsvdTERJ6a7Ox2rr_Y?authuser=0&hl=en&rclk=1 | B32: 7 Bridges Craft Beer Taproom & Restaurant / Lê Thánh Tôn | C32: 4.6 | D32: 954 | E32: ₫200–300K | G32: "Delicious , friendly service and fun location." | H32: 15B/12 Lê Thánh Tôn | I32: 10.780242 | J32: 106.70466 | K32: District 1 | L32: Bến Nghé | M32: Premium | N32: No data | O32: 36 | P32: Vegetarian bistro / casual dining | Q32: English / international-facing | R32: No
A33: https://www.google.com/maps/place/Tib+-+Hue+Restaurant/data=!4m7!3m6!1s0x31752f34773a47e3:0x62842bc6c1157c15!8m2!3d10.7858338!4d106.6942744!16s%2Fg%2F1vpq4c2m!19sChIJ40c6dzQvdTERFXwVwcYrhGI?authuser=0&hl=en&rclk=1 | B33: Tib - Hue Restaurant | C33: 4.3 | D33: 916 | E33: $$ | F33: 0.45833333 | G33: "Amazing place in folk style, found a delicious menu, recommend" | H33: 187 Ter Hai Bà Trưng | I33: 10.785834 | J33: 106.69427 | K33: District 1 | L33: Đa Kao | M33: No data | N33: Lunch | O33: 37 | P33: Vegetarian bistro / casual dining | Q33: English / international-facing | R33: No
A34: https://www.google.com/maps/place/La+Moi+plant-based+Restaurant/data=!4m7!3m6!1s0x31752fb36bbd2f47:0x35c6b390bd1bdfcf!8m2!3d10.778431!4d106.699046!16s%2Fg%2F11k4qvqc29!19sChIJRy-9a7MvdTERz98bvZCzxjU?authuser=0&hl=en&rclk=1 | B34: La Moi plant-based Restaurant | C34: 4.7 | D34: 910 | E34: ₫200–300K | F34: 0.33333333 | G34: "The Pad Thai was a flavor explosion, setting a high bar for cuisine." | H34: 84 Nguyễn Du | I34: 10.778431 | J34: 106.69905 | K34: District 1 | L34: Bến Thành | M34: Premium | N34: Morning | O34: 38 | P34: Modern vegan / plant-based | Q34: English / international-facing | R34: No
A35: https://www.google.com/maps/place/Li+Bai+Authentic+Cantonese+Restaurant/data=!4m7!3m6!1s0x31752f91eed42415:0xa178e41d3c672dda!8m2!3d10.7757259!4d106.703781!16s%2Fg%2F11sm70dxh6!19sChIJFSTU7pEvdTER2i1nPB3keKE?authuser=0&hl=en&rclk=1 | B35: Li Bai Authentic Cantonese Restaurant | C35: 4.8 | D35: 882 | E35: ₫1,000,000+ | F35: 0.75 | G35: "Not only the was delicious, I was surprised by the attentive staff." | H35: Sheraton Saigon Grand Opera Hotel, 88 Đồng Khởi | I35: 10.775726 | J35: 106.70378 | K35: District 1 | L35: Bến Nghé | M35: No data | N35: Night | O35: 39 | P35: Vegetarian bistro / casual dining | Q35: English / international-facing | R35: No
A36: https://www.google.com/maps/place/Bon%E2%80%99s+Vegan+Bistro+-+B%C3%A1nh+M%C3%AC+%26+Coffee/data=!4m7!3m6!1s0x31752fac15ce84d1:0xb3ae51a8927c2cb!8m2!3d10.7702529!4d106.7020348!16s%2Fg%2F11j72t29ws!19sChIJ0YTOFawvdTERy8IniRrlOgs?authuser=0&hl=en&rclk=1 | B36: Bon’s Vegan Bistro - Bánh Mì & Coffee | C36: 4.9 | D36: 834 | E36: ₫100–200K | F36: 0.33333333 | G36: "Delicious , the loveliest service and a beautiful environment." | H36: 89/8 Hàm Nghi | I36: 10.770253 | J36: 106.70203 | K36: District 1 | L36: Nguyễn Thái Bình | M36: Medium | N36: Morning | O36: 40 | P36: Quick-service / noodle / banh mi vegetarian | Q36: English / international-facing | R36: Yes
A37: https://www.google.com/maps/place/Nh%C3%A0+h%C3%A0ng+thu%E1%BA%A7n+chay+Ngon+Vegan+Dining+%26+Cafe+-+Tr%E1%BA%A7n+Cao+V%C3%A2n/data=!4m7!3m6!1s0x31752f005f2a10c3:0xe910019d74900f91!8m2!3d10.7844858!4d106.6975065!16s%2Fg%2F11yb67g06h!19sChIJwxAqXwAvdTERkQ-QdJ0BEOk?authuser=0&hl=en&rclk=1 | B37: Nhà hàng thuần chay Ngon Vegan Dining & Cafe - Trần Cao Vân | C37: 4.8 | D37: 809 | E37: ₫100–200K | F37: 0.41666667 | G37: "Great , a really cozy atmosphere, and very generous portions." | H37: 16 Trần Cao Vân | I37: 10.784486 | J37: 106.69751 | K37: District 1 | L37: Đa Kao | M37: Medium | N37: Morning | O37: 41 | P37: Vegetarian cafe / light dining | Q37: Mixed local + English-facing | R37: Yes
A38: https://www.google.com/maps/place/LuLi%E2%80%99s+Kitchen+-+District+1/data=!4m7!3m6!1s0x3175273ff56582c7:0xdd300353ed536440!8m2!3d10.7785192!4d106.6981803!16s%2Fg%2F11y1hqb5vt!19sChIJx4Jl9T8ndTERQGRT7VMDMN0?authuser=0&hl=en&rclk=1 | B38: LuLi’s Kitchen - District 1 | C38: 4.9 | D38: 755 | E38: ₫100–200K | G38: "Very accommodating for my gluten free needs too." | H38: Pasteur/182A Ward | I38: 10.778519 | J38: 106.69818 | K38: District 1 | L38: Bến Nghé | M38: Medium | N38: No data | O38: 43 | P38: Local Vietnamese vegetarian | Q38: Mixed local + English-facing | R38: No
A39: https://www.google.com/maps/place/Lim+Veggie+Bistro/data=!4m7!3m6!1s0x317529bb1656f27d:0xc74b19bde30c8bc0!8m2!3d10.7810504!4d106.7061501!16s%2Fg%2F11kb92ssq9!19sChIJffJWFrspdTERwIsM470ZS8c?authuser=0&hl=en&rclk=1 | B39: Lim Veggie Bistro | C39: 4.9 | D39: 664 | E39: ₫100–200K | F39: 0.375 | G39: "Exceptional and atmosphere." | H39: 07 Ngô Văn Năm | I39: 10.78105 | J39: 106.70615 | K39: District 1 | L39: Bến Nghé | M39: Medium | N39: Morning | O39: 44 | P39: Vegetarian bistro / casual dining | Q39: English / international-facing | R39: No
A40: https://www.google.com/maps/place/M%C3%8A+RAU+Vegetarian+-+Buffet+L%E1%BA%A9u+Rau+N%E1%BA%A5m/data=!4m7!3m6!1s0x31752f0001fe0033:0x3a0e0448b5313e8a!8m2!3d10.7871204!4d106.6960532!16s%2Fg%2F11vz620fyq!19sChIJMwD-AQAvdTERij4xtUgEDjo?authuser=0&hl=en&rclk=1 | B40: MÊ RAU Vegetarian - Buffet Lẩu Rau Nấm | C40: 4.3 | D40: 642 | E40: ₫100–200K | F40: 0.4375 | G40: "It comes with tons of veggie, tofu, and broth selection." | H40: 174 Nguyễn Văn Thủ | I40: 10.78712 | J40: 106.69605 | K40: District 1 | L40: Đa Kao | M40: Medium | N40: Morning | O40: 45 | P40: Buffet / hotpot vegetarian | Q40: English / international-facing | R40: No
A41: https://www.google.com/maps/place/Filthy+Vegan/data=!4m7!3m6!1s0x31752f666798070d:0x89f2c77331d1e65f!8m2!3d10.7649171!4d106.6947502!16s%2Fg%2F11hzyv036d!19sChIJDQeYZ2YvdTERX-bRMXPH8ok?authuser=0&hl=en&rclk=1 | B41: Filthy Vegan | C41: 4.8 | D41: 641 | E41: ₫100–200K | F41: 0.45833333 | G41: "Delicious comfort | H41: 86 Cô Bắc | I41: 10.764917 | J41: 106.69475 | K41: District 1 | L41: Cô Giang | M41: Medium | N41: Lunch | O41: 46 | P41: Modern vegan / plant-based | Q41: English / international-facing | R41: No
A42: https://www.google.com/maps/place/OM+Eatery+-+Vegetarian+%26+Vegan+Food/data=!4m7!3m6!1s0x31752f38023fcab5:0x2352c23a411e03d6!8m2!3d10.7890301!4d106.6908913!16s%2Fg%2F11vhczg2kr!19sChIJtco_AjgvdTER1gMeQTrCUiM?authuser=0&hl=en&rclk=1 | B42: OM Eatery - Vegetarian & Vegan Food | C42: 4.8 | D42: 634 | E42: ₫200–300K | F42: 0.375 | G42: "It’s both satisfying and guilt-free — a great balance of health and taste." | H42: 80 Đinh Công Tráng | I42: 10.78903 | J42: 106.69089 | K42: District 1 | L42: Tân Định | M42: Premium | N42: Morning | O42: 47 | P42: Modern vegan / plant-based | Q42: English / international-facing | R42: No
A43: https://www.google.com/maps/place/%C4%90u+%C4%90%E1%BB%A7+Xanh+%7C+Ti%E1%BB%87m+Chay+.+Vegetarian/data=!4m7!3m6!1s0x31752f8da57b3c39:0x81c6ddef64b28268!8m2!3d10.7863279!4d106.6946945!16s%2Fg%2F11qkk7rf9v!19sChIJOTx7pY0vdTERaIKyZO_dxoE?authuser=0&hl=en&rclk=1 | B43: Đu Đủ Xanh | Tiệm Chay . Vegetarian | C43: 4.8 | D43: 626 | E43: ₫200–300K | F43: 0.45833333 | G43: "Truly excellent and | H43: 178A Hai Bà Trưng | I43: 10.786328 | J43: 106.69469 | K43: District 1 | L43: Đa Kao | M43: Premium | N43: Lunch | O43: 48 | P43: Local Vietnamese vegetarian | Q43: Mixed local + English-facing | R43: No
A44: https://www.google.com/maps/place/MANA+Station+-+Ti%E1%BB%87m+%C4%82n+M%C3%B3n+Vi%E1%BB%87t/data=!4m7!3m6!1s0x31752fd3bea193bb:0x725fbe1807742206!8m2!3d10.776731!4d106.7047843!16s%2Fg%2F11thkdrbm0!19sChIJu5OhvtMvdTERBiJ0Bxi-X3I?authuser=0&hl=en&rclk=1 | B44: MANA Station - Tiệm Ăn Món Việt | C44: 4.6 | D44: 622 | E44: ₫100–200K | G44: "The Tofu here was cooked to PERFECTION!" | H44: Hai Bà Trưng/57 Ward | I44: 10.776731 | J44: 106.70478 | K44: District 1 | L44: Bến Nghé | M44: Medium | N44: No data | O44: 49 | P44: Local Vietnamese vegetarian | Q44: Mixed local + English-facing | R44: No
A45: https://www.google.com/maps/place/Hoang%E2%80%99s+Kitchen+-+Vietnamese+cuisine+%26+vegan+food+4/data=!4m7!3m6!1s0x31752f000b681f0b:0x4ac289fc569a9d84!8m2!3d10.7813151!4d106.7055893!16s%2Fg%2F11yqvldd8l!19sChIJCx9oCwAvdTERhJ2aVvyJwko?authuser=0&hl=en&rclk=1 | B45: Hoang’s Kitchen - Vietnamese cuisine & vegan food 4 | C45: 4.9 | D45: 621 | E45: ₫200–300K | F45: 0.4375 | G45: "lovely meal , very friendly and great staff !" | H45: 13/1 Lê Thánh Tôn | I45: 10.781315 | J45: 106.70559 | K45: District 1 | L45: Bến Nghé | M45: Premium | N45: Morning | O45: 50 | P45: Modern vegan / plant-based | Q45: English / international-facing | R45: No
A46: https://www.google.com/maps/place/7+Bridges+Saigon+Craft+Beer+Taproom+%26+Restaurant+%2F+%C4%90%C3%B4ng+Du/data=!4m7!3m6!1s0x31752f3c6c5bfb91:0x806606bca8cdaaf8!8m2!3d10.7765601!4d106.7049095!16s%2Fg%2F11l6zdkck9!19sChIJkftbbDwvdTER-KrNqLwGZoA?authuser=0&hl=en&rclk=1 | B46: 7 Bridges Saigon Craft Beer Taproom & Restaurant / Đông Du | C46: 4.7 | D46: 614 | E46: ₫200–300K | G46: "Sooo many different flavors, very creative." | H46: Saigon Ward, 38 Đông Du | I46: 10.77656 | J46: 106.70491 | K46: District 1 | L46: Bến Nghé | M46: Premium | N46: No data | O46: 51 | P46: Vegetarian bistro / casual dining | Q46: English / international-facing | R46: No
A47: https://www.google.com/maps/place/Atithi+Indian+Vegetarian+Restaurant/data=!4m7!3m6!1s0x31752f623b8c0c27:0x7526c3936d0827bc!8m2!3d10.7721026!4d106.6941655!16s%2Fg%2F11yqspzhpd!19sChIJJwyMO2IvdTERvCcIbZPDJnU?authuser=0&hl=en&rclk=1 | B47: Atithi Indian Vegetarian Restaurant | C47: 4.9 | D47: 611 | E47: ₫200–300K | F47: 0.33333333 | G47: "Fresh and healthy , sitting very comfortable, reasonable prices" | H47: 246 Lý Tự Trọng | I47: 10.772103 | J47: 106.69417 | K47: District 1 | L47: Phạm Ngũ Lão | M47: Premium | N47: Morning | O47: 52 | P47: Vegetarian bistro / casual dining | Q47: English / international-facing | R47: No
A48: https://www.google.com/maps/place/Bebop+Asian+Fusion+Restaurant+%26+Live+Performance/data=!4m7!3m6!1s0x31752f235128cbf7:0xfd9c5e6c405cd012!8m2!3d10.7772531!4d106.7002681!16s%2Fg%2F11ltdhfx0h!19sChIJ98soUSMvdTEREtBcQGxenP0?authuser=0&hl=en&rclk=1 | B48: Bebop Asian Fusion Restaurant & Live Performance | C48: 4.8 | D48: 549 | E48: ₫200–300K | F48: 0.70833333 | G48: "The was delicious and beautifully presented." | H48: 38 Lý Tự Trọng | I48: 10.777253 | J48: 106.70027 | K48: District 1 | L48: Bến Nghé | M48: Premium | N48: Afternoon | O48: 53 | P48: Vegetarian bistro / casual dining | Q48: English / international-facing | R48: No
A49: https://www.google.com/maps/place/M%C4%83ng%27s+Mania+Vegetarian+Restaurant/data=!4m7!3m6!1s0x31752f47bc4175ad:0x88bff037ac27b014!8m2!3d10.7753458!4d106.7029181!16s%2Fg%2F11f3vdjxcn!19sChIJrXVBvEcvdTERFLAnrDfwv4g?authuser=0&hl=en&rclk=1 | B49: Măng's Mania Vegetarian Restaurant | C49: 4.7 | D49: 507 | E49: ₫100–200K | F49: 0.4375 | G49: "I can’t say I’ve tasted better anywhere else, it’s delicious." | H49: 86 Nguyễn Huệ | I49: 10.775346 | J49: 106.70292 | K49: District 1 | L49: Bến Nghé | M49: Medium | N49: Morning | O49: 55 | P49: Vegetarian bistro / casual dining | Q49: English / international-facing | R49: No
A50: https://www.google.com/maps/place/Au+Patio+-+Brunch+%26+Wine/data=!4m7!3m6!1s0x31752f5c1be82ea1:0xb13afb0e57047e13!8m2!3d10.7798799!4d106.7029516!16s%2Fg%2F11q45gq_jn!19sChIJoS7oG1wvdTERE34EVw77OrE?authuser=0&hl=en&rclk=1 | B50: Au Patio - Brunch & Wine | C50: 4.7 | D50: 507 | E50: ₫200–300K | G50: "Chill space, healthy foods, focus on options." | H50: 31A Lý Tự Trọng | I50: 10.77988 | J50: 106.70295 | K50: District 1 | L50: Bến Nghé | M50: Premium | N50: No data | O50: 54 | P50: Vegetarian cafe / light dining | Q50: English / international-facing | R50: Yes
A51: https://www.google.com/maps/place/Nh%C3%A0+H%C3%A0ng+Thu%E1%BA%A7n+Chay+B%C3%80+X%C3%83+-+CN+Pasteur+-+Vegan+Restaurant/data=!4m7!3m6!1s0x31752fe13640cfd5:0x3e6e8f125b8c8735!8m2!3d10.778468!4d106.698772!16s%2Fg%2F11t4dy6gm0!19sChIJ1c9ANuEvdTERNYeMWxKPbj4?authuser=0&hl=en&rclk=1 | B51: Nhà Hàng Thuần Chay BÀ XÃ - CN Pasteur - Vegan Restaurant | C51: 4.3 | D51: 500 | E51: ₫100–200K | F51: 0.375 | G51: "The whole fish is an amazing experience!" | H51: 178/4 Pasteur | I51: 10.778468 | J51: 106.69877 | K51: District 1 | L51: Bến Nghé | M51: Medium | N51: Morning | O51: 56 | P51: Modern vegan / plant-based | Q51: Mixed local + English-facing | R51: No
A52: https://www.google.com/maps/place/Qu%C3%A1n+Chay+Nh%C3%A0+T%C3%B4i+Vegan/data=!4m7!3m6!1s0x31752f0633e21f63:0xfe2d2b3e975465f!8m2!3d10.7883804!4d106.6974632!16s%2Fg%2F11h1z213jn!19sChIJYx_iMwYvdTERX0Z16bPS4g8?authuser=0&hl=en&rclk=1 | B52: Quán Chay Nhà Tôi Vegan | C52: 4.3 | D52: 488 | E52: ₫1–100,000 | G52: "Really delicious noodle dish, friendly staff, reasonable prices." | H52: 124 Nguyễn Văn Thủ | I52: 10.78838 | J52: 106.69746 | K52: District 1 | L52: Đa Kao | M52: Low | N52: No data | O52: 57 | P52: Modern vegan / plant-based | Q52: Mixed local + English-facing | R52: No
A53: https://www.google.com/maps/place/Amitaba+Vegetarian+Restaurant/data=!4m7!3m6!1s0x31752f15039af52b:0xa72c4e69add2cb72!8m2!3d10.7650756!4d106.6973781!16s%2Fg%2F11f40028wt!19sChIJK_WaAxUvdTERcsvSrWlOLKc?authuser=0&hl=en&rclk=1 | B53: Amitaba Vegetarian Restaurant | C53: 4.4 | D53: 453 | E53: ₫100–200K | F53: 0.66666667 | G53: "Delicious for a great price." | H53: 40 Nguyễn Thái Học | I53: 10.765076 | J53: 106.69738 | K53: District 1 | L53: Cầu Ông Lãnh | M53: Medium | N53: Afternoon | O53: 58 | P53: Vegetarian bistro / casual dining | Q53: English / international-facing | R53: No
A54: https://www.google.com/maps/place/The+Tri%E1%BB%87u+Institute+-+Contemporary+Vietnamese+Restaurant+%26+Cocktail+Bar/data=!4m7!3m6!1s0x31752fee66731693:0xc76cdf3a36a0291e!8m2!3d10.7757948!4d106.7049791!16s%2Fg%2F11t7fbl3t0!19sChIJkxZzZu4vdTERHimgNjrfbMc?authuser=0&hl=en&rclk=1 | B54: The Triệu Institute - Contemporary Vietnamese Restaurant & Cocktail Bar | C54: 4.8 | D54: 398 | E54: ₫200–300K | F54: 0.70833333 | G54: "Every meal we ordered was a 10 out of 10. Flawless presentation and service." | H54: 10 Mạc Thị Bưởi | I54: 10.775795 | J54: 106.70498 | K54: District 1 | L54: Bến Nghé | M54: Premium | N54: Afternoon | O54: 59 | P54: Vegetarian bistro / casual dining | Q54: English / international-facing | R54: No
A55: https://www.google.com/maps/place/Chef+Thi%E1%BB%87n/data=!4m7!3m6!1s0x31752f2549e534db:0x34ffbe0fee59d02f!8m2!3d10.7773358!4d106.6999711!16s%2Fg%2F11gv16lbbw!19sChIJ2zTlSSUvdTERL9BZ7g--_zQ?authuser=0&hl=en&rclk=1 | B55: Chef Thiện | C55: 4.6 | D55: 394 | E55: ₫200–300K | F55: 0.72916667 | G55: "All were very delicious and the prices were reasonable." | H55: 158 Pasteur | I55: 10.777336 | J55: 106.69997 | K55: District 1 | L55: Bến Nghé | M55: Premium | N55: Afternoon | O55: 60 | P55: Local Vietnamese vegetarian | Q55: Mixed local + English-facing | R55: No
A56: https://www.google.com/maps/place/CHAY+GARDEN+Nguy%E1%BB%85n+Th%E1%BB%8B+Minh+Khai+-+Vegetarian+Restaurant+%26+Space/data=!4m7!3m6!1s0x31752ffb64ae97c9:0xc6fb1c069a9e660d!8m2!3d10.7851375!4d106.6999919!16s%2Fg%2F11ypknpdb2!19sChIJyZeuZPsvdTERDWaemgYc-8Y?authuser=0&hl=en&rclk=1 | B56: CHAY GARDEN Nguyễn Thị Minh Khai - Vegetarian Restaurant & Space | C56: 4.8 | D56: 393 | E56: ₫100–200K | F56: 0.4375 | G56: "Very good , kind service and nice atmosphere." | H56: 20 Nguyễn Thị Minh Khai | I56: 10.785137 | J56: 106.69999 | K56: District 1 | L56: Đa Kao | M56: Medium | N56: Morning | O56: 61 | P56: Vegetarian bistro / casual dining | Q56: Mixed local + English-facing | R56: No
A57: https://www.google.com/maps/place/Lune+Restaurant+and+Bar/data=!4m7!3m6!1s0x31752f822051a9e1:0xe414547cfa081b96!8m2!3d10.7798729!4d106.7041977!16s%2Fg%2F11stxhq_vm!19sChIJ4alRIIIvdTERlhsI-nxUFOQ?authuser=0&hl=en&rclk=1 | B57: Lune Restaurant and Bar | C57: 4.8 | D57: 375 | E57: ₫1,000,000+ | F57: 0.70833333 | G57: "The plating and the presentation were perfect and the tastes sensational." | H57: 17/14 Lê Thánh Tôn | I57: 10.779873 | J57: 106.7042 | K57: District 1 | L57: Bến Nghé | M57: No data | N57: Afternoon | O57: 62 | P57: Vegetarian bistro / casual dining | Q57: English / international-facing | R57: No
A58: https://www.google.com/maps/place/iBERICO+-+TAPAS+y+VINO+Thi+Sach/data=!4m7!3m6!1s0x31752f6f80d7230d:0x5c8fb833f95b52d0!8m2!3d10.778821!4d106.704387!16s%2Fg%2F11td0lqvyl!19sChIJDSPXgG8vdTER0FJb-TO4j1w?authuser=0&hl=en&rclk=1 | B58: iBERICO - TAPAS y VINO Thi Sach | C58: 4.7 | D58: 358 | E58: ₫200–300K | G58: "The was excellent and had ample | H58: 20A Thi Sách | I58: 10.778821 | J58: 106.70439 | K58: District 1 | L58: Bến Nghé | M58: Premium | N58: No data | O58: 63 | P58: Vegetarian bistro / casual dining | Q58: English / international-facing | R58: No
A59: https://www.google.com/maps/place/Hikari+Vegetarian+Cafe+Q1/data=!4m7!3m6!1s0x31752fa4d83e812f:0xe1b1994af5985b1e!8m2!3d10.7842945!4d106.7057539!16s%2Fg%2F11w4wcp3bn!19sChIJL4E-2KQvdTERHluY9UqZseE?authuser=0&hl=en&rclk=1 | B59: Hikari Vegetarian Cafe Q1 | C59: 4.6 | D59: 356 | E59: ₫1–100,000 | F59: 0.35416667 | G59: "The Japanese dish I ordered was delicious!" | H59: 5/47 Nguyễn Trung Ngạn | I59: 10.784294 | J59: 106.70575 | K59: District 1 | L59: Bến Nghé | M59: Low | N59: Morning | O59: 64 | P59: Vegetarian cafe / light dining | Q59: English / international-facing | R59: Yes
A60: https://www.google.com/maps/place/Le+Jardin/data=!4m7!3m6!1s0x31752f91869ef491:0x9692260637b12915!8m2!3d10.7799746!4d106.7034214!16s%2Fg%2F11vdz9w2wp!19sChIJkfSehpEvdTERFSmxNwYmkpY?authuser=0&hl=en&rclk=1 | B60: Le Jardin | C60: 4.3 | D60: 350 | E60: ₫200–300K | F60: 0.72916667 | G60: "The was tasty, nicely presented, and service was attentive throughout." | H60: 31 Thái Văn Lung | I60: 10.779975 | J60: 106.70342 | K60: District 1 | L60: Bến Nghé | M60: Premium | N60: Afternoon | O60: 65 | P60: Vegetarian bistro / casual dining | Q60: English / international-facing | R60: No
A61: https://www.google.com/maps/place/Cherry+Restaurant/data=!4m7!3m6!1s0x31752f1fbdcc0e6f:0xb771493e9e619807!8m2!3d10.77901!4d106.704562!16s%2Fg%2F11v5_27lj3!19sChIJbw7MvR8vdTERB5hhnj5Jcbc?authuser=0&hl=en&rclk=1 | B61: Cherry Restaurant | C61: 4.7 | D61: 315 | E61: ₫200–300K | G61: "Super nice and central location, big menu and options, too!" | H61: Thái Văn Lung/11B Ward | I61: 10.77901 | J61: 106.70456 | K61: District 1 | L61: Bến Nghé | M61: Premium | N61: No data | O61: 68 | P61: Vegetarian bistro / casual dining | Q61: Mixed local + English-facing | R61: No
A62: https://www.google.com/maps/place/Mustard+The+Indian+Bistro/data=!4m7!3m6!1s0x31752fc1a0d7a8ef:0xb0cad5e546d4bd1b!8m2!3d10.7787636!4d106.7027829!16s%2Fg%2F11zjlxvv9y!19sChIJ76jXoMEvdTERG73URuXVyrA?authuser=0&hl=en&rclk=1 | B62: Mustard The Indian Bistro | C62: 4.9 | D62: 295 | E62: ₫200–300K | G62: "I had the veggie momos (perfect in all regards!) and the hara kebab." | H62: 76 Hai Bà Trưng (Mặt trước), Quận 1, Hồ Chí Minh Balcony:, Mặt sau, view balcony, 62 Lê Thánh Tôn | I62: 10.778764 | J62: 106.70278 | K62: District 1 | L62: Bến Nghé | M62: Premium | N62: No data | O62: 71 | P62: Vegetarian bistro / casual dining | Q62: English / international-facing | R62: No
A63: https://www.google.com/maps/place/The+Shed/data=!4m7!3m6!1s0x31752f885a2180bd:0xefcc60c1524ca3af!8m2!3d10.7782614!4d106.6984487!16s%2Fg%2F11xmf7bzd0!19sChIJvYAhWogvdTERr6NMUsFgzO8?authuser=0&hl=en&rclk=1 | B63: The Shed | C63: 4.9 | D63: 271 | E63: ₫200–300K | G63: " is sensational with options for everyone and every family friendly." | H63: 178 Pasteur | I63: 10.778261 | J63: 106.69845 | K63: District 1 | L63: Bến Nghé | M63: Premium | N63: No data | O63: 73 | P63: Vegetarian cafe / light dining | Q63: English / international-facing | R63: Yes
A64: https://www.google.com/maps/place/Tandoor/data=!4m7!3m6!1s0x31752f05e93cef9f:0x80c92fbf53ff0f62!8m2!3d10.7799751!4d106.7043106!16s%2Fg%2F11s82xpb1c!19sChIJn-886QUvdTERYg__U78vyYA?authuser=0&hl=en&rclk=1 | B64: Tandoor | C64: 4.3 | D64: 265 | E64: ₫200–300K | F64: 0.70833333 | G64: "Each dish we tried was cooked to perfection and beautifully presented." | H64: Lê Thánh Tôn/17/10 Ward | I64: 10.779975 | J64: 106.70431 | K64: District 1 | L64: Bến Nghé | M64: Premium | N64: Afternoon | O64: 74 | P64: Vegetarian bistro / casual dining | Q64: English / international-facing | R64: No
A65: https://www.google.com/maps/place/Buffet+Chay+C%E1%BB%8F+N%E1%BB%99i+Vegetarian/data=!4m7!3m6!1s0x31752f9f959154e7:0xedb6b3f43a48a30b!8m2!3d10.7750885!4d106.7037454!16s%2Fg%2F11gr5_vr46!19sChIJ51SRlZ8vdTERC6NIOvSztu0?authuser=0&hl=en&rclk=1 | B65: Buffet Chay Cỏ Nội Vegetarian | C65: 4.6 | D65: 160 | E65: ₫200–300K | F65: 0.45833333 | G65: "Incredibly tasty Asian buffet at $8 per head!" | H65: Khách sạn Bông Sen Sài Gòn, Tầng 7, 123 Đồng Khởi | I65: 10.775089 | J65: 106.70375 | K65: District 1 | L65: Bến Nghé | M65: Premium | N65: Lunch | O65: 75 | P65: Buffet / hotpot vegetarian | Q65: Mixed local + English-facing | R65: No
A66: https://www.google.com/maps/place/Qu%C3%A1n+Chay+Li%C3%AAn+T%E1%BB%8Fa+-+Vegetarian/data=!4m7!3m6!1s0x31752f6591337af7:0x31fec20c0e25f8ee!8m2!3d10.7850596!4d106.700441!16s%2Fg%2F11w4fzfj0l!19sChIJ93ozkWUvdTER7vglDgzC_jE?authuser=0&hl=en&rclk=1 | B66: Quán Chay Liên Tỏa - Vegetarian | C66: 4.7 | D66: 133 | E66: ₫100–200K | F66: 0.41666667 | G66: "A beautiful with | H66: 17C Nguyễn Thị Minh Khai | I66: 10.78506 | J66: 106.70044 | K66: District 1 | L66: Đa Kao | M66: Medium | N66: Morning | O66: 77 | P66: Local Vietnamese vegetarian | Q66: Mixed local + English-facing | R66: No
A67: https://www.google.com/maps/place/We+Desi+Tadka+pure+vegetarian+Indian+restaurant/data=!4m7!3m6!1s0x31752fa42f902c89:0x2986500e958c8491!8m2!3d10.768231!4d106.693986!16s%2Fg%2F11wx6w9klh!19sChIJiSyQL6QvdTERkYSMlQ5Qhik?authuser=0&hl=en&rclk=1 | B67: We Desi Tadka pure vegetarian Indian restaurant | C67: 4.8 | D67: 124 | E67: ₫100–200K | G67: "Delicious , top-notch service, 👍🏻and outstanding ambiance." | H67: 185/30 Phạm Ngũ Lão | I67: 10.768231 | J67: 106.69399 | K67: District 1 | L67: Phạm Ngũ Lão | M67: Medium | N67: No data | O67: 79 | P67: Vegetarian bistro / casual dining | Q67: English / international-facing | R67: No
A68: https://www.google.com/maps/place/C%C6%A1m+Chay+Thi%E1%BB%87n+Quang+2+%28Vegetarian+restaurant%29/data=!4m7!3m6!1s0x31752fa2a1016a31:0xda1d5e0e43d45645!8m2!3d10.7838305!4d106.7053702!16s%2Fg%2F11qprvz6lb!19sChIJMWoBoaIvdTERRVbUQw5eHdo?authuser=0&hl=en&rclk=1 | B68: Cơm Chay Thiện Quang 2 (Vegetarian restaurant) | C68: 4.8 | D68: 95 | E68: ₫1–100,000 | F68: 0.41666667 | G68: "Simple with just the right balance of healthy and fried." | H68: 15 Nguyễn Trung Ngạn | I68: 10.783831 | J68: 106.70537 | K68: District 1 | L68: Bến Nghé | M68: Low | N68: Morning | O68: 81 | P68: Local Vietnamese vegetarian | Q68: Mixed local + English-facing | R68: No
A69: https://www.google.com/maps/place/Gotama+Buffet+Chay+%28Vegetarian+buffet+50k%29/data=!4m7!3m6!1s0x31752f682a188d09:0x22717d29bc8714e1!8m2!3d10.7876178!4d106.702848!16s%2Fg%2F11wr9wf3qd!19sChIJCY0YKmgvdTER4RSHvCl9cSI?authuser=0&hl=en&rclk=1 | B69: Gotama Buffet Chay (Vegetarian buffet 50k) | C69: 4.8 | D69: 26 | E69: ₫1–100,000 | G69: "Very fresh, delicious flavours & a good variety of proteins & veg & soup!" | H69: 7A Nguyễn Thị Minh Khai | I69: 10.787618 | J69: 106.70285 | K69: District 1 | L69: Bến Nghé | M69: Low | N69: No data | O69: 86 | P69: Buffet / hotpot vegetarian | Q69: Mixed local + English-facing | R69: No
A70: https://www.google.com/maps/place/Antico+Fornaio+-+Union+Square/data=!4m7!3m6!1s0x31752fd1e165ab05:0x4823ab3f43c97d0d!8m2!3d10.7763495!4d106.7023643!16s%2Fg%2F11z2yyy39q!19sChIJBatl4dEvdTERDX3JQz-rI0g?authuser=0&hl=en&rclk=1 | B70: Antico Fornaio - Union Square | C70: 4.9 | D70: 22 | E70: ₫200–300K | G70: "Great hospitality from the team and they even have a option." | H70: LL2, 171 Đồng Khởi | I70: 10.77635 | J70: 106.70236 | K70: District 1 | L70: Bến Nghé | M70: Premium | N70: No data | O70: 87 | P70: Vegetarian cafe / light dining | Q70: English / international-facing | R70: Yes
A71: https://www.google.com/maps/place/C%C3%B4+Th%E1%BA%A3o+Vegetarian+Restaurant/data=!4m7!3m6!1s0x31752f09caa62d41:0x88b3e7e94ee3307a!8m2!3d10.7849579!4d106.6989365!16s%2Fg%2F11tp6q55xm!19sChIJQS2mygkvdTERejDjTunns4g?authuser=0&hl=en&rclk=1 | B71: Cô Thảo Vegetarian Restaurant | C71: 5 | D71: 18 | H71: 37/3 Mạc Đĩnh Chi | I71: 10.784958 | J71: 106.69894 | K71: District 1 | L71: Đa Kao | M71: No data | N71: No data | O71: 88 | P71: Vegetarian bistro / casual dining | Q71: English / international-facing | R71: No
A72: https://www.google.com/maps/place/Shelley%27s+Vegetarian+Comfort+Food/data=!4m7!3m6!1s0x31752f007600a107:0x24460b087f2ac904!8m2!3d10.7750811!4d106.700503!16s%2Fg%2F11y2sf18_b!19sChIJB6EAdgAvdTERBMkqfwgLRiQ?authuser=0&hl=en&rclk=1 | B72: Shelley's Vegetarian Comfort Food | C72: 4.1 | D72: 16 | E72: ₫200–300K | F72: 0.33333333 | G72: "I came for the , the burger was delicious." | H72: 73 Pasteur | I72: 10.775081 | J72: 106.7005 | K72: District 1 | L72: Bến Nghé | M72: Premium | N72: Morning | O72: 89 | P72: Modern vegan / plant-based | Q72: English / international-facing | R72: No
A73: https://www.google.com/maps/place/Vegan+B%C3%A1nh+Mi/data=!4m7!3m6!1s0x31752f001ae6d3d3:0xb2e6e3061e0bc2ba!8m2!3d10.7862146!4d106.7011551!16s%2Fg%2F11xrdt5k2q!19sChIJ09PmGgAvdTERusILHgbj5rI?authuser=0&hl=en&rclk=1 | B73: Vegan Bánh Mi | C73: 4.9 | D73: 10 | E73: ₫1–100,000 | G73: "Great place for breakfast, lunch etc open 24 hours" | H73: 16 Nguyễn Thị Minh Khai | I73: 10.786215 | J73: 106.70116 | K73: District 1 | L73: Đa Kao | M73: Low | N73: No data | O73: 92 | P73: Modern vegan / plant-based | Q73: English / international-facing | R73: No
A74: https://www.google.com/maps/place/Hum+Central+-+Healthy+Veggies+Delights/data=!4m7!3m6!1s0x31752fef2f233813:0xa84709dc86dcbdaf!8m2!3d10.7800639!4d106.6994983!16s%2Fg%2F11n9s98s8q!19sChIJEzgjL-8vdTERr73chtwJR6g?authuser=0&hl=en&rclk=1 | B74: Hum Central - Healthy Veggies Delights | C74: 5 | D74: 2 | E74: ₫200–300K | H74: Toà nhà Viễn Thông Thành Phố, vào lối cửa 6, Đ. Nguyễn Văn Bình | I74: 10.780064 | J74: 106.6995 | K74: District 1 | L74: Bến Nghé | M74: Premium | N74: No data | O74: 95 | P74: Vegetarian bistro / casual dining | Q74: English / international-facing | R74: No
A75: https://www.google.com/maps/place/Here+%26+Now+Vegetarian+%28Restaurant+%26+coffee%29/data=!4m7!3m6!1s0x317529b04721988d:0xcf571837c81a5526!8m2!3d10.7898785!4d106.7109045!16s%2Fg%2F11fj8j6x8c!19sChIJjZghR7ApdTERJlUayDcYV88?authuser=0&hl=en&rclk=1 | B75: Here & Now Vegetarian (Restaurant & coffee) | C75: 4.3 | D75: 489 | E75: ₫100–200K | G75: "Delicious in a calm and inviting atmosphere" | H75: 74/1 Phạm Viết Chánh | I75: 10.789879 | J75: 106.7109 | K75: Binh Thanh | L75: Ward 19 | M75: Medium | N75: No data | O75: 2 | P75: Vegetarian cafe / light dining | Q75: English / international-facing | R75: Yes
A76: https://www.google.com/maps/place/Santorino+coffee+%26+veggies/data=!4m7!3m6!1s0x3175294056ebc581:0x4844703a35afacdd!8m2!3d10.7886858!4d106.7087982!16s%2Fg%2F11h37m7rc_!19sChIJgcXrVkApdTER3ayvNTpwREg?authuser=0&hl=en&rclk=1 | B76: Santorino coffee & veggies | C76: 4.7 | D76: 344 | E76: ₫100–200K | F76: 0.32291667 | G76: "Friendly staff, SO MANY options and really cute vibes inside!" | H76: 74 Nguyễn Ngọc Phương | I76: 10.788686 | J76: 106.7088 | K76: Binh Thanh | L76: Ward 19 | M76: Medium | N76: Morning | O76: 4 | P76: Vegetarian cafe / light dining | Q76: English / international-facing | R76: Yes
A77: https://www.google.com/maps/place/Tu%E1%BB%87+Minh+Vegan+Food+%26+Drinks+%7C+Qu%C3%A1n+Chay+Ngon+B%C3%ACnh+Th%E1%BA%A1nh/data=!4m7!3m6!1s0x317529007b12be85:0xdb6ab139bfcbcc1c!8m2!3d10.790118!4d106.7112413!16s%2Fg%2F11y50t524s!19sChIJhb4SewApdTERHMzLvzmxats?authuser=0&hl=en&rclk=1 | B77: Tuệ Minh Vegan Food & Drinks | Quán Chay Ngon Bình Thạnh | C77: 4.8 | D77: 333 | E77: ₫100–200K | F77: 0.4375 | G77: "Delicious , which is also tasty for people who usually like meat." | H77: 76C-76D Phạm Viết Chánh | I77: 10.790118 | J77: 106.71124 | K77: Binh Thanh | L77: Ward 19 | M77: Medium | N77: Morning | O77: 5 | P77: Modern vegan / plant-based | Q77: Mixed local + English-facing | R77: No
A78: https://www.google.com/maps/place/B%E1%BA%BFp+Chay+%26+Cafe+NH%C3%80+M%E1%BA%A4Y+D%C3%8C/data=!4m7!3m6!1s0x3175298fe06f3bbd:0xcf0b8de597c559c!8m2!3d10.795483!4d106.7101379!16s%2Fg%2F11sw0vlbpy!19sChIJvTtv4I8pdTERnFV8Wd648Aw?authuser=0&hl=en&rclk=1 | B78: Bếp Chay & Cafe NHÀ MẤY DÌ | C78: 4.5 | D78: 169 | E78: ₫100–200K | F78: 0.41666667 | G78: "Great place on the water, cool view and tasty dishes" | H78: 80 Xô Viết Nghệ Tĩnh | I78: 10.795483 | J78: 106.71014 | K78: Binh Thanh | L78: Ward 19 | M78: Medium | N78: Morning | O78: 6 | P78: Vegetarian cafe / light dining | Q78: Mixed local + English-facing | R78: Yes
A79: https://www.google.com/maps/place/Qu%C3%A1n+Chay+L%E1%BB%A5c+H%C3%B2a+-+Vegetarian+Food/data=!4m7!3m6!1s0x317529c902304233:0x36e40983a9e64800!8m2!3d10.8035694!4d106.7210512!16s%2Fg%2F11rzwqhbxd!19sChIJM0IwAskpdTERAEjmqYMJ5DY?authuser=0&hl=en&rclk=1 | B79: Quán Chay Lục Hòa - Vegetarian Food | C79: 4.5 | D79: 68 | E79: ₫1–100,000 | F79: 0.35416667 | G79: "We had a nice Vietnamese breakfast here, braised tofu, hu tori, yummm" | H79: 191 Nguyễn Văn Thương | I79: 10.803569 | J79: 106.72105 | K79: Binh Thanh | L79: Ward 22 | M79: Low | N79: Morning | O79: 9 | P79: Local Vietnamese vegetarian | Q79: Mixed local + English-facing | R79: No
A80: https://www.google.com/maps/place/GBomb+Cuisine+-+Vegan+Thu%E1%BA%A7n+Chay/data=!4m7!3m6!1s0x317529d705e9553b:0xf3d465855b494436!8m2!3d10.7888411!4d106.7150518!16s%2Fg%2F11l6rzxw03!19sChIJO1XpBdcpdTERNkRJW4Vl1PM?authuser=0&hl=en&rclk=1 | B80: GBomb Cuisine - Vegan Thuần Chay | C80: 4.6 | D80: 55 | E80: ₫1–100,000 | F80: 0.41666667 | G80: "Honestly the best Döner and Wrap that we ever had." | H80: 36 Nguyễn Hữu Cảnh | I80: 10.788841 | J80: 106.71505 | K80: Binh Thanh | L80: Ward 22 | M80: Low | N80: Morning | O80: 10 | P80: Modern vegan / plant-based | Q80: Mixed local + English-facing | R80: No
A81: https://www.google.com/maps/place/Xanh+vegan+and+vegetarian/data=!4m7!3m6!1s0x317529262821a143:0x65f789063aa8afae!8m2!3d10.7919385!4d106.7195364!16s%2Fg%2F11jgq4cmvc!19sChIJQ6EhKCYpdTERrq-oOgaJ92U?authuser=0&hl=en&rclk=1 | B81: Xanh vegan and vegetarian | C81: 4.1 | D81: 43 | E81: ₫100–200K | G81: "Very good , eco friendly packaging, generous portions and good price." | H81: hẻm 132 132/41 Nguyễn Hữu Cảnh | I81: 10.791939 | J81: 106.71954 | K81: Binh Thanh | L81: Ward 22 | M81: Medium | N81: No data | O81: 11 | P81: Modern vegan / plant-based | Q81: English / international-facing | R81: No
A82: https://www.google.com/maps/place/Healthy+Choice+-+Love.Peace.Vegan/data=!4m7!3m6!1s0x3175295eced7374f:0x5876940b742edc25!8m2!3d10.7895113!4d106.7081421!16s%2Fg%2F11rzd8pkp9!19sChIJTzfXzl4pdTERJdwudAuUdlg?authuser=0&hl=en&rclk=1 | B82: Healthy Choice - Love.Peace.Vegan | C82: 4.9 | D82: 20 | E82: ₫100–200K | G82: " is varied and delicious." | H82: 62/4 Nguyễn Ngọc Phương | I82: 10.789511 | J82: 106.70814 | K82: Binh Thanh | L82: Ward 19 | M82: Medium | N82: No data | O82: 13 | P82: Modern vegan / plant-based | Q82: English / international-facing | R82: No
A83: https://www.google.com/maps/place/L%C3%AA+An+vegetarian/data=!4m7!3m6!1s0x3175299a5b54e267:0x2c5aed119c2b2a6!8m2!3d10.7983324!4d106.7131962!16s%2Fg%2F11w427gzpj!19sChIJZ-JUW5opdTERprLCGdGuxQI?authuser=0&hl=en&rclk=1 | B83: Lê An vegetarian | C83: 5 | D83: 2 | E83: ₫100–200K | G83: Dine-in No-contact delivery | H83: Block E1 Chung cư Mỹ Đức, Xô Viết Nghệ Tĩnh | I83: 10.798332 | J83: 106.7132 | K83: Binh Thanh | L83: Ward 17 | M83: Medium | N83: No data | O83: 18 | P83: Vegetarian bistro / casual dining | Q83: English / international-facing | R83: No
A84: https://www.google.com/maps/place/Hum+Signature+-+Plant-based+fine+dining/data=!4m7!3m6!1s0x31752f309f992c8b:0x213c2b2d1ba2c2d6!8m2!3d10.7788628!4d106.6920523!16s%2Fg%2F1hg4_mb04!19sChIJiyyZnzAvdTER1sKiGy0rPCE?authuser=0&hl=en&rclk=1 | B84: Hum Signature - Plant-based fine dining | C84: 4.6 | D84: 4975 | E84: ₫200–300K | F84: 0.75 | G84: "A beautiful tranquil setting with excellent and | H84: 32 Võ Văn Tần | I84: 10.778863 | J84: 106.69205 | K84: District 3 | L84: Võ Thị Sáu | M84: Premium | N84: Night | O84: 1 | P84: Modern vegan / plant-based | Q84: English / international-facing | R84: No
A85: https://www.google.com/maps/place/CHAY+GARDEN+V%C3%B5+V%C4%83n+T%E1%BA%A7n+-+Vegetarian+Restaurant+%26+Coffee/data=!4m7!3m6!1s0x31752fff8c8f8461:0x7e220b548354ff32!8m2!3d10.7781582!4d106.69066!16s%2Fg%2F11h22hsnl5!19sChIJYYSPjP8vdTERMv9Ug1QLIn4?authuser=0&hl=en&rclk=1 | B85: CHAY GARDEN Võ Văn Tần - Vegetarian Restaurant & Coffee | C85: 4.7 | D85: 2193 | E85: ₫200–300K | F85: 0.4375 | G85: "Delicious in a clean and beautiful atmosphere." | H85: 52 Võ Văn Tần | I85: 10.778158 | J85: 106.69066 | K85: District 3 | L85: Võ Thị Sáu | M85: Premium | N85: Morning | O85: 3 | P85: Vegetarian cafe / light dining | Q85: Mixed local + English-facing | R85: Yes
A86: https://www.google.com/maps/place/V%E1%BB%8B+S%C3%A0i+G%C3%B2n+Restaurant+%26+Caf%C3%A9/data=!4m7!3m6!1s0x31752f7ab9ad1afb:0xe03b4971af3c924a!8m2!3d10.7770411!4d106.6885969!16s%2Fg%2F11vz4qxqtz!19sChIJ-xqtuXovdTERSpI8r3FJO-A?authuser=0&hl=en&rclk=1 | B86: Vị Sài Gòn Restaurant & Café | C86: 4.9 | D86: 2008 | E86: ₫100–200K | F86: 0.35416667 | G86: "The was delicious—fresh, flavorful, and beautifully presented." | H86: 254 Bis Nguyễn Đình Chiểu | I86: 10.777041 | J86: 106.6886 | K86: District 3 | L86: Võ Thị Sáu | M86: Medium | N86: Morning | O86: 4 | P86: Vegetarian cafe / light dining | Q86: English / international-facing | R86: Yes
A87: https://www.google.com/maps/place/Bong+Sung+Vegetarian+Restaurant/data=!4m7!3m6!1s0x31752f381d81fe73:0x59186104b466e0fc!8m2!3d10.7753458!4d106.6902814!16s%2Fg%2F11clytphpw!19sChIJc_6BHTgvdTER_OBmtARhGFk?authuser=0&hl=en&rclk=1 | B87: Bong Sung Vegetarian Restaurant | C87: 4.4 | D87: 1178 | E87: ₫100–200K | F87: 0.3125 | G87: "The was great and delicious, and the staff were very friendly!" | H87: 4 Bà Huyện Thanh Quan | I87: 10.775346 | J87: 106.69028 | K87: District 3 | L87: Võ Thị Sáu | M87: Medium | N87: Morning | O87: 5 | P87: Vegetarian bistro / casual dining | Q87: English / international-facing | R87: No
A88: https://www.google.com/maps/place/Nh%C3%A0+H%C3%A0ng+Thu%E1%BA%A7n+Chay+B%C3%80+X%C3%83+-+CN+Tr%C6%B0%C6%A1ng+%C4%90%E1%BB%8Bnh+-+Vegan+Restaurant/data=!4m7!3m6!1s0x31752f244e07201f:0x53563bf15a0e7a59!8m2!3d10.7787053!4d106.6885592!16s%2Fg%2F11h4d6p37q!19sChIJHyAHTiQvdTERWXoOWvE7VlM?authuser=0&hl=en&rclk=1 | B88: Nhà Hàng Thuần Chay BÀ XÃ - CN Trương Định - Vegan Restaurant | C88: 4.4 | D88: 1119 | E88: ₫100–200K | F88: 0.375 | G88: "The fish and beef were incredible too." | H88: 107K Trương Định | I88: 10.778705 | J88: 106.68856 | K88: District 3 | L88: Võ Thị Sáu | M88: Medium | N88: Morning | O88: 6 | P88: Modern vegan / plant-based | Q88: Mixed local + English-facing | R88: No
A89: https://www.google.com/maps/place/Qu%C3%A1n+chay+L%C3%A1+%7C+Vegetarian+Restaurant/data=!4m7!3m6!1s0x31752f4e4d07f6c5:0xff498675a1cc48c6!8m2!3d10.7864414!4d106.6923565!16s%2Fg%2F11sv_2sb0j!19sChIJxfYHTU4vdTERxkjMoXWGSf8?authuser=0&hl=en&rclk=1 | B89: Quán chay Lá | Vegetarian Restaurant | C89: 4.5 | D89: 662 | E89: ₫1–100,000 | F89: 0.4375 | G89: "Delicious and for an unbeatable price!!" | H89: 66/10 Phạm Ngọc Thạch | I89: 10.786441 | J89: 106.69236 | K89: District 3 | L89: Võ Thị Sáu | M89: Low | N89: Morning | O89: 8 | P89: Local Vietnamese vegetarian | Q89: Mixed local + English-facing | R89: No
A90: https://www.google.com/maps/place/Vinh+Nghiem+Vegetarian+restaurant/data=!4m7!3m6!1s0x317528d3538dd6df:0xdb1ddd14ed0cc702!8m2!3d10.7904546!4d106.6826408!16s%2Fg%2F11dx9608vv!19sChIJ39aNU9ModTERAscM7RTdHds?authuser=0&hl=en&rclk=1 | B90: Vinh Nghiem Vegetarian restaurant | C90: 4.4 | D90: 629 | E90: ₫100–200K | F90: 0.66666667 | G90: "Amazing tasty for a good price!" | H90: 339 Nam Kỳ Khởi Nghĩa | I90: 10.790455 | J90: 106.68264 | K90: District 3 | L90: Võ Thị Sáu | M90: Medium | N90: Afternoon | O90: 9 | P90: Vegetarian bistro / casual dining | Q90: English / international-facing | R90: No
A91: https://www.google.com/maps/place/T%C3%A2m+T%C3%A2m+Vegetarian+%26+Coffee/data=!4m7!3m6!1s0x31752f0039cee3fd:0x3ac1c8aab080479b!8m2!3d10.7797526!4d106.6855053!16s%2Fg%2F11y8mw3gjz!19sChIJ_ePOOQAvdTERm0eAsKrIwTo?authuser=0&hl=en&rclk=1 | B91: Tâm Tâm Vegetarian & Coffee | C91: 4.9 | D91: 420 | E91: ₫100–200K | F91: 0.41666667 | G91: "Delicious and great service" | H91: 49C Tú Xương | I91: 10.779753 | J91: 106.68551 | K91: District 3 | L91: Võ Thị Sáu | M91: Medium | N91: Morning | O91: 11 | P91: Vegetarian cafe / light dining | Q91: English / international-facing | R91: Yes
A92: https://www.google.com/maps/place/Hum+Lounge+-+Healthy+Veggies+Delights/data=!4m7!3m6!1s0x31752f78f8ad36e9:0x6b9f0dd3b56322e5!8m2!3d10.7786114!4d106.6920676!16s%2Fg%2F11vqs4_p8x!19sChIJ6Tat-HgvdTER5SJjtdMNn2s?authuser=0&hl=en&rclk=1 | B92: Hum Lounge - Healthy Veggies Delights | C92: 4.8 | D92: 314 | E92: ₫200–300K | F92: 0.41666667 | G92: "Refreshing and delicious dishes with friendly staff." | H92: 34 Võ Văn Tần | I92: 10.778611 | J92: 106.69207 | K92: District 3 | L92: Võ Thị Sáu | M92: Premium | N92: Morning | O92: 12 | P92: Vegetarian cafe / light dining | Q92: English / international-facing | R92: Yes
A93: https://www.google.com/maps/place/CHAY+TU%E1%BB%86+%C4%90%C4%82NG+QUANG+%7C+Qu%C3%A1n+Chay+G%E1%BA%A7n+%C4%90%C3%A2y+-+Qu%E1%BA%ADn+3+%7C+Vegetarian+Restaurant+near+here/data=!4m7!3m6!1s0x31752f38875e271d:0x24634d76745f0827!8m2!3d10.7900213!4d106.6794503!16s%2Fg%2F11x83jyqv0!19sChIJHSdehzgvdTERJwhfdHZNYyQ?authuser=0&hl=en&rclk=1 | B93: CHAY TUỆ ĐĂNG QUANG | Quán Chay Gần Đây - Quận 3 | Vegetarian Restaurant near here | C93: 4.9 | D93: 186 | E93: ₫1–100,000 | G93: "Delicious authentic with a friendly owner" | H93: Trần Quang Diệu | I93: 10.790021 | J93: 106.67945 | K93: District 3 | L93: Ward 14 | M93: Low | N93: No data | O93: 13 | P93: Local Vietnamese vegetarian | Q93: Mixed local + English-facing | R93: No
A94: https://www.google.com/maps/place/Chay+Xanh+-+Green+Vegan+Food+%28Veggie+Saigon%29/data=!4m7!3m6!1s0x31752f909619c2d3:0xea65839705473093!8m2!3d10.78609!4d106.671357!16s%2Fg%2F11rqcf85nb!19sChIJ08IZlpAvdTERkzBHBZeDZeo?authuser=0&hl=en&rclk=1 | B94: Chay Xanh - Green Vegan Food (Veggie Saigon) | C94: 4.5 | D94: 90 | E94: ₫1–100,000 | F94: 0.41666667 | G94: " was delicious and it had a really relaxing atmosphere." | H94: 237/40 Đ. Đỗ Thị Lời | I94: 10.78609 | J94: 106.67136 | K94: District 3 | L94: Ward 11 | M94: Low | N94: Morning | O94: 15 | P94: Modern vegan / plant-based | Q94: Mixed local + English-facing | R94: No
A95: https://www.google.com/maps/place/H%C6%B0%C6%A1ng+B%E1%BB%91n+M%C3%B9a+Coffee/data=!4m7!3m6!1s0x31752f92ee2dc7df:0x2415fa6a33541a3a!8m2!3d10.7868864!4d106.6922142!16s%2Fg%2F11kj8p4vb8!19sChIJ38ct7pIvdTEROhpUM2r6FSQ?authuser=0&hl=en&rclk=1 | B95: Hương Bốn Mùa Coffee | C95: 4.5 | D95: 69 | E95: ₫1–100,000 | G95: "The taste was incredible—I could hardly believe it was plant-based!" | H95: Đ. Trương Quyền | I95: 10.786886 | J95: 106.69221 | K95: District 3 | L95: Võ Thị Sáu | M95: Low | N95: No data | O95: 16 | P95: Vegetarian cafe / light dining | Q95: English / international-facing | R95: Yes
A96: https://www.google.com/maps/place/Vegan+Kitchen+An+Nhien+Vien/data=!4m7!3m6!1s0x31752f00203f4c53:0xc832b8014a4368ca!8m2!3d10.7757216!4d106.6747094!16s%2Fg%2F11xkn9xvrq!19sChIJU0w_IAAvdTERymhDSgG4Msg?authuser=0&hl=en&rclk=1 | B96: Vegan Kitchen An Nhien Vien | C96: 4.9 | D96: 51 | E96: ₫1–100,000 | F96: 0.41666667 | G96: "A pleasant hidden away on the back street." | H96: 392/20/64, Cao Thắng | I96: 10.775722 | J96: 106.67471 | K96: District 3 | L96: Ward 12 | M96: Low | N96: Morning | O96: 17 | P96: Modern vegan / plant-based | Q96: English / international-facing | R96: No
A97: https://www.google.com/maps/place/Vegan+Pho+Nhu+Restaurant/data=!4m7!3m6!1s0x31752f330af86531:0x389be670d1d0c33!8m2!3d10.787003!4d106.6923163!16s%2Fg%2F11h7s4ng65!19sChIJMWX4CjMvdTERMwwdDWe-iQM?authuser=0&hl=en&rclk=1 | B97: Vegan Pho Nhu Restaurant | C97: 4.5 | D97: 23 | E97: ₫1–100,000 | G97: "Very flavorful, fun, and creative dishes!" | H97: 54 Đ. Trương Quyền | I97: 10.787003 | J97: 106.69232 | K97: District 3 | L97: Võ Thị Sáu | M97: Low | N97: No data | O97: 20 | P97: Quick-service / noodle / banh mi vegetarian | Q97: English / international-facing | R97: No
A98: https://www.google.com/maps/place/Baba%27s+Kitchen+Indian+Restaurant+-+Thao+Dien/data=!4m7!3m6!1s0x3175262237da0859:0x2e8c079ba024e026!8m2!3d10.8055277!4d106.733663!16s%2Fg%2F11dyz97wlm!19sChIJWQjaNyImdTERJuAkoJsHjC4?authuser=0&hl=en&rclk=1 | B98: Baba's Kitchen Indian Restaurant - Thao Dien | C98: 4.8 | D98: 2258 | E98: ₫200–300K | F98: 0.45833333 | G98: "The menu has a great variety of options, including plenty for vegetarians." | H98: 35 Lê Văn Miến | I98: 10.805528 | J98: 106.73366 | K98: District 2 | L98: Thảo Điền | M98: Premium | N98: Lunch | O98: 1 | P98: Vegetarian bistro / casual dining | Q98: English / international-facing | R98: No
A99: https://www.google.com/maps/place/CHAY+GARDEN+Xu%C3%A2n+Th%E1%BB%A7y+-+Vegetarian+Restaurant+%26+Tea+House/data=!4m7!3m6!1s0x317527baef2e86b7:0x74d3ba96e8dbab1!8m2!3d10.8029541!4d106.7312266!16s%2Fg%2F11sttt9pwl!19sChIJt4Yu77ondTERsbqNbqk7TQc?authuser=0&hl=en&rclk=1 | B99: CHAY GARDEN Xuân Thủy - Vegetarian Restaurant & Tea House | C99: 4.8 | D99: 1644 | E99: ₫200–300K | F99: 0.4375 | G99: "delicious , good space and service, worth the experience" | H99: 52 Xuân Thủy | I99: 10.802954 | J99: 106.73123 | K99: District 2 | L99: Thảo Điền | M99: Premium | N99: Morning | O99: 2 | P99: Vegetarian cafe / light dining | Q99: Mixed local + English-facing | R99: Yes
A100: https://www.google.com/maps/place/Hum+Garden+-+Healthy+Veggies+Delights/data=!4m7!3m6!1s0x317526146200ff4b:0xe3bd3251a80b0465!8m2!3d10.8042095!4d106.7440478!16s%2Fg%2F11d_v9rggx!19sChIJS_8AYhQmdTERZQQLqFEyveM?authuser=0&hl=en&rclk=1 | B100: Hum Garden - Healthy Veggies Delights | C100: 4.6 | D100: 1504 | E100: ₫200–300K | F100: 0.41666667 | G100: "Delicious in a beautiful garden-like setting." | H100: 32 Đ. Số 10 | I100: 10.80421 | J100: 106.74405 | K100: District 2 | L100: Thảo Điền | M100: Premium | N100: Morning | O100: 3 | P100: Vegetarian cafe / light dining | Q100: English / international-facing | R100: Yes
...

Sheet Dictionary
A1: Field Name | B1: Data Type | C1: Description
A2: Link | B2: Text / URL | C2: Google Maps listing URL for each restaurant.
A3: Restaurant_name | B3: Text | C3: Cleaned restaurant name from Google Maps.
A4: Review_score | B4: Decimal number | C4: Google Maps average rating score.
A5: No_of_reviews | B5: Whole number | C5: Number of Google Maps reviews for the restaurant.
A6: Price_range | B6: Text / category | C6: Raw price range label captured from Google Maps.
A7: Open_time | B7: Time / Excel serial | C7: Opening time captured from listing, stored as Excel time fraction.
A8: Review | B8: Text | C8: Representative review snippet captured from Google Maps.
A9: Address | B9: Text | C9: Street address of the restaurant.
A10: District classification.Latitude | B10: Decimal number | C10: Latitude coordinate from the district classification process.
A11: District classification.Longitude | B11: Decimal number | C11: Longitude coordinate from the district classification process.
A12: District | B12: Category | C12: Cleaned district group used for analysis.
... A19: Cafe_options | B19: Yes/No | C19: Flag showing whether the concept includes cafe, coffee, tea, or light-dining cues.

Sheet Recommended districts
A1: District | B1: Key characteristics | C1: Suitable foreigner type | D1: Stay term
A2: District 1 | B2: CBD, tourist center, financial/corporate offices, walkable but expensive and crowded | C2: Business travelers, short-stay expats, people working in CBD | D2: Short–medium term
A3: District 2 | B3: Expat enclave, many serviced apartments, villas, cafes, restaurants, gyms, nightlife, international school | C3: Western expats, teachers, young professionals, expat families | D3: Short–long term
A4: District 3 | B4: Near District 1 but calmer, cheaper, tree-lined streets, cafes, gyms, local lifestyle | C4: Expats who want central location without District 1 chaos | D4: Medium–long term
A5: District 7 | B5: Quiet, planned, green, wide roads, malls, parks, international schools, Korean community | C5: Families, Korean expats, long-term professionals | D5: Long-term
A6: Binh Thanh | B6: Close to District 1, many condos, cafes, local food, Vinhomes/Landmark 81 area is more premium | C6: Young professionals, teachers, people wanting city access but lower cost | D6: Medium–long term

Sheet Location
A2: No of restaurant by district | D2: No of review by district | G2: Review per restaurant | P2: No of review of Top 3 restaurant | S2: Review per restaurant by ward
A4: Row Labels | B4: No of restaurant | D4: Row Labels | E4: Sum of No_of_reviews | G4: Row Labels | H4: Total district restaurant | I4: Total district review | J4: No of review per restaurant | K4: Average review per restaurant: | L4: Avg review score | M4: No of review of Top 5 restaurant | N4: % Top 5 Review | P4: Rank | Q4: (Multiple Items) | S4: District | T4: Ward | U4: No of restaurant | V4: Sum of No_of_reviews | W4: No of review per restaurant
A5: Binh Thanh | B5: 9 | D5: Binh Thanh | E5: 0.0093107707 | G5: District 1 | H5: =COUNTIF('Cleaned Table'!K:K,Location!G5) -> 73 | I5: =SUMIF('Cleaned Table'!K:K,Location!G5,'Cleaned Table'!D:D) -> 128619 | J5: =I5/H5 -> 1761.9041 | K5: =Location!I10/Location!H10 -> 1160.0993 | L5: =AVERAGEIF('Cleaned Table'!K:K,G5,'Cleaned Table'!C:C) -> 4.7054795 | M5: =_xlfn.XLOOKUP(G5,Location!$P$7:$P$11,Location!$Q$7:$Q$11) -> 55042 | N5: =M5/I5 -> 0.4279461 | S5: Binh Thanh | T5: Ward 17 | U5: =COUNTIF('Cleaned Table'!L:L,Location!T5) -> 1 | V5: =SUMIF('Cleaned Table'!L:L,Location!T5,'Cleaned Table'!D:D) -> 2 | W5: =V5/U5 -> 2
A6: District 7 | B6: 12 | D6: District 7 | E6: 0.029148887 | G6: District 2 | H6: =COUNTIF('Cleaned Table'!K:K,Location!G6) -> 33 | I6: =SUMIF('Cleaned Table'!K:K,Location!G6,'Cleaned Table'!D:D) -> 14747 | J6: =I6/H6 -> 446.87879 | K6: =$K$5 -> 1160.0993 | L6: =AVERAGEIF('Cleaned Table'!K:K,G6,'Cleaned Table'!C:C) -> 4.7272727 | M6: =_xlfn.XLOOKUP(G6,Location!$P$7:$P$11,Location!$Q$7:$Q$11) -> 6625 | N6: =M6/I6 -> 0.44924391 | P6: District | Q6: Sum of No_of_reviews | T6: Ward 19 | U6: =COUNTIF('Cleaned Table'!L:L,Location!T6) -> 5 | V6: =SUMIF('Cleaned Table'!L:L,Location!T6,'Cleaned Table'!D:D) -> 1355 | W6: =V6/U6 -> 271
A7: District 3 | B7: 14 | D7: District 3 | E7: 0.085080759 | G7: District 3 | H7: =COUNTIF('Cleaned Table'!K:K,Location!G7) -> 14 | I7: =SUMIF('Cleaned Table'!K:K,Location!G7,'Cleaned Table'!D:D) -> 13917 | J7: =I7/H7 -> 994.07143 | K7: =$K$5 -> 1160.0993 | L7: =AVERAGEIF('Cleaned Table'!K:K,G7,'Cleaned Table'!C:C) -> 4.6357143 | M7: =_xlfn.XLOOKUP(G7,Location!$P$7:$P$11,Location!$Q$7:$Q$11) -> 10354 | N7: =M7/I7 -> 0.74398218 | P7: Binh Thanh | Q7: 1166 | T7: Ward 22 | U7: =COUNTIF('Cleaned Table'!L:L,Location!T7) -> 3 | V7: =SUMIF('Cleaned Table'!L:L,Location!T7,'Cleaned Table'!D:D) -> 166 | W7: =V7/U7 -> 55.333333
A8: District 2 | B8: 33 | D8: District 2 | E8: 0.090154915 | G8: District 7 | H8: =COUNTIF('Cleaned Table'!K:K,Location!G8) -> 12 | I8: =SUMIF('Cleaned Table'!K:K,Location!G8,'Cleaned Table'!D:D) -> 4768 | J8: =I8/H8 -> 397.33333 | K8: =$K$5 -> 1160.0993 | L8: =AVERAGEIF('Cleaned Table'!K:K,G8,'Cleaned Table'!C:C) -> 4.7083333 | M8: =_xlfn.XLOOKUP(G8,Location!$P$7:$P$11,Location!$Q$7:$Q$11) -> 3270 | N8: =M8/I8 -> 0.68582215 | P8: District 1 | Q8: 55042 | S8: District 1 | T8: Bến Nghé | U8: =COUNTIF('Cleaned Table'!L:L,Location!T8) -> 40 | V8: =SUMIF('Cleaned Table'!L:L,Location!T8,'Cleaned Table'!D:D) -> 45173 | W8: =V8/U8 -> 1129.325
A9: District 1 | B9: 73 | D9: District 1 | E9: 0.78630467 | G9: Binh Thanh | H9: =COUNTIF('Cleaned Table'!K:K,Location!G9) -> 9 | I9: =SUMIF('Cleaned Table'!K:K,Location!G9,'Cleaned Table'!D:D) -> 1523 | J9: =I9/H9 -> 169.22222 | K9: =$K$5 -> 1160.0993 | L9: =AVERAGEIF('Cleaned Table'!K:K,G9,'Cleaned Table'!C:C) -> 4.6 | M9: =_xlfn.XLOOKUP(G9,Location!$P$7:$P$11,Location!$Q$7:$Q$11) -> 1166 | N9: =M9/I9 -> 0.76559422 | P9: District 3 | Q9: 10354 | T9: Bến Thành | U9: =COUNTIF('Cleaned Table'!L:L,Location!T9) -> 7 | V9: =SUMIF('Cleaned Table'!L:L,Location!T9,'Cleaned Table'!D:D) -> 37723 | W9: =V9/U9 -> 5389
A10: Grand Total | B10: 141 | D10: Grand Total | E10: 1 | H10: =SUM(Location!H5:H9) -> 141 | I10: =SUM(Location!I5:I9) -> 163574 | P10: District 7 | Q10: 3270 | T10: Cầu Ông Lãnh | U10: =COUNTIF('Cleaned Table'!L:L,Location!T10) -> 1 | V10: =SUMIF('Cleaned Table'!L:L,Location!T10,'Cleaned Table'!D:D) -> 453 | W10: =V10/U10 -> 453
P11: District 2 | Q11: 6625 | T11: Cô Giang | U11: =COUNTIF('Cleaned Table'!L:L,Location!T11) -> 1 | V11: =SUMIF('Cleaned Table'!L:L,Location!T11,'Cleaned Table'!D:D) -> 641 | W11: =V11/U11 -> 641
T12: Đa Kao | U12: =COUNTIF('Cleaned Table'!L:L,Location!T12) -> 13 | V12: =SUMIF('Cleaned Table'!L:L,Location!T12,'Cleaned Table'!D:D) -> 9068 | W12: =V12/U12 -> 697.53846
T13: Nguyễn Thái Bình | U13: =COUNTIF('Cleaned Table'!L:L,Location!T13) -> 2 | V13: =SUMIF('Cleaned Table'!L:L,Location!T13,'Cleaned Table'!D:D) -> 3054 | W13: =V13/U13 -> 1527
T14: Phạm Ngũ Lão | U14: =COUNTIF('Cleaned Table'!L:L,Location!T14) -> 6 | V14: =SUMIF('Cleaned Table'!L:L,Location!T14,'Cleaned Table'!D:D) -> 28493 | W14: =V14/U14 -> 4748.8333
T15: Tân Định | U15: =COUNTIF('Cleaned Table'!L:L,Location!T15) -> 3 | V15: =SUMIF('Cleaned Table'!L:L,Location!T15,'Cleaned Table'!D:D) -> 4014 | W15: =V15/U15 -> 1338
S16: District 3 | T16: Võ Thị Sáu | U16: =COUNTIF('Cleaned Table'!L:L,Location!T16) -> 11 | V16: =SUMIF('Cleaned Table'!L:L,Location!T16,'Cleaned Table'!D:D) -> 13590 | W16: =V16/U16 -> 1235.4545
T17: Ward 14 | U17: =COUNTIF('Cleaned Table'!L:L,Location!T17) -> 1 | V17: =SUMIF('Cleaned Table'!L:L,Location!T17,'Cleaned Table'!D:D) -> 186 | W17: =V17/U17 -> 186
T18: Ward 11 | U18: =COUNTIF('Cleaned Table'!L:L,Location!T18) -> 1 | V18: =SUMIF('Cleaned Table'!L:L,Location!T18,'Cleaned Table'!D:D) -> 90 | W18: =V18/U18 -> 90
T19: Ward 12 | U19: =COUNTIF('Cleaned Table'!L:L,Location!T19) -> 1 | V19: =SUMIF('Cleaned Table'!L:L,Location!T19,'Cleaned Table'!D:D) -> 51 | W19: =V19/U19 -> 51
S20: District 7 | T20: Tân Hưng | U20: =COUNTIF('Cleaned Table'!L:L,Location!T20) -> 1 | V20: =SUMIF('Cleaned Table'!L:L,Location!T20,'Cleaned Table'!D:D) -> 686 | W20: =V20/U20 -> 686
T21: Tân Phong | U21: =COUNTIF('Cleaned Table'!L:L,Location!T21) -> 4 | V21: =SUMIF('Cleaned Table'!L:L,Location!T21,'Cleaned Table'!D:D) -> 2048 | W21: =V21/U21 -> 512
T22: Tân Phú | U22: =COUNTIF('Cleaned Table'!L:L,Location!T22) -> 5 | V22: =SUMIF('Cleaned Table'!L:L,Location!T22,'Cleaned Table'!D:D) -> 1608 | W22: =V22/U22 -> 321.6
T23: Tân Quy | U23: =COUNTIF('Cleaned Table'!L:L,Location!T23) -> 2 | V23: =SUMIF('Cleaned Table'!L:L,Location!T23,'Cleaned Table'!D:D) -> 426 | W23: =V23/U23 -> 213
S24: District 2 | T24: Thảo Điền | U24: =COUNTIF('Cleaned Table'!L:L,Location!T24) -> 28 | V24: =SUMIF('Cleaned Table'!L:L,Location!T24,'Cleaned Table'!D:D) -> 13473 | W24: =V24/U24 -> 481.17857
T25: An Phú | U25: =COUNTIF('Cleaned Table'!L:L,Location!T25) -> 5 | V25: =SUMIF('Cleaned Table'!L:L,Location!T25,'Cleaned Table'!D:D) -> 1274 | W25: =V25/U25 -> 254.8

Sheet Price Gap
A2: Price range share | F2: Popular price range by district | K2: Popular price range
B4: Column Labels | F4: Count of Restaurant_name | G4: Column Labels | K4: Count of Restaurant_name | M4: Price_bucket
A5: Values | B5: Low | C5: Medium | D5: Premium | F5: Row Labels | G5: Low | H5: Medium | I5: Premium | K5: District | L5: Ward | M5: Low | N5: Medium | O5: Premium | P5: No data
A6: # Listing | B6: 0.15151515 | C6: 0.47727273 | D6: 0.37121212 | F6: District 1 | G6: 6 | H6: 28 | I6: 34 | K6: Binh Thanh | L6: Ward 17 | N6: 1
A7: # Reviews | B7: 0.033984766 | C7: 0.61612248 | D7: 0.34989276 | F7: District 2 | G7: 6 | H7: 17 | I7: 10 | K7: Binh Thanh | L7: Ward 19 | N7: 5
F8: District 3 | G8: 6 | H8: 5 | I8: 3 | K8: Binh Thanh | L8: Ward 22 | M8: 2 | N8: 1
F9: District 7 | H9: 6 | I9: 2 | K9: Binh Thanh Total | M9: 2 | N9: 7
F10: Binh Thanh | G10: 2 | H10: 7 | K10: District 1 | L10: Bến Nghé | M10: 3 | N10: 9 | O10: 25 | P10: 3
F11: Grand Total | G11: 20 | H11: 63 | I11: 49 | K11: District 1 | L11: Bến Thành | N11: 6 | O11: 1
K12: District 1 | L12: Cầu Ông Lãnh | N12: 1
K13: District 1 | L13: Cô Giang | N13: 1
K14: District 1 | L14: Đa Kao | M14: 2 | N14: 5 | O14: 4 | P14: 2
K15: District 1 | L15: Nguyễn Thái Bình | N15: 1 | O15: 1
K16: District 1 | L16: Phạm Ngũ Lão | M16: 1 | N16: 3 | O16: 2
K17: District 1 | L17: Tân Định | N17: 2 | O17: 1
K18: District 1 Total | M18: 6 | N18: 28 | O18: 34 | P18: 5
K19: District 3 | L19: Võ Thị Sáu | M19: 3 | N19: 5 | O19: 3
K20: District 3 | L20: Ward 14 | M20: 1
K21: District 3 | L21: Ward 11 | M21: 1
K22: District 3 | L22: Ward 12 | M22: 1
K23: District 3 Total | M23: 6 | N23: 5 | O23: 3
K24: District 7 | L24: Tân Hưng | N24: 1
K25: District 7 | L25: Tân Phong | N25: 2 | P25: 2
K26: District 7 | L26: Tân Phú | N26: 2 | O26: 2 | P26: 1
K27: District 7 | L27: Tân Quy | N27: 1 | P27: 1
K28: District 7 Total | N28: 6 | O28: 2 | P28: 4
K29: District 2 | L29: An Phú | M29: 3 | N29: 2
K30: District 2 | L30: Thảo Điền | M30: 3 | N30: 15 | O30: 10
K31: District 2 Total | M31: 6 | N31: 17 | O31: 10
K32: Grand Total | M32: 20 | N32: 63 | O32: 49 | P32: 9

Sheet Concept
A2: # Restaurant & review by restaurant concept | E2: # restaurant per district by restaurant concept | M2: Price range distribution by restaurant concept | S2: Restaurant quantity by café options | V2: Restaurant quantity breakdown by café options & district | Z2: Price range distribution by Café options
A4: Row Labels | B4: % reviews | C4: % restaurant | E4: Count of Restaurant_name | F4: Column Labels | M4: Count of Restaurant_name | N4: Column Labels | S4: Row Labels | T4: Count of Restaurant_name | V4: Count of Restaurant_name | W4: Column Labels | Z4: Count of Restaurant_name | AA4: Column Labels
A5: Buffet / hotpot vegetarian | B5: 0.0050619292 | C5: 0.021276596 | E5: Row Labels | F5: District 1 | G5: District 2 | H5: District 3 | I5: District 7 | J5: Binh Thanh | K5: Grand Total | M5: Row Labels | N5: Low | O5: Medium | P5: Premium | Q5: Grand Total | S5: No | T5: 0.78014184 | V5: Row Labels | W5: No | X5: Yes | Z5: Row Labels | AA5: No | AB5: Yes | AC5: Grand Total
A6: Quick-service / noodle / banh mi vegetarian | B6: 0.11900424 | C6: 0.042553191 | E6: Vegetarian bistro / casual dining | F6: 37 | G6: 12 | H6: 2 | I6: 3 | J6: 1 | K6: 55 | M6: Vegetarian bistro / casual dining | N6: 5 | O6: 19 | P6: 24 | Q6: 48 | S6: Yes | T6: 0.21985816 | V6: Binh Thanh | W6: 0.66666667 | X6: 0.33333333 | Z6: Low | AA6: 17 | AB6: 3 | AC6: 20
A7: Local Vietnamese vegetarian | B7: 0.048320638 | C7: 0.092198582 | E7: Modern vegan / plant-based | F7: 12 | G7: 9 | H7: 4 | I7: 5 | J7: 4 | K7: 34 | M7: Modern vegan / plant-based | N7: 5 | O7: 20 | P7: 9 | Q7: 34 | S7: Grand Total | T7: 1 | V7: District 1 | W7: 0.8630137 | X7: 0.1369863 | Z7: Medium | AA7: 48 | AB7: 15 | AC7: 63
A8: Vegetarian cafe / light dining | B8: 0.13207478 | C8: 0.21276596 | E8: Vegetarian cafe / light dining | F8: 9 | G8: 9 | H8: 5 | I8: 4 | J8: 3 | K8: 30 | M8: Vegetarian cafe / light dining | N8: 3 | O8: 14 | P8: 11 | Q8: 28 | V8: District 3 | W8: 0.64285714 | X8: 0.35714286 | Z8: Premium | AA8: 38 | AB8: 11 | AC8: 49
A9: Modern vegan / plant-based | B9: 0.25407461 | C9: 0.24113475 | E9: Local Vietnamese vegetarian | F9: 8 | G9: 2 | H9: 2 | J9: 1 | K9: 13 | M9: Local Vietnamese vegetarian | N9: 4 | O9: 5 | P9: 4 | Q9: 13 | V9: District 7 | W9: 0.66666667 | X9: 0.33333333 | Z9: No data | AA9: 7 | AB9: 2 | AC9: 9
A10: Vegetarian bistro / casual dining | B10: 0.4414638 | C10: 0.39007092 | E10: Quick-service / noodle / banh mi vegetarian | F10: 4 | G10: 1 | H10: 1 | K10: 6 | M10: Quick-service / noodle / banh mi vegetarian | N10: 2 | O10: 4 | Q10: 6 | V10: District 2 | W10: 0.72727273 | X10: 0.27272727 | Z10: Grand Total | AA10: 110 | AB10: 31 | AC10: 141
A11: Grand Total | B11: 1 | C11: 1 | E11: Buffet / hotpot vegetarian | F11: 3 | K11: 3 | M11: Buffet / hotpot vegetarian | N11: 1 | O11: 1 | P11: 1 | Q11: 3 | V11: Grand Total | W11: 0.78014184 | X11: 0.21985816
E12: Grand Total | F12: 73 | G12: 33 | H12: 14 | I12: 12 | J12: 9 | K12: 141 | M12: Grand Total | N12: 20 | O12: 63 | P12: 49 | Q12: 132

Sheet Others
A2: Rating vs Number of Reviews | D2: Restaurant Opening hour | G2: Opening hour by district | N2: Restaurant Opening hour
A4: Mean | B4: =AVERAGE('Cleaned Table'!C:C) -> 4.6971631 | D4: Row Labels | E4: Count of Restaurant_name | G4: Count of Restaurant_name | H4: Column Labels | N4: Row Labels | O4: Count of Restaurant_name
A5: Mode | B5: =_xlfn.MODE.SNGL('Cleaned Table'!C:C) -> 4.9 | D5: Morning | E5: 0.77011494 | G5: Row Labels | H5: Morning | I5: Lunch | J5: Afternoon | K5: Night | L5: No data | N5: Morning | O5: 0.77011494
A6: Weighted rating | B6: =SUMPRODUCT(A9:A18,B9:B18)/SUM(B9:B18) -> 4.7153032 | D6: Lunch | E6: 0.091954023 | G6: Binh Thanh | H6: 5 | L6: 4 | N6: 0.3125 | O6: 0.011494253
D7: Afternoon | E7: 0.11494253 | G7: District 1 | H7: 30 | I7: 4 | J7: 8 | K7: 1 | L7: 30 | N7: 0.32291667 | O7: 0.011494253
A8: Row Labels | B8: Sum of No_of_reviews | D8: Night | E8: 0.022988506 | G8: District 3 | H8: 9 | J8: 1 | K8: 1 | L8: 3 | N8: 0.33333333 | O8: 0.11494253
A9: 4.1 | B9: 59 | D9: Grand Total | E9: 1 | G9: District 7 | H9: 5 | I9: 1 | L9: 6 | N9: 0.35416667 | O9: 0.08045977
A10: 4.2 | B10: 276 | G10: District 2 | H10: 18 | I10: 3 | J10: 1 | L10: 11 | N10: 0.375 | O10: 0.17241379
A11: 4.3 | B11: 17300 | G11: Grand Total | H11: 67 | I11: 8 | J11: 10 | K11: 2 | L11: 54 | N11: 0.39583333 | O11: 0.022988506
A12: 4.4 | B12: 8656 | N12: 0.41666667 | O12: 0.25287356
A13: 4.5 | B13: 13614 | N13: 0.4375 | O13: 0.10344828
A14: 4.6 | B14: 17307 | N14: Lunch | O14: 0.091954023
A15: 4.7 | B15: 11244 | N15: 0.45833333 | O15: 0.08045977
A16: 4.8 | B16: 23928 | N16: 0.47916667 | O16: 0.011494253
A17: 4.9 | B17: 71029 | N17: Afternoon | O17: 0.11494253
A18: 5 | B18: 161 | N18: 0.66666667 | O18: 0.022988506
A19: Grand Total | B19: 163574 | N19: 0.6875 | O19: 0.011494253
N20: 0.70833333 | O20: 0.045977011
N21: 0.72916667 | O21: 0.034482759
N22: Night | O22: 0.022988506
N23: 0.75 | O23: 0.022988506
N24: Grand Total | O24: 1

Sheet Scoring model_input
A1: Scenario | B1: District | C1: Restaurants in bucket | D1: Reviews in bucket | E1: Reviews / restaurant | F1: Price restaurant share | G1: Price review share | H1: Opportunity gap | I1: Customer segment fit | J1: Restaurant concept fit | K1: Notes
A2: Medium | B2: District 1 | C2: =COUNTIFS('Cleaned Table'!$M:$M,'Scoring model_input'!A2,'Cleaned Table'!$K:$K,'Scoring model_input'!B2) -> 28 | D2: =SUMIFS('Cleaned Table'!$D:$D,'Cleaned Table'!$M:$M,'Scoring model_input'!A2,'Cleaned Table'!$K:$K,'Scoring model_input'!B2) -> 83237 | E2: =D2/C2 -> 2972.75 | F2: =C2/COUNTIF('Cleaned Table'!$K:$K,'Scoring model_input'!B2) -> 0.38356164 | G2: =D2/SUMIF('Cleaned Table'!$K:$K,'Scoring model_input'!B2,'Cleaned Table'!$D:$D) -> 0.64715944 | H2: =G2-F2 -> 0.2635978 | I2: 90 | J2: 80 | K2: Strongest proven demand; use only with clear differentiation due to competition.
A3: Medium | B3: District 2 | C3: =COUNTIFS('Cleaned Table'!$M:$M,'Scoring model_input'!A3,'Cleaned Table'!$K:$K,'Scoring model_input'!B3) -> 17 | D3: =SUMIFS('Cleaned Table'!$D:$D,'Cleaned Table'!$M:$M,'Scoring model_input'!A3,'Cleaned Table'!$K:$K,'Scoring model_input'!B3) -> 5357 | E3: =D3/C3 -> 315.11765 | F3: =C3/COUNTIF('Cleaned Table'!$K:$K,'Scoring model_input'!B3) -> 0.51515152 | G3: =D3/SUMIF('Cleaned Table'!$K:$K,'Scoring model_input'!B3,'Cleaned Table'!$D:$D) -> 0.36326032 | H3: =G3-F3 -> -0.15189119 | I3: 95 | J3: 70 | K3: Good expat fit; medium bistro/cafe can work if positioned more lifestyle-led.
A4: Medium | B4: District 3 | C4: =COUNTIFS('Cleaned Table'!$M:$M,'Scoring model_input'!A4,'Cleaned Table'!$K:$K,'Scoring model_input'!B4) -> 5 | D4: =SUMIFS('Cleaned Table'!$D:$D,'Cleaned Table'!$M:$M,'Scoring model_input'!A4,'Cleaned Table'!$K:$K,'Scoring model_input'!B4) -> 5354 | E4: =D4/C4 -> 1070.8 | F4: =C4/COUNTIF('Cleaned Table'!$K:$K,'Scoring model_input'!B4) -> 0.35714286 | G4: =D4/SUMIF('Cleaned Table'!$K:$K,'Scoring model_input'!B4,'Cleaned Table'!$D:$D) -> 0.38470935 | H4: =G4-F4 -> 0.027566491 | I4: 75 | J4: 90 | K4: Smaller base but strong reviews per restaurant; good alternative to D1.
A5: Medium | B5: District 7 | C5: =COUNTIFS('Cleaned Table'!$M:$M,'Scoring model_input'!A5,'Cleaned Table'!$K:$K,'Scoring model_input'!B5) -> 6 | D5: =SUMIFS('Cleaned Table'!$D:$D,'Cleaned Table'!$M:$M,'Scoring model_input'!A5,'Cleaned Table'!$K:$K,'Scoring model_input'!B5) -> 2605 | E5: =D5/C5 -> 434.16667 | F5: =C5/COUNTIF('Cleaned Table'!$K:$K,'Scoring model_input'!B5) -> 0.5 | G5: =D5/SUMIF('Cleaned Table'!$K:$K,'Scoring model_input'!B5,'Cleaned Table'!$D:$D) -> 0.54635067 | H5: =G5-F5 -> 0.046350671 | I5: 85 | J5: 90 | K5: Balanced medium opportunity for expat/residential market.
A6: Medium | B6: Binh Thanh | C6: =COUNTIFS('Cleaned Table'!$M:$M,'Scoring model_input'!A6,'Cleaned Table'!$K:$K,'Scoring model_input'!B6) -> 7 | D6: =SUMIFS('Cleaned Table'!$D:$D,'Cleaned Table'!$M:$M,'Scoring model_input'!A6,'Cleaned Table'!$K:$K,'Scoring model_input'!B6) -> 1400 | E6: =D6/C6 -> 200 | F6: =C6/COUNTIF('Cleaned Table'!$K:$K,'Scoring model_input'!B6) -> 0.77777778 | G6: =D6/SUMIF('Cleaned Table'!$K:$K,'Scoring model_input'!B6,'Cleaned Table'!$D:$D) -> 0.91923835 | H6: =G6-F6 -> 0.14146057 | I6: 80 | J6: 85 | K6: Medium price is the dominant bucket, but total demand is still smaller.
A7: Premium | B7: District 1 | C7: =COUNTIFS('Cleaned Table'!$M:$M,'Scoring model_input'!A7,'Cleaned Table'!$K:$K,'Scoring model_input'!B7) -> 34 | D7: =SUMIFS('Cleaned Table'!$D:$D,'Cleaned Table'!$M:$M,'Scoring model_input'!A7,'Cleaned Table'!$K:$K,'Scoring model_input'!B7) -> 39415 | E7: =D7/C7 -> 1159.2647 | F7: =C7/COUNTIF('Cleaned Table'!$K:$K,'Scoring model_input'!B7) -> 0.46575342 | G7: =D7/SUMIF('Cleaned Table'!$K:$K,'Scoring model_input'!B7,'Cleaned Table'!$D:$D) -> 0.30644773 | H7: =G7-F7 -> -0.1593057 | I7: 90 | J7: 92 | K7: Premium demand exists, but market is highly saturated.
A8: Premium | B8: District 2 | C8: =COUNTIFS('Cleaned Table'!$M:$M,'Scoring model_input'!A8,'Cleaned Table'!$K:$K,'Scoring model_input'!B8) -> 10 | D8: =SUMIFS('Cleaned Table'!$D:$D,'Cleaned Table'!$M:$M,'Scoring model_input'!A8,'Cleaned Table'!$K:$K,'Scoring model_input'!B8) -> 7766 | E8: =D8/C8 -> 776.6 | F8: =C8/COUNTIF('Cleaned Table'!$K:$K,'Scoring model_input'!B8) -> 0.3030303 | G8: =D8/SUMIF('Cleaned Table'!$K:$K,'Scoring model_input'!B8,'Cleaned Table'!$D:$D) -> 0.52661558 | H8: =G8-F8 -> 0.22358528 | I8: 95 | J8: 92 | K8: Best premium white-space: strong expat fit and review share exceeds supply share.
A9: Premium | B9: District 3 | C9: =COUNTIFS('Cleaned Table'!$M:$M,'Scoring model_input'!A9,'Cleaned Table'!$K:$K,'Scoring model_input'!B9) -> 3 | D9: =SUMIFS('Cleaned Table'!$D:$D,'Cleaned Table'!$M:$M,'Scoring model_input'!A9,'Cleaned Table'!$K:$K,'Scoring model_input'!B9) -> 7482 | E9: =D9/C9 -> 2494 | F9: =C9/COUNTIF('Cleaned Table'!$K:$K,'Scoring model_input'!B9) -> 0.21428571 | G9: =D9/SUMIF('Cleaned Table'!$K:$K,'Scoring model_input'!B9,'Cleaned Table'!$D:$D) -> 0.53761587 | H9: =G9-F9 -> 0.32333015 | I9: 55 | J9: 85 | K9: Strong premium review signal, but lower strategic fit than D2 for expat/lifestyle positioning; validate audience mix and site economics.
A10: Premium | B10: District 7 | C10: =COUNTIFS('Cleaned Table'!$M:$M,'Scoring model_input'!A10,'Cleaned Table'!$K:$K,'Scoring model_input'!B10) -> 2 | D10: =SUMIFS('Cleaned Table'!$D:$D,'Cleaned Table'!$M:$M,'Scoring model_input'!A10,'Cleaned Table'!$K:$K,'Scoring model_input'!B10) -> 964 | E10: =D10/C10 -> 482 | F10: =C10/COUNTIF('Cleaned Table'!$K:$K,'Scoring model_input'!B10) -> 0.16666667 | G10: =D10/SUMIF('Cleaned Table'!$K:$K,'Scoring model_input'!B10,'Cleaned Table'!$D:$D) -> 0.20218121 | H10: =G10-F10 -> 0.035514541 | I10: 75 | J10: 80 | K10: Lower competition, but premium demand is smaller than D1/D2/D3.
A11: Premium | B11: Binh Thanh | C11: =COUNTIFS('Cleaned Table'!$M:$M,'Scoring model_input'!A11,'Cleaned Table'!$K:$K,'Scoring model_input'!B11) -> 0 | D11: =SUMIFS('Cleaned Table'!$D:$D,'Cleaned Table'!$M:$M,'Scoring model_input'!A11,'Cleaned Table'!$K:$K,'Scoring model_input'!B11) -> 0 | E11: =IFERROR(D11/C11,0) -> 0 | F11: =C11/COUNTIF('Cleaned Table'!$K:$K,'Scoring model_input'!B11) -> 0 | G11: =D11/SUMIF('Cleaned Table'!$K:$K,'Scoring model_input'!B11,'Cleaned Table'!$D:$D) -> 0 | H11: =G11-F11 -> 0 | I11: 65 | J11: 30 | K11: No premium evidence in current shortlist.

Sheet Scoring model_result
A1: Scenario | B1: District | C1: Restaurants | D1: Reviews | E1: Reviews / restaurant | F1: Price restaurant share | G1: Price review share | H1: Opportunity gap | I1: Demand Strength Score | J1: Competition Intensity | K1: Gap Score | L1: Price Fit Score | M1: Customer Fit Score | N1: Concept Fit Score | O1: Final Weighted Score | P1: Rank | Q1: Interpretation
A2: ='[1]Input Metrics'!A10 -> Medium | B2: ='[1]Input Metrics'!B10 -> District 1 | C2: ='Scoring model_input'!C2 -> 28 | D2: ='Scoring model_input'!D2 -> 83237 | E2: ='Scoring model_input'!E2 -> 2972.75 | F2: ='Scoring model_input'!F2 -> 0.38356164 | G2: ='Scoring model_input'!G2 -> 0.64715944 | H2: ='Scoring model_input'!H2 -> 0.2635978 | I2: =IFERROR(0.6*((D2-_xlfn.MINIFS($D$2:$D$11,$A$2:$A$11,$A2))/(_xlfn.MAXIFS($D$2:$D$11,$A$2:$A$11,$A2)-_xlfn.MINIFS($D$2:$D$11,$A$2:$A$11,$A2))*100)+0.4*((E2-_xlfn.MINIFS($E$2:$E$11,$A$2:$A$11,$A2))/(_xlfn.MAXIFS($E$2:$E$11,$A$2:$A$11,$A2)-_xlfn.MINIFS($E$2:$E$11,$A$2:$A$11,$A2))*100),0) -> 100 | J2: =IF(D2=0,45,IFERROR((_xlfn.MAXIFS($C$2:$C$11,$A$2:$A$11,$A2)-C2)/(_xlfn.MAXIFS($C$2:$C$11,$A$2:$A$11,$A2)-_xlfn.MINIFS($C$2:$C$11,$A$2:$A$11,$A2))*100,0)) -> 0 | K2: =IFERROR((H2-_xlfn.MINIFS($H$2:$H$11,$A$2:$A$11,$A2))/(_xlfn.MAXIFS($H$2:$H$11,$A$2:$A$11,$A2)-_xlfn.MINIFS($H$2:$H$11,$A$2:$A$11,$A2))*100,0) -> 100 | L2: =((F2*100)*0.5)+((G2*100)*0.5) -> 51.536054 | M2: ='[1]Input Metrics'!J10 -> 90 | N2: ='[1]Input Metrics'!K10 -> 80 | O2: =I2*VLOOKUP($A2,$A$16:$G$18,2,FALSE)+J2*VLOOKUP($A2,$A$16:$G$18,3,FALSE)+K2*VLOOKUP($A2,$A$16:$G$18,4,FALSE)+L2*VLOOKUP($A2,$A$16:$G$18,5,FALSE)+M2*VLOOKUP($A2,$A$16:$G$18,6,FALSE)+N2*VLOOKUP($A2,$A$16:$G$18,7,FALSE) -> 74.230408 | P2: =COUNTIFS($A$2:$A$11,A2,$O$2:$O$11,">"&O2)+1 -> 1 | Q2: =IF(P2=1,"Best option for "&A2,IF(P2=2,"Runner-up","Lower priority / validate further")) -> Best option for Medium
A3: ='[1]Input Metrics'!A11 -> Medium | B3: ='[1]Input Metrics'!B11 -> District 2 | C3: ='Scoring model_input'!C3 -> 17 | D3: ='Scoring model_input'!D3 -> 5357 | E3: ='Scoring model_input'!E3 -> 315.11765 | F3: ='Scoring model_input'!F3 -> 0.51515152 | G3: ='Scoring model_input'!G3 -> 0.36326032 | H3: ='Scoring model_input'!H3 -> -0.15189119 | I3: =IFERROR(0.6*((D3-_xlfn.MINIFS($D$2:$D$11,$A$2:$A$11,$A3))/(_xlfn.MAXIFS($D$2:$D$11,$A$2:$A$11,$A3)-_xlfn.MINIFS($D$2:$D$11,$A$2:$A$11,$A3))*100)+0.4*((E3-_xlfn.MINIFS($E$2:$E$11,$A$2:$A$11,$A3))/(_xlfn.MAXIFS($E$2:$E$11,$A$2:$A$11,$A3)-_xlfn.MINIFS($E$2:$E$11,$A$2:$A$11,$A3))*100),0) -> 4.5618327 | J3: =IF(D3=0,45,IFERROR((_xlfn.MAXIFS($C$2:$C$11,$A$2:$A$11,$A3)-C3)/(_xlfn.MAXIFS($C$2:$C$11,$A$2:$A$11,$A3)-_xlfn.MINIFS($C$2:$C$11,$A$2:$A$11,$A3))*100,0)) -> 47.826087 | K3: =IFERROR((H3-_xlfn.MINIFS($H$2:$H$11,$A$2:$A$11,$A3))/(_xlfn.MAXIFS($H$2:$H$11,$A$2:$A$11,$A3)-_xlfn.MINIFS($H$2:$H$11,$A$2:$A$11,$A3))*100,0) -> 0 | L3: =((F3*100)*0.5)+((G3*100)*0.5) -> 43.920592 | M3: ='[1]Input Metrics'!J11 -> 95 | N3: ='[1]Input Metrics'!K11 -> 70 | O3: =I3*VLOOKUP($A3,$A$16:$G$18,2,FALSE)+J3*VLOOKUP($A3,$A$16:$G$18,3,FALSE)+K3*VLOOKUP($A3,$A$16:$G$18,4,FALSE)+L3*VLOOKUP($A3,$A$16:$G$18,5,FALSE)+M3*VLOOKUP($A3,$A$16:$G$18,6,FALSE)+N3*VLOOKUP($A3,$A$16:$G$18,7,FALSE) -> 36.15246 | P3: =COUNTIFS($A$2:$A$11,A3,$O$2:$O$11,">"&O3)+1 -> 5 | Q3: =IF(P3=1,"Best option for "&A3,IF(P3=2,"Runner-up","Lower priority / validate further")) -> Lower priority / validate further
A4: ='[1]Input Metrics'!A12 -> Medium | B4: ='[1]Input Metrics'!B12 -> District 3 | C4: ='Scoring model_input'!C4 -> 5 | D4: ='Scoring model_input'!D4 -> 5354 | E4: ='Scoring model_input'!E4 -> 1070.8 | F4: ='Scoring model_input'!F4 -> 0.35714286 | G4: ='Scoring model_input'!G4 -> 0.38470935 | H4: ='Scoring model_input'!H4 -> 0.027566491 | I4: =IFERROR(0.6*((D4-_xlfn.MINIFS($D$2:$D$11,$A$2:$A$11,$A4))/(_xlfn.MAXIFS($D$2:$D$11,$A$2:$A$11,$A4)-_xlfn.MINIFS($D$2:$D$11,$A$2:$A$11,$A4))*100)+0.4*((E4-_xlfn.MINIFS($E$2:$E$11,$A$2:$A$11,$A4))/(_xlfn.MAXIFS($E$2:$E$11,$A$2:$A$11,$A4)-_xlfn.MINIFS($E$2:$E$11,$A$2:$A$11,$A4))*100),0) -> 15.461191 | J4: =IF(D4=0,45,IFERROR((_xlfn.MAXIFS($C$2:$C$11,$A$2:$A$11,$A4)-C4)/(_xlfn.MAXIFS($C$2:$C$11,$A$2:$A$11,$A4)-_xlfn.MINIFS($C$2:$C$11,$A$2:$A$11,$A4))*100,0)) -> 100 | K4: =IFERROR((H4-_xlfn.MINIFS($H$2:$H$11,$A$2:$A$11,$A4))/(_xlfn.MAXIFS($H$2:$H$11,$A$2:$A$11,$A4)-_xlfn.MINIFS($H$2:$H$11,$A$2:$A$11,$A4))*100,0) -> 43.191923 | L4: =((F4*100)*0.5)+((G4*100)*0.5) -> 37.09261 | M4: ='[1]Input Metrics'!J12 -> 75 | N4: ='[1]Input Metrics'!K12 -> 90 | O4: =I4*VLOOKUP($A4,$A$16:$G$18,2,FALSE)+J4*VLOOKUP($A4,$A$16:$G$18,3,FALSE)+K4*VLOOKUP($A4,$A$16:$G$18,4,FALSE)+L4*VLOOKUP($A4,$A$16:$G$18,5,FALSE)+M4*VLOOKUP($A4,$A$16:$G$18,6,FALSE)+N4*VLOOKUP($A4,$A$16:$G$18,7,FALSE) -> 53.317574 | P4: =COUNTIFS($A$2:$A$11,A4,$O$2:$O$11,">"&O4)+1 -> 4 | Q4: =IF(P4=1,"Best option for "&A4,IF(P4=2,"Runner-up","Lower priority / validate further")) -> Lower priority / validate further
A5: ='[1]Input Metrics'!A13 -> Medium | B5: ='[1]Input Metrics'!B13 -> District 7 | C5: ='Scoring model_input'!C5 -> 6 | D5: ='Scoring model_input'!D5 -> 2605 | E5: ='Scoring model_input'!E5 -> 434.16667 | F5: ='Scoring model_input'!F5 -> 0.5 | G5: ='Scoring model_input'!G5 -> 0.54635067 | H5: ='Scoring model_input'!H5 -> 0.046350671 | I5: =IFERROR(0.6*((D5-_xlfn.MINIFS($D$2:$D$11,$A$2:$A$11,$A5))/(_xlfn.MAXIFS($D$2:$D$11,$A$2:$A$11,$A5)-_xlfn.MINIFS($D$2:$D$11,$A$2:$A$11,$A5))*100)+0.4*((E5-_xlfn.MINIFS($E$2:$E$11,$A$2:$A$11,$A5))/(_xlfn.MAXIFS($E$2:$E$11,$A$2:$A$11,$A5)-_xlfn.MINIFS($E$2:$E$11,$A$2:$A$11,$A5))*100),0) -> 4.2615779 | J5: =IF(D5=0,45,IFERROR((_xlfn.MAXIFS($C$2:$C$11,$A$2:$A$11,$A5)-C5)/(_xlfn.MAXIFS($C$2:$C$11,$A$2:$A$11,$A5)-_xlfn.MINIFS($C$2:$C$11,$A$2:$A$11,$A5))*100,0)) -> 95.652174 | K5: =IFERROR((H5-_xlfn.MINIFS($H$2:$H$11,$A$2:$A$11,$A5))/(_xlfn.MAXIFS($H$2:$H$11,$A$2:$A$11,$A5)-_xlfn.MINIFS($H$2:$H$11,$A$2:$A$11,$A5))*100,0) -> 47.712904 | L5: =((F5*100)*0.5)+((G5*100)*0.5) -> 52.317534 | M5: ='[1]Input Metrics'!J13 -> 85 | N5: ='[1]Input Metrics'!K13 -> 90 | O5: =I5*VLOOKUP($A5,$A$16:$G$18,2,FALSE)+J5*VLOOKUP($A5,$A$16:$G$18,3,FALSE)+K5*VLOOKUP($A5,$A$16:$G$18,4,FALSE)+L5*VLOOKUP($A5,$A$16:$G$18,5,FALSE)+M5*VLOOKUP($A5,$A$16:$G$18,6,FALSE)+N5*VLOOKUP($A5,$A$16:$G$18,7,FALSE) -> 54.553431 | P5: =COUNTIFS($A$2:$A$11,A5,$O$2:$O$11,">"&O5)+1 -> 3 | Q5: =IF(P5=1,"Best option for "&A5,IF(P5=2,"Runner-up","Lower priority / validate further")) -> Lower priority / validate further
A6: ='[1]Input Metrics'!A14 -> Medium | B6: ='[1]Input Metrics'!B14 -> Binh Thanh | C6: ='Scoring model_input'!C6 -> 7 | D6: ='Scoring model_input'!D6 -> 1400 | E6: ='Scoring model_input'!E6 -> 200 | F6: ='Scoring model_input'!F6 -> 0.77777778 | G6: ='Scoring model_input'!G6 -> 0.91923835 | H6: ='Scoring model_input'!H6 -> 0.14146057 | I6: =IFERROR(0.6*((D6-_xlfn.MINIFS($D$2:$D$11,$A$2:$A$11,$A6))/(_xlfn.MAXIFS($D$2:$D$11,$A$2:$A$11,$A6)-_xlfn.MINIFS($D$2:$D$11,$A$2:$A$11,$A6))*100)+0.4*((E6-_xlfn.MINIFS($E$2:$E$11,$A$2:$A$11,$A6))/(_xlfn.MAXIFS($E$2:$E$11,$A$2:$A$11,$A6)-_xlfn.MINIFS($E$2:$E$11,$A$2:$A$11,$A6))*100),0) -> 0 | J6: =IF(D6=0,45,IFERROR((_xlfn.MAXIFS($C$2:$C$11,$A$2:$A$11,$A6)-C6)/(_xlfn.MAXIFS($C$2:$C$11,$A$2:$A$11,$A6)-_xlfn.MINIFS($C$2:$C$11,$A$2:$A$11,$A6))*100,0)) -> 91.304348 | K6: =IFERROR((H6-_xlfn.MINIFS($H$2:$H$11,$A$2:$A$11,$A6))/(_xlfn.MAXIFS($H$2:$H$11,$A$2:$A$11,$A6)-_xlfn.MINIFS($H$2:$H$11,$A$2:$A$11,$A6))*100,0) -> 70.603979 | L6: =((F6*100)*0.5)+((G6*100)*0.5) -> 84.850806 | M6: ='[1]Input Metrics'!J14 -> 80 | N6: ='[1]Input Metrics'!K14 -> 85 | O6: =I6*VLOOKUP($A6,$A$16:$G$18,2,FALSE)+J6*VLOOKUP($A6,$A$16:$G$18,3,FALSE)+K6*VLOOKUP($A6,$A$16:$G$18,4,FALSE)+L6*VLOOKUP($A6,$A$16:$G$18,5,FALSE)+M6*VLOOKUP($A6,$A$16:$G$18,6,FALSE)+N6*VLOOKUP($A6,$A$16:$G$18,7,FALSE) -> 61.044069 | P6: =COUNTIFS($A$2:$A$11,A6,$O$2:$O$11,">"&O6)+1 -> 2 | Q6: =IF(P6=1,"Best option for "&A6,IF(P6=2,"Runner-up","Lower priority / validate further")) -> Runner-up
A7: ='[1]Input Metrics'!A15 -> Premium | B7: ='[1]Input Metrics'!B15 -> District 1 | C7: ='Scoring model_input'!C7 -> 34 | D7: ='Scoring model_input'!D7 -> 39415 | E7: ='Scoring model_input'!E7 -> 1159.2647 | F7: ='Scoring model_input'!F7 -> 0.46575342 | G7: ='Scoring model_input'!G7 -> 0.30644773 | H7: ='Scoring model_input'!H7 -> -0.1593057 | I7: =IFERROR(0.6*((D7-_xlfn.MINIFS($D$2:$D$11,$A$2:$A$11,$A7))/(_xlfn.MAXIFS($D$2:$D$11,$A$2:$A$11,$A7)-_xlfn.MINIFS($D$2:$D$11,$A$2:$A$11,$A7))*100)+0.4*((E7-_xlfn.MINIFS($E$2:$E$11,$A$2:$A$11,$A7))/(_xlfn.MAXIFS($E$2:$E$11,$A$2:$A$11,$A7)-_xlfn.MINIFS($E$2:$E$11,$A$2:$A$11,$A7))*100),0) -> 78.592858 | J7: =IF(D7=0,45,IFERROR((_xlfn.MAXIFS($C$2:$C$11,$A$2:$A$11,$A7)-C7)/(_xlfn.MAXIFS($C$2:$C$11,$A$2:$A$11,$A7)-_xlfn.MINIFS($C$2:$C$11,$A$2:$A$11,$A7))*100,0)) -> 0 | K7: =IFERROR((H7-_xlfn.MINIFS($H$2:$H$11,$A$2:$A$11,$A7))/(_xlfn.MAXIFS($H$2:$H$11,$A$2:$A$11,$A7)-_xlfn.MINIFS($H$2:$H$11,$A$2:$A$11,$A7))*100,0) -> 0 | L7: =((F7*100)*0.5)+((G7*100)*0.5) -> 38.610058 | M7: ='[1]Input Metrics'!J15 -> 90 | N7: ='[1]Input Metrics'!K15 -> 92 | O7: =I7*VLOOKUP($A7,$A$16:$G$18,2,FALSE)+J7*VLOOKUP($A7,$A$16:$G$18,3,FALSE)+K7*VLOOKUP($A7,$A$16:$G$18,4,FALSE)+L7*VLOOKUP($A7,$A$16:$G$18,5,FALSE)+M7*VLOOKUP($A7,$A$16:$G$18,6,FALSE)+N7*VLOOKUP($A7,$A$16:$G$18,7,FALSE) -> 55.140583 | P7: =COUNTIFS($A$2:$A$11,A7,$O$2:$O$11,">"&O7)+1 -> 3 | Q7: =IF(P7=1,"Best option for "&A7,IF(P7=2,"Runner-up","Lower priority / validate further")) -> Lower priority / validate further
A8: ='[1]Input Metrics'!A16 -> Premium | B8: ='[1]Input Metrics'!B16 -> District 2 | C8: ='Scoring model_input'!C8 -> 10 | D8: ='Scoring model_input'!D8 -> 7766 | E8: ='Scoring model_input'!E8 -> 776.6 | F8: ='Scoring model_input'!F8 -> 0.3030303 | G8: ='Scoring model_input'!G8 -> 0.52661558 | H8: ='Scoring model_input'!H8 -> 0.22358528 | I8: =IFERROR(0.6*((D8-_xlfn.MINIFS($D$2:$D$11,$A$2:$A$11,$A8))/(_xlfn.MAXIFS($D$2:$D$11,$A$2:$A$11,$A8)-_xlfn.MINIFS($D$2:$D$11,$A$2:$A$11,$A8))*100)+0.4*((E8-_xlfn.MINIFS($E$2:$E$11,$A$2:$A$11,$A8))/(_xlfn.MAXIFS($E$2:$E$11,$A$2:$A$11,$A8)-_xlfn.MINIFS($E$2:$E$11,$A$2:$A$11,$A8))*100),0) -> 24.277388 | J8: =IF(D8=0,45,IFERROR((_xlfn.MAXIFS($C$2:$C$11,$A$2:$A$11,$A8)-C8)/(_xlfn.MAXIFS($C$2:$C$11,$A$2:$A$11,$A8)-_xlfn.MINIFS($C$2:$C$11,$A$2:$A$11,$A8))*100,0)) -> 70.588235 | K8: =IFERROR((H8-_xlfn.MINIFS($H$2:$H$11,$A$2:$A$11,$A8))/(_xlfn.MAXIFS($H$2:$H$11,$A$2:$A$11,$A8)-_xlfn.MINIFS($H$2:$H$11,$A$2:$A$11,$A8))*100,0) -> 79.333307 | L8: =((F8*100)*0.5)+((G8*100)*0.5) -> 41.482294 | M8: ='[1]Input Metrics'!J16 -> 95 | N8: ='[1]Input Metrics'!K16 -> 92 | O8: =I8*VLOOKUP($A8,$A$16:$G$18,2,FALSE)+J8*VLOOKUP($A8,$A$16:$G$18,3,FALSE)+K8*VLOOKUP($A8,$A$16:$G$18,4,FALSE)+L8*VLOOKUP($A8,$A$16:$G$18,5,FALSE)+M8*VLOOKUP($A8,$A$16:$G$18,6,FALSE)+N8*VLOOKUP($A8,$A$16:$G$18,7,FALSE) -> 65.49801 | P8: =COUNTIFS($A$2:$A$11,A8,$O$2:$O$11,">"&O8)+1 -> 1 | Q8: =IF(P8=1,"Best option for "&A8,IF(P8=2,"Runner-up","Lower priority / validate further")) -> Best option for Premium
A9: ='[1]Input Metrics'!A17 -> Premium | B9: ='[1]Input Metrics'!B17 -> District 3 | C9: ='Scoring model_input'!C9 -> 3 | D9: ='Scoring model_input'!D9 -> 7482 | E9: ='Scoring model_input'!E9 -> 2494 | F9: ='Scoring model_input'!F9 -> 0.21428571 | G9: ='Scoring model_input'!G9 -> 0.53761587 | H9: ='Scoring model_input'!H9 -> 0.32333015 | I9: =IFERROR(0.6*((D9-_xlfn.MINIFS($D$2:$D$11,$A$2:$A$11,$A9))/(_xlfn.MAXIFS($D$2:$D$11,$A$2:$A$11,$A9)-_xlfn.MINIFS($D$2:$D$11,$A$2:$A$11,$A9))*100)+0.4*((E9-_xlfn.MINIFS($E$2:$E$11,$A$2:$A$11,$A9))/(_xlfn.MAXIFS($E$2:$E$11,$A$2:$A$11,$A9)-_xlfn.MINIFS($E$2:$E$11,$A$2:$A$11,$A9))*100),0) -> 51.389572 | J9: =IF(D9=0,45,IFERROR((_xlfn.MAXIFS($C$2:$C$11,$A$2:$A$11,$A9)-C9)/(_xlfn.MAXIFS($C$2:$C$11,$A$2:$A$11,$A9)-_xlfn.MINIFS($C$2:$C$11,$A$2:$A$11,$A9))*100,0)) -> 91.176471 | K9: =IFERROR((H9-_xlfn.MINIFS($H$2:$H$11,$A$2:$A$11,$A9))/(_xlfn.MAXIFS($H$2:$H$11,$A$2:$A$11,$A9)-_xlfn.MINIFS($H$2:$H$11,$A$2:$A$11,$A9))*100,0) -> 100 | L9: =((F9*100)*0.5)+((G9*100)*0.5) -> 37.595079 | M9: ='[1]Input Metrics'!J17 -> 55 | N9: ='[1]Input Metrics'!K17 -> 85 | O9: =I9*VLOOKUP($A9,$A$16:$G$18,2,FALSE)+J9*VLOOKUP($A9,$A$16:$G$18,3,FALSE)+K9*VLOOKUP($A9,$A$16:$G$18,4,FALSE)+L9*VLOOKUP($A9,$A$16:$G$18,5,FALSE)+M9*VLOOKUP($A9,$A$16:$G$18,6,FALSE)+N9*VLOOKUP($A9,$A$16:$G$18,7,FALSE) -> 64.605754 | P9: =COUNTIFS($A$2:$A$11,A9,$O$2:$O$11,">"&O9)+1 -> 2 | Q9: =IF(P9=1,"Best option for "&A9,IF(P9=2,"Runner-up","Lower priority / validate further")) -> Runner-up
A10: ='[1]Input Metrics'!A18 -> Premium | B10: ='[1]Input Metrics'!B18 -> District 7 | C10: ='Scoring model_input'!C10 -> 2 | D10: ='Scoring model_input'!D10 -> 964 | E10: ='Scoring model_input'!E10 -> 482 | F10: ='Scoring model_input'!F10 -> 0.16666667 | G10: ='Scoring model_input'!G10 -> 0.20218121 | H10: ='Scoring model_input'!H10 -> 0.035514541 | I10: =IFERROR(0.6*((D10-_xlfn.MINIFS($D$2:$D$11,$A$2:$A$11,$A10))/(_xlfn.MAXIFS($D$2:$D$11,$A$2:$A$11,$A10)-_xlfn.MINIFS($D$2:$D$11,$A$2:$A$11,$A10))*100)+0.4*((E10-_xlfn.MINIFS($E$2:$E$11,$A$2:$A$11,$A10))/(_xlfn.MAXIFS($E$2:$E$11,$A$2:$A$11,$A10)-_xlfn.MINIFS($E$2:$E$11,$A$2:$A$11,$A10))*100),0) -> 9.198015 | J10: =IF(D10=0,45,IFERROR((_xlfn.MAXIFS($C$2:$C$11,$A$2:$A$11,$A10)-C10)/(_xlfn.MAXIFS($C$2:$C$11,$A$2:$A$11,$A10)-_xlfn.MINIFS($C$2:$C$11,$A$2:$A$11,$A10))*100,0)) -> 94.117647 | K10: =IFERROR((H10-_xlfn.MINIFS($H$2:$H$11,$A$2:$A$11,$A10))/(_xlfn.MAXIFS($H$2:$H$11,$A$2:$A$11,$A10)-_xlfn.MINIFS($H$2:$H$11,$A$2:$A$11,$A10))*100,0) -> 40.365887 | L10: =((F10*100)*0.5)+((G10*100)*0.5) -> 18.442394 | M10: ='[1]Input Metrics'!J18 -> 75 | N10: ='[1]Input Metrics'!K18 -> 80 | O10: =I10*VLOOKUP($A10,$A$16:$G$18,2,FALSE)+J10*VLOOKUP($A10,$A$16:$G$18,3,FALSE)+K10*VLOOKUP($A10,$A$16:$G$18,4,FALSE)+L10*VLOOKUP($A10,$A$16:$G$18,5,FALSE)+M10*VLOOKUP($A10,$A$16:$G$18,6,FALSE)+N10*VLOOKUP($A10,$A$16:$G$18,7,FALSE) -> 45.057141 | P10: =COUNTIFS($A$2:$A$11,A10,$O$2:$O$11,">"&O10)+1 -> 4 | Q10: =IF(P10=1,"Best option for "&A10,IF(P10=2,"Runner-up","Lower priority / validate further")) -> Lower priority / validate further
A11: ='[1]Input Metrics'!A19 -> Premium | B11: ='[1]Input Metrics'!B19 -> Binh Thanh | C11: ='Scoring model_input'!C11 -> 0 | D11: ='Scoring model_input'!D11 -> 0 | E11: ='Scoring model_input'!E11 -> 0 | F11: ='Scoring model_input'!F11 -> 0 | G11: ='Scoring model_input'!G11 -> 0 | H11: ='Scoring model_input'!H11 -> 0 | I11: =IFERROR(0.6*((D11-_xlfn.MINIFS($D$2:$D$11,$A$2:$A$11,$A11))/(_xlfn.MAXIFS($D$2:$D$11,$A$2:$A$11,$A11)-_xlfn.MINIFS($D$2:$D$11,$A$2:$A$11,$A11))*100)+0.4*((E11-_xlfn.MINIFS($E$2:$E$11,$A$2:$A$11,$A11))/(_xlfn.MAXIFS($E$2:$E$11,$A$2:$A$11,$A11)-_xlfn.MINIFS($E$2:$E$11,$A$2:$A$11,$A11))*100),0) -> 0 | J11: =IF(D11=0,45,IFERROR((_xlfn.MAXIFS($C$2:$C$11,$A$2:$A$11,$A11)-C11)/(_xlfn.MAXIFS($C$2:$C$11,$A$2:$A$11,$A11)-_xlfn.MINIFS($C$2:$C$11,$A$2:$A$11,$A11))*100,0)) -> 45 | K11: =IFERROR((H11-_xlfn.MINIFS($H$2:$H$11,$A$2:$A$11,$A11))/(_xlfn.MAXIFS($H$2:$H$11,$A$2:$A$11,$A11)-_xlfn.MINIFS($H$2:$H$11,$A$2:$A$11,$A11))*100,0) -> 33.007432 | L11: =((F11*100)*0.5)+((G11*100)*0.5) -> 0 | M11: ='[1]Input Metrics'!J19 -> 65 | N11: ='[1]Input Metrics'!K19 -> 30 | O11: =I11*VLOOKUP($A11,$A$16:$G$18,2,FALSE)+J11*VLOOKUP($A11,$A$16:$G$18,3,FALSE)+K11*VLOOKUP($A11,$A$16:$G$18,4,FALSE)+L11*VLOOKUP($A11,$A$16:$G$18,5,FALSE)+M11*VLOOKUP($A11,$A$16:$G$18,6,FALSE)+N11*VLOOKUP($A11,$A$16:$G$18,7,FALSE) -> 28.101486 | P11: =COUNTIFS($A$2:$A$11,A11,$O$2:$O$11,">"&O11)+1 -> 5 | Q11: =IF(P11=1,"Best option for "&A11,IF(P11=2,"Runner-up","Lower priority / validate further")) -> Lower priority / validate further
A15: Scenario | B15: Demand Strength | C15: Competition Intensity | D15: Demand-to-Competition Gap | E15: Price Bucket Fit | F15: Customer Segment Fit | G15: Restaurant Model Fit | H15: Weight Check
A16: Low | B16: 0.2 | C16: 0.2 | D16: 0.2 | E16: 0.2 | F16: 0.1 | G16: 0.1 | H16: =SUM(B16:G16) -> 1
A17: Medium | B17: 0.25 | C17: 0.15 | D17: 0.2 | E17: 0.15 | F17: 0.15 | G17: 0.1 | H17: =SUM(B17:G17) -> 1
A18: Premium | B18: 0.2 | C18: 0.05 | D18: 0.2 | E18: 0.2 | F18: 0.25 | G18: 0.1 | H18: =SUM(B18:G18) -> 1

Sheet Dist  Binh Thanh
A1: hfpxzc href | B1: qBF1Pd | C1: MW4etd | D1: UY7F9 | E1: AJB7ye | F1: AJB7ye 2 | G1: W4Efsd | H1: W4Efsd 2 | I1: W4Efsd 3 | J1: W4Efsd 4 | K1: W4Efsd 5 | L1: FQ2IWe src | M1: Jn12ke src | N1: ah5Ghc | O1: ah5Ghc 2 | P1: ah5Ghc 3
A2: https://www.google.com/maps/place/Tu%E1%BB%87+Minh+Vegan+Food+%26+Drinks+%7C+Qu%C3%A1n+Chay+Ngon+B%C3%ACnh+Th%E1%BA%A1nh/data=!4m7!3m6!1s0x317529007b12be85:0xdb6ab139bfcbcc1c!8m2!3d10.790118!4d106.7112413!16s%2Fg%2F11y50t524s!19sChIJhb4SewApdTERHMzLvzmxats?authuser=0&hl=en&rclk=1 | B2: Tuệ Minh Vegan Food & Drinks | Quán Chay Ngon Bình Thạnh | C2: 4.8 | D2: -333 | E2: · | F2: ₫100–200K | G2: Restaurant | H2: · | I2: 76C-76D Phạm Viết Chánh | J2: Closed | K2: · Opens 10:30 AM | L2: https://lh3.googleusercontent.com/gps-cs-s/APNQkAGITNJYyo1b5q_RsZJQLBFrsUvNnUlt0LTq5vdMdLyiyhz4AxlBlCwuw2UFWsOanRNuYWI3euieP7uoMTVid-5uXVLsZjhZHyuH0e7XndKVmX5FSVIBk1K-11VPcH6kUeXXeMiIFjcU-IcC=w163-h92-k-no | M2: https://ssl.gstatic.com/local/servicebusiness/default_user.png | N2: "Delicious | O2: vegan food | P2: , which is also tasty for people who usually like meat."
A3: https://www.google.com/maps/place/Santorino+coffee+%26+veggies/data=!4m7!3m6!1s0x3175294056ebc581:0x4844703a35afacdd!8m2!3d10.7886858!4d106.7087982!16s%2Fg%2F11h37m7rc_!19sChIJgcXrVkApdTER3ayvNTpwREg?authuser=0&hl=en&rclk=1 | B3: Santorino coffee & veggies | C3: 4.7 | D3: -344 | E3: · | F3: ₫100–200K | G3: Vegan | H3: · | I3: · | J3: Opens soon | K3: · 7:45 AM | L3: https://lh3.googleusercontent.com/gps-cs-s/APNQkAETTMMMK3UYj5S-Io9Xhl1JO4uoAG1hztHqxCRsf1xMFVcTffbCDguMYhbuXtsE2Z3Rp7Tu29jqfYIOQkvc_zkzvru9hOiC1aFnSL3ldtOwpYLc-du65xB-bNQP_iC9ZI_4ODo=w122-h92-k-no | M3: https://ssl.gstatic.com/local/servicebusiness/default_user.png | N3: "Friendly staff, SO MANY | O3: vegan | P3: options and really cute vibes inside!"
A4: https://www.google.com/maps/place/B%E1%BA%BFp+Chay+%26+Cafe+NH%C3%80+M%E1%BA%A4Y+D%C3%8C/data=!4m7!3m6!1s0x3175298fe06f3bbd:0xcf0b8de597c559c!8m2!3d10.795483!4d106.7101379!16s%2Fg%2F11sw0vlbpy!19sChIJvTtv4I8pdTERnFV8Wd648Aw?authuser=0&hl=en&rclk=1 | B4: Bếp Chay & Cafe NHÀ MẤY DÌ | C4: 4.5 | D4: -169 | E4: · | F4: ₫100–200K | G4: Vegetarian | H4: · | I4: 80 Xô Viết Nghệ Tĩnh | J4: Closed | K4: · Opens 10 AM | L4: https://lh3.googleusercontent.com/gps-cs-s/APNQkAGasCU95XDbC2UNRmdsPJB76EgtedeHQQ6704IA7rVlwGsVTBqWSqg_8jZlujvq9RO8tSA-tGFQfI5dN0qALucsP4V599UEvTiLzio5qrbXzs6d6lWFRk6cDW2Idaauc88TMS0H=w80-h106-k-no | M4: https://ssl.gstatic.com/local/servicebusiness/default_user.png | N4: "Great | O4: vegan | P4: place on the water, cool view and tasty dishes"
A5: https://www.google.com/maps/place/L%C3%AA+An+vegetarian/data=!4m7!3m6!1s0x3175299a5b54e267:0x2c5aed119c2b2a6!8m2!3d10.7983324!4d106.7131962!16s%2Fg%2F11w427gzpj!19sChIJZ-JUW5opdTERprLCGdGuxQI?authuser=0&hl=en&rclk=1 | B5: Lê An vegetarian | C5: 5 | D5: -2 | F5: ₫100–200K | G5: Vegetarian | H5: · | I5: Block E1 Chung cư Mỹ Đức, Xô Viết Nghệ Tĩnh | J5: Open | K5: · Closes 7 PM | L5: https://lh3.googleusercontent.com/gps-cs-s/APNQkAFt6eCcel1HjcykhHDWr9brV6dfC2tTAOEtpuvKnq0Hx5VmzL7Xwgi88ZYPocxQXOznbARi2GVW573_NR3cKiQLosjIcqz4R7uwQ1bmqlryFCYag1vDzlmQykZ4JcyFl5GkhMIi=w132-h92-k-no | N5: Dine-in | O5: Curbside pickup | P5: No-contact delivery
A6: https://www.google.com/maps/place/B%E1%BA%BFp+Chay+Di%E1%BB%87u+An/data=!4m7!3m6!1s0x317529d5b3db254f:0xb1e8052d7e559426!8m2!3d10.790244!4d106.7154314!16s%2Fg%2F11yfr0tm1s!19sChIJTyXbs9UpdTERJpRVfi0F6LE?authuser=0&hl=en&rclk=1 | B6: Bếp Chay Diệu An | C6: 5 | D6: -15 | E6: · | F6: ₫1–100,000 | G6: Vegan | H6: · | I6: 142 Ngô Tất Tố | J6: Open | K6: · Closes 8 PM | L6: https://lh3.googleusercontent.com/gps-cs-s/APNQkAFCDufbr6UjRWN1k25CnFgRz1yeeBLHl9bI9JEnPg2A5aLkiWD-h5H-N0Vnze0d0tSw4cAjVH0hvQOEywVl-uQoFAH_BRnG6swDk3cNoGaEvNhI8XiTy12jgNe0ID7k2dFvX2BlrR7fDZ1n=w204-h92-k-no | N6: Dine-in | O6: Takeout
A7: https://www.google.com/maps/place/GBomb+Cuisine+-+Vegan+Thu%E1%BA%A7n+Chay/data=!4m7!3m6!1s0x317529d705e9553b:0xf3d465855b494436!8m2!3d10.7888411!4d106.7150518!16s%2Fg%2F11l6rzxw03!19sChIJO1XpBdcpdTERNkRJW4Vl1PM?authuser=0&hl=en&rclk=1 | B7: GBomb Cuisine - Vegan Thuần Chay | C7: 4.6 | D7: -55 | E7: · | F7: ₫1–100,000 | G7: Vegan | H7: · | I7: 36 Nguyễn Hữu Cảnh | J7: Closed | K7: · Opens 10 AM | L7: https://lh3.googleusercontent.com/gps-cs-s/APNQkAGGQIV8n5_BsYHOp7hu6ALAUjJxY7CeVYbGz8IzBz1bo4CaWzU1qrTM_rmcF-w80g0BAJZzDO7tdsj-eYi6bSLgAbt9ugBCnSu4EWRZZEdlCzhaPGd3CUqm35VAEc0BwM-DsLWZ2urjbCtr=w80-h106-k-no | M7: https://ssl.gstatic.com/local/servicebusiness/default_user.png | N7: "Honestly the best | O7: vegan | P7: Döner and Wrap that we ever had."
A8: https://www.google.com/maps/place/Fingerprint+Chay/data=!4m7!3m6!1s0x317529664f6132b3:0x1d2ab256182a0670!8m2!3d10.7914651!4d106.7048986!16s%2Fg%2F11h6t6hsww!19sChIJszJhT2YpdTERcAYqGFayKh0?authuser=0&hl=en&rclk=1 | B8: Fingerprint Chay | C8: 4.7 | D8: -103 | E8: · | F8: ₫1–100,000 | G8: Vegan | H8: · | I8: 2/1i1, Nguyễn Thị Minh Khai | J8: Open | K8: · Closes 9 PM | L8: https://lh3.googleusercontent.com/gps-cs-s/APNQkAFnhj5hm20ts0d_sE8JkyIrFu-XltGV9LgPt_wkdXLNsezOtqJtRT1pUTb-fDZp1QH0S61hJfhShs6fGHs6_qdUofXSe-YNCi2BGE3rNUHyzOaX2BUJfE60fYj9JNdROVWvqWFk=w122-h92-k-no | M8: https://ssl.gstatic.com/local/servicebusiness/default_user.png | N8: "Amazing | O8: vegan | P8: Bahn mi at a great price."
A9: https://www.google.com/maps/place/Here+%26+Now+Vegetarian+%28Restaurant+%26+coffee%29/data=!4m7!3m6!1s0x317529b04721988d:0xcf571837c81a5526!8m2!3d10.7898785!4d106.7109045!16s%2Fg%2F11fj8j6x8c!19sChIJjZghR7ApdTERJlUayDcYV88?authuser=0&hl=en&rclk=1 | B9: Here & Now Vegetarian (Restaurant & coffee) | C9: 4.3 | D9: -489 | E9: · | F9: ₫100–200K | G9: Vegetarian | H9: · | I9: · | J9: Closed | K9: · Opens 10 AM Wed | L9: https://lh3.googleusercontent.com/gps-cs-s/APNQkAGxGWqknxDB3NkVSnptepTQbkPIuGjrljJuHIDim8maSi__V9qjHB4iMFp67DA-iadRwvCO6LbhO6AamxlepSxKvTc-LFIV2hX06qvqgIfjPF34FUFVZUXEyIHpHv_rlQnxsBg=w138-h92-k-no | M9: https://ssl.gstatic.com/local/servicebusiness/default_user.png | N9: "Delicious | O9: vegetarian food | P9: in a calm and inviting atmosphere"
A10: https://www.google.com/maps/place/N%C6%AF%E1%BB%9AC+L%C3%88O+CHAY/data=!4m7!3m6!1s0x317529d071e6fc45:0xeca2ba2a38aad121!8m2!3d10.7943889!4d106.7162037!16s%2Fg%2F11h81jyn70!19sChIJRfzmcdApdTERIdGqOCq6ouw?authuser=0&hl=en&rclk=1 | B10: NƯỚC LÈO CHAY | C10: 4.5 | D10: -86 | E10: · | F10: ₫1–100,000 | G10: Vegetarian | H10: · | I10: Nguyễn Hữu Cảnh | J10: Open | K10: · Closes 7 PM | L10: https://lh3.googleusercontent.com/gps-cs-s/APNQkAGjKsMteyxZf-xdYtfivwH1h5y1mnKyFML9p4NNsMplAGd0_B5Ew-dy92ha_MkAVlwyocTY3k5kv1aG4MnmuF1iutorcihYVoceb_LCooSAlEzVvKBQKynGGYMSjASeQ4iSRoVW=w122-h92-k-no | M10: https://ssl.gstatic.com/local/servicebusiness/default_user.png | N10: "Delicious classic Vietnamese | O10: food | P10: in its
A11: https://www.google.com/maps/place/Little+India/data=!4m7!3m6!1s0x3175298063499757:0xa3ccbfa8acb2c51b!8m2!3d10.7900161!4d106.712004!16s%2Fg%2F11l6t2f849!19sChIJV5dJY4ApdTERG8WyrKi_zKM?authuser=0&hl=en&rclk=1 | B11: Little India | C11: 4.9 | D11: -452 | E11: · | F11: ₫200–300K | G11: Vegan | H11: · | I11: 92 Phạm Viết Chánh | J11: Closed | K11: · Opens 10 AM | L11: https://lh3.googleusercontent.com/gps-cs-s/APNQkAE-kxjQAYACBa_2fL0omzqnvfOY0jeDbUUdL7am_FyCavVq7TEUBTxfEtqNLFhaYiOL7-Bgx0AzKrnjL2Wu3pB5yQ9oFHaPmtgxUgLMrgtRYg1aV-z3cyhLEBnfFNqdRHThFjJ5gsx0OKc4=w80-h106-k-no | M11: https://ssl.gstatic.com/local/servicebusiness/default_user.png | N11: "The owner is gentle but super friendly 😁 Many choices for vegetarians."
A12: https://www.google.com/maps/place/Qu%C3%A1n+Chay+Nh%C3%A0+Min+-+L%E1%BA%A9u+Chay+C%C6%A1m+Chay/data=!4m7!3m6!1s0x31752919fa06f69b:0x8086849763a3cdb7!8m2!3d10.7939259!4d106.7094174!16s%2Fg%2F11mzv9dpk5!19sChIJm_YG-hkpdTERt82jY5eEhoA?authuser=0&hl=en&rclk=1 | B12: Quán Chay Nhà Min - Lẩu Chay Cơm Chay | C12: 4.9 | D12: -39 | E12: · | F12: ₫1–100,000 | G12: Vegetarian | H12: · | I12: 40 Nguyễn Văn Lạc | J12: Closed | K12: · Opens 9 AM | L12: https://lh3.googleusercontent.com/gps-cs-s/APNQkAHmqBaCciiSenVRidu8UwmuFS4PZ8j81sKtwLHZOEla4xoh-J7VQbr0xZlVO9XKbYVXhW9SgvcTtUBoy_zAzlIqc0wTLGGh-rx3JyDFUwimhNB8-Fvh9xIgmwOQL_K8qt2jhGN1HOZkpr9U=w80-h106-k-no | M12: https://ssl.gstatic.com/local/servicebusiness/default_user.png | N12: "Tasty | O12: food | P12: , friendly service, great price."
A13: https://www.google.com/maps/place/C%C6%A1m+Chay+T%E1%BB%8Bnh+%C4%90%E1%BB%99/data=!4m7!3m6!1s0x317528ac4c4e0819:0xed23015ebb6b3fd3!8m2!3d10.7906319!4d106.7173571!16s%2Fg%2F11btxcp54w!19sChIJGQhOTKwodTER0z9ru14BI-0?authuser=0&hl=en&rclk=1 | B13: Cơm Chay Tịnh Độ | C13: 4.3 | D13: -305 | E13: · | F13: ₫1–100,000 | G13: Vegan | H13: · | I13: · | J13: Open | K13: · Closes 9 PM | L13: https://lh3.googleusercontent.com/gps-cs-s/APNQkAHYDtzCb6oLtL64927p0fuM8cEDGYM_v86RjuPBAPZitQ_c3X5b-kU1q4INIsGjhYroOT0DNSHtisvPrzwxragqcnpbY9dMCRo3phL3qZtDB6xc8fIxbxEhn76MMcUu73DoP3-Z=w122-h92-k-no | M13: https://ssl.gstatic.com/local/servicebusiness/default_user.png | N13: "It's cheap and convenient for nearby vegetarians."
A14: https://www.google.com/maps/place/Xanh+vegan+and+vegetarian/data=!4m7!3m6!1s0x317529262821a143:0x65f789063aa8afae!8m2!3d10.7919385!4d106.7195364!16s%2Fg%2F11jgq4cmvc!19sChIJQ6EhKCYpdTERrq-oOgaJ92U?authuser=0&hl=en&rclk=1 | B14: Xanh vegan and vegetarian | C14: 4.1 | D14: -43 | E14: · | F14: ₫100–200K | G14: Vegetarian | H14: · | I14: hẻm 132 132/41 Nguyễn Hữu Cảnh | J14: Open | K14: · Closes 11:30 PM | L14: https://lh3.googleusercontent.com/gps-cs-s/APNQkAHqZJDXMmj0xEJA9ytrK8VHsa1wVXGriJY-YPOjF4EcTjUODQszCysjUh6hIbPHhXZYtLtTURPc_o7qH3TqobjZBFjoQp4QwyaoWYeYKt94izED3IxUvlyzIW1vIaxcIRAdyn7O=w80-h106-k-no | M14: https://ssl.gstatic.com/local/servicebusiness/default_user.png | N14: "Very good | O14: food | P14: , eco friendly packaging, generous portions and good price."
A15: https://www.google.com/maps/place/Quan+chay+Trung+Thanh/data=!4m7!3m6!1s0x317529000b3e1be1:0xdb90388cc38600db!8m2!3d10.7928043!4d106.7116873!16s%2Fg%2F11wqbm3wfy!19sChIJ4Rs-CwApdTER2wCGw4w4kNs?authuser=0&hl=en&rclk=1 | B15: Quan chay Trung Thanh | C15: 4.3 | D15: -16 | E15: · | F15: ₫1–100,000 | G15: Vegan | H15: · | I15: 71 Ngô Tất Tố | J15: Open | K15: · Closes 9 PM | L15: https://lh3.googleusercontent.com/gps-cs-s/APNQkAEoLUnLR50t5_TDa8FuZIzYJK3OASA0AERC0jDVXJZE-vWY-pDpNs6ULaw1hEGp_5piXBvAlXo2NaBtDqTxdE72GvJ7Sh3ra9qNfX-S1LgFiaB9uxBcgwsxUJq8-uztDeXbj3ae=w80-h106-k-no | M15: https://ssl.gstatic.com/local/servicebusiness/default_user.png | N15: "Very good chay | O15: restaurant | P15: ."
A16: https://www.google.com/maps/place/H%E1%BB%A7+t%C3%ADu+m%C3%AC+chay+59/data=!4m7!3m6!1s0x3175290032e53097:0xb5dd442b9d0c29f0!8m2!3d10.7918298!4d106.709977!16s%2Fg%2F11wwhrznh_!19sChIJlzDlMgApdTER8CkMnStE3bU?authuser=0&hl=en&rclk=1 | B16: Hủ tíu mì chay 59 | C16: 5 | D16: -7 | E16: · | F16: ₫1–100,000 | G16: Vegetarian | H16: · | I16: 59 Nguyễn Công Trứ | L16: https://lh3.googleusercontent.com/gps-cs-s/APNQkAFbFHEJhcCDvRfRFWaAwKm1jEg3oYatYSap1bAp_yLtGZFbe42EdMysjcWHBL4xTW5Y0rsSJeeXW7HEp7Z2bJdOV_POKLCHRfRVFaa65WzkY-VEd-uOF1I9yPm04TLbtfRNDS2Htff99TFU=w122-h92-k-no | M16: https://ssl.gstatic.com/local/servicebusiness/default_user.png | N16: "Traditional Vietnamese soups for cheap 25k - all | O16: vegan | P16: ."
A17: https://www.google.com/maps/place/C%C6%A1m+chay+Thi%C3%AAn+Ph%C3%BAc/data=!4m7!3m6!1s0x3175299865b641b1:0x4b4e7e2b1d6cb3f1!8m2!3d10.7960973!4d106.7185351!16s%2Fg%2F11ft0t7_fv!19sChIJsUG2ZZgpdTER8bNsHSt-Tks?authuser=0&hl=en&rclk=1 | B17: Cơm chay Thiên Phúc | C17: 4.5 | D17: -159 | E17: · | F17: ₫1–100,000 | G17: Vegetarian | H17: · | I17: · | J17: Opens soon | K17: · 7:30 AM | L17: https://lh3.googleusercontent.com/gps-cs-s/APNQkAEmoxsS13S1EIhx11fOrpL6-ujWwDchCmBM7T8-1mPyZsveg4o3UZlcdWIv5iQC1ZVvfVGpq8p_jN2pqHq6uI01IGfmmpqF5_-4kAYk4_b7wfoxXpN_B2ytIAaTgIWymmT0TDF6VMUk5_c4=w80-h106-k-no | M17: https://ssl.gstatic.com/local/servicebusiness/default_user.png | N17: "This place is | O17: vegetarian | P17: friendly, cheap and so tasty!"
A18: https://www.google.com/maps/place/Qu%C3%A1n+Chay+%C4%90%E1%BB%A9c+T%C3%A2m/data=!4m7!3m6!1s0x31752931b6d8d815:0xd39646780ea7b120!8m2!3d10.7972109!4d106.7056765!16s%2Fg%2F11rzq085_x!19sChIJFdjYtjEpdTERILGnDnhGltM?authuser=0&hl=en&rclk=1 | B18: Quán Chay Đức Tâm | C18: 3.2 | D18: -5 | F18: ₫1–100,000 | G18: Vegetarian | H18: · | I18: 36 Điện Biên Phủ | J18: Closed | K18: · Opens 8 AM | L18: https://lh3.googleusercontent.com/gps-cs-s/APNQkAHRR2u8dnZ7E8sGb3K2rOapN5tp4dKx81woQB-PsvIN5BV1ZraV_6tRhCzVRZbvvy8tDgMqDdmWWQTeH_HBWo1RBttaS1G5F2uigfzoNn3A72SeW4YBCj4_EtWldjWDn6HkotDXQA=w122-h92-k-no | N18: Dine-in | O18: Takeout
A19: https://www.google.com/maps/place/RuNam+Boutiqiue+-+Landmark+81/data=!4m7!3m6!1s0x317529de3a17b2d3:0x8fb6c3c42a8ad823!8m2!3d10.7951287!4d106.7210912!16s%2Fg%2F11fhz0h3ch!19sChIJ07IXOt4pdTERI9iKKsTDto8?authuser=0&hl=en&rclk=1 | B19: RuNam Boutiqiue - Landmark 81 | C19: 4.4 | D19: -503 | F19: ₫200–300K | G19: Restaurant | H19: · | I19: 720 Điện Biên Phủ | J19: Closed | K19: · Opens 9 AM | L19: https://lh3.googleusercontent.com/gps-cs-s/APNQkAG2mAaoM7KgHAotQeGdUrkaZfVPwhIcfC-d2r2nxmVtBFeBrxqUq9rvkZmI76JYhgbTbBRXq3wnD7SJ6C-Q2_Hi2mUpSOhtjumd67zYIcyEKfdijndybJGfRaByOxa5Tet9tudOtw=w163-h92-k-no | M19: https://ssl.gstatic.com/local/servicebusiness/default_user.png | N19: "Highly recommended for a refined, memorable meal."
A20: https://www.google.com/maps/place/Healthy+Choice+-+Love.Peace.Vegan/data=!4m7!3m6!1s0x3175295eced7374f:0x5876940b742edc25!8m2!3d10.7895113!4d106.7081421!16s%2Fg%2F11rzd8pkp9!19sChIJTzfXzl4pdTERJdwudAuUdlg?authuser=0&hl=en&rclk=1 | B20: Healthy Choice - Love.Peace.Vegan | C20: 4.9 | D20: -20 | F20: ₫100–200K | G20: Vegan | H20: · | I20: 62/4 Nguyễn Ngọc Phương | L20: https://lh3.googleusercontent.com/gps-cs-s/APNQkAEgWLRYX6kfRc_DNqPNA8HRHdEqtzcgpCwxV3RPDLm0AFg6xufwNM0kX-ijrz0sFIi2SSgxTDAU3HOWn2wY4FCzsF_1maXy1UhF2-4hTNepStSMJY6bB1Q66vub0MfbnjEjLVGm=w80-h106-k-no | M20: https://ssl.gstatic.com/local/servicebusiness/default_user.png | N20: " | O20: Vegetarian food | P20: is varied and delicious."
A21: https://www.google.com/maps/place/Linh+Lan+Shop/data=!4m7!3m6!1s0x317529001e581e65:0x4b4c6d926529c4d9!8m2!3d10.7906632!4d106.7105803!16s%2Fg%2F11zjb5cd31!19sChIJZR5YHgApdTER2cQpZZJtTEs?authuser=0&hl=en&rclk=1 | B21: Linh Lan Shop | F21: ₫100–200K | G21: Vegetarian | H21: · | I21: Chung Cư, Phạm Viết Chánh | J21: Opens soon | K21: · 7:30 AM | L21: https://lh3.googleusercontent.com/gps-cs-s/APNQkAEK8zWO6q-jMk0x9g_igHYaaLh9CdwxH7mqP0uYLwreqykCzIhiqitbd7oDvkT2PN2XCvM4PJFoaJGqcdqjdUOkuFY3agUhkTGz5Gbr59xQLXN4NKKgaTqCrTSy4d470Vbdrk0Z1JEuuyU4=w92-h92-k-no | N21: Dine-in

Sheet Dist 7
A1: hfpxzc href | B1: qBF1Pd | C1: MW4etd | D1: UY7F9 | E1: W4Efsd | F1: W4Efsd 2 | G1: W4Efsd 3 | H1: W4Efsd 4 | I1: W4Efsd 5 | J1: FQ2IWe src | K1: Jn12ke src | L1: ah5Ghc | M1: ah5Ghc 2 | N1: ah5Ghc 3 | O1: AJB7ye | P1: AJB7ye 2 | Q1: doJOZc | R1: W4Efsd 6
A4: https://www.google.com/maps/place/T%E1%BB%8ANH+V%E1%BB%8A+Vegan+Restaurant+-+Caf%C3%A9+%26+Tea+House/data=!4m7!3m6!1s0x31752538eb4f5349:0xc89e6827652da1b0!8m2!3d10.723496!4d106.7280633!16s%2Fg%2F11z3mt_y0g!19sChIJSVNP6zgldTERsKEtZSdonsg?authuser=0&hl=en&rclk=1 | B4: TỊNH VỊ Vegan Restaurant - Café & Tea House | C4: 5 | D4: -56 | E4: Vegan | F4: · | G4: 45 Đường C | H4: Open | I4: · Closes 9:30 PM | J4: https://lh3.googleusercontent.com/gps-cs-s/APNQkAEj6G3aUT616tih33g_ghtcm5RriNwGWJaELCyyFDUWVXAoZwLpw5kZdWqFApbVVh4sIbp7nemybbtbUBoymwD2JYLi_wiR3mqP9OdVyIpZ5RXike_3ePZSSW_MPcHLukU_e2vfodRWwrqm=w122-h92-k-no | K4: https://ssl.gstatic.com/local/servicebusiness/default_user.png | L4: "The | M4: food | N4: very delicious and nice service."
A5: https://www.google.com/maps/place/Golden+Lotus+Vegan+Restaurant+-+Coffe/data=!4m7!3m6!1s0x31752f6551d478e1:0x9cded1a1ba44c85d!8m2!3d10.7234968!4d106.7281066!16s%2Fg%2F11vlwhs07c!19sChIJ4XjUUWUvdTERXchEuqHR3pw?authuser=0&hl=en&rclk=1 | B5: Golden Lotus Vegan Restaurant - Coffe | C5: 4.7 | D5: -312 | E5: Vegan | F5: · | G5: · | H5: Open | I5: · Closes 9:30 PM | J5: https://lh3.googleusercontent.com/gps-cs-s/APNQkAGsD4LKUI1lzjMJjQr2XJ__PZPWk61XlYyseIKELEXG-5uK3i7D8r2hTK1-EdFKWhsakNVfP1X3xscYOlqybGtpjWdyUyPv_dAoI5isNOk4v0XE4B_GPqA8y68KKerXCS23th8G=w92-h92-k-no | K5: https://ssl.gstatic.com/local/servicebusiness/default_user.png | L5: "Fantastic | M5: vegan food | N5: in Saigon, really nice staff and great service." | O5: · | P5: ₫100–200K | Q5:  | R5: 45 Đường C
A6: https://www.google.com/maps/place/AN+vegetarian+restaurant+%26+cafe/data=!4m7!3m6!1s0x317525ccb9333c99:0xda58d8a6074bac72!8m2!3d10.7198048!4d106.7311906!16s%2Fg%2F11fklj_sv0!19sChIJmTwzucwldTERcqxLB6bYWNo?authuser=0&hl=en&rclk=1 | B6: AN vegetarian restaurant & cafe | C6: 4.5 | D6: -738 | E6: Vegetarian | F6: · | G6: Phố Tiểu Nam/75 Phú Mỹ Hưng | H6: Open | I6: · Closes 9:30 PM | J6: https://lh3.googleusercontent.com/gps-cs-s/APNQkAF158nfsbYNraDt_Jxen7db4ezEFU1-s1R02GH0RT3lvtgOSk6vYuDoXfl2dqqmeaT75BK3Rd8IXs2toHXj86RcLcah71NpQp7J65uWU3EAZJyYWwhvryHz6j_Gzto1AwjoYKEE=w138-h92-k-no | K6: https://ssl.gstatic.com/local/servicebusiness/default_user.png | L6: "Best place for who eat | M6: vegan food | N6: , quiet, comfort and clean place." | O6: · | P6: ₫200–300K
A7: https://www.google.com/maps/place/AN+-+nh%C3%A0+h%C3%A0ng+chay+An+%26+cafe+-+Ph%E1%BA%A1m+Th%C3%A1i+B%C6%B0%E1%BB%9Dng/data=!4m7!3m6!1s0x31752f1b223d3a45:0x9f3b5d0dd2597ef3!8m2!3d10.7275792!4d106.7124718!16s%2Fg%2F11s57yrk_7!19sChIJRTo9IhsvdTER835Z0g1dO58?authuser=0&hl=en&rclk=1 | B7: AN - nhà hàng chay An & cafe - Phạm Thái Bường | C7: 4.5 | D7: -370 | E7: Vegan | F7: · | G7: 220 Phạm Thái Bường | H7: Open | I7: · Closes 9:30 PM | J7: https://lh3.googleusercontent.com/gps-cs-s/APNQkAF1mhxKmGGO1mPyKBSCin8mxcIYO0bVtb9qOPeW4El2eh7UpndrsPFuoO59GKsh5NrByHKOCwK3XChMzZN1x0LKxxp92jf34c48-ewubVIvupsCmw0TfeWwMcuUti8-0EfvNuMO=w122-h92-k-no | K7: https://ssl.gstatic.com/local/servicebusiness/default_user.png | L7: "It's my first | M7: vegan restaurant | N7: experience and it's so delicious and healthy!" | O7: · | P7: $$
A8: https://www.google.com/maps/place/Nh%C3%A0+H%C3%A0ng+CHAY+365+-+%E1%BA%A8m+Th%E1%BB%B1c+Chay+%26+L%E1%BA%A9u+Chay+Th%C6%B0%E1%BB%A3ng+H%E1%BA%A1ng/data=!4m7!3m6!1s0x3175254f5c1ba6c7:0xe8f99b079cc1474a!8m2!3d10.7502899!4d106.7356134!16s%2Fg%2F11kj9lhjk0!19sChIJx6YbXE8ldTERSkfBnAeb-eg?authuser=0&hl=en&rclk=1 | B8: Nhà Hàng CHAY 365 - Ẩm Thực Chay & Lẩu Chay Thượng Hạng | C8: 4.9 | D8: -197 | E8: Vegan | F8: · | G8: 210 Bùi Văn Ba | H8: Open | I8: · Closes 10 PM | J8: https://lh3.googleusercontent.com/gps-cs-s/APNQkAEkfagu9uEqXUk4Z8baCjZg3ICDMMfuVklZgeQK3g9EL5Z2n7KfoWjGlaWbeWHDx8ti9LTUaumNLKxIMyUuoQFVQ_JiBoa_7HYst3OovmkPanQcQygIhegy5qDSMToBEGTa2s65=w122-h92-k-no | K8: https://ssl.gstatic.com/local/servicebusiness/default_user.png | L8: "Really an amazing place to eat | M8: vegan/vegetarian | N8: Banh mi and salted coffee." | O8: · | P8: ₫1–100,000
A9: https://www.google.com/maps/place/Nh%C3%A0+h%C3%A0ng+thu%E1%BA%A7n+chay+Ngon+Vegan+Dining+%26+Cafe+-+Nguy%E1%BB%85n+Cao/data=!4m7!3m6!1s0x31752f0043507b35:0xbd73279122c4ae3a!8m2!3d10.722411!4d106.7124706!16s%2Fg%2F11x6wzj1r5!19sChIJNXtQQwAvdTEROq7EIpEnc70?authuser=0&hl=en&rclk=1 | B9: Nhà hàng thuần chay Ngon Vegan Dining & Cafe - Nguyễn Cao | C9: 4.8 | D9: -659 | E9: Vegan | F9: · | G9: · | H9: Open | I9: · Closes 10 PM | J9: https://lh3.googleusercontent.com/gps-cs-s/APNQkAE76av07omrTU0hUHpu3cVShiE7m7CHz1zz-LxFlEkYAqIuosAJmc672d_PC2r6v3emuI8SVYoF1xpT3cd_xyqjVWZtU1trjP_OK8rFFTz3Q5vlMj6jReueVc13I781zbCXuvC9civCxAao=w138-h92-k-no | K9: https://ssl.gstatic.com/local/servicebusiness/default_user.png | L9: "The portions are generous, yet the plating is neat and thoughtful." | O9: · | P9: ₫100–200K | Q9:  | R9: 135 Nguyễn Cao
A10: https://www.google.com/maps/place/Mantra+Vegetarian+Restaurant/data=!4m7!3m6!1s0x317525f4d06b5e2d:0xf8f9a7a57e6adbc8!8m2!3d10.7300534!4d106.7094791!16s%2Fg%2F11t5x6_5cn!19sChIJLV5r0PQldTERyNtqfqWn-fg?authuser=0&hl=en&rclk=1 | B10: Mantra Vegetarian Restaurant | C10: 4.7 | D10: -252 | E10: Vegan | F10: · | G10: · | H10: Closed | I10: · Opens 10 AM | J10: https://lh3.googleusercontent.com/gps-cs-s/APNQkAF3VQkEB58VJlGfc2x2wqtDk-iVO_jnTheu76wIF7TPn3hVW5CgK64Vv9yMKYplgbUYWPKl8E_i78aPTBD2zB7Svb3FAargJhZz4cH8P2oFmY3_lHGf1Xo5-FxQyEwMO1j1Cd5dXw=w102-h92-k-no | K10: https://ssl.gstatic.com/local/servicebusiness/default_user.png | L10: "My meal tasted healthy, nutritious, and delicious!" | O10: · | P10: ₫100–200K | Q10:  | R10: SHOP HOUSE J040 CHUNG CƯ HƯNG VƯỢNG, 1 Đường số 6
A11: https://www.google.com/maps/place/Chay+Tu%E1%BB%87+Garden+-+Nguy%E1%BB%85n+B%C3%ADnh/data=!4m7!3m6!1s0x31752f2581753a33:0x27d514c6cea786f8!8m2!3d10.7280502!4d106.7103638!16s%2Fg%2F11vxxvtf0g!19sChIJMzp1gSUvdTER-IanzsYU1Sc?authuser=0&hl=en&rclk=1 | B11: Chay Tuệ Garden - Nguyễn Bính | C11: 4.9 | D11: -767 | E11: Vegan | F11: · | G11: Nguyễn Bính/101 Khu Phố Mỹ Hoàng | H11: Closed | I11: · Opens 10 AM | J11: https://lh3.googleusercontent.com/gps-cs-s/APNQkAHSK2DpULhqN4xi9pQkDvjZTLAIBHmXKDWST28HJ9NVByAChapwIfcijSOPdPNpoT4z1a8OqALWyP1ko1TKiLP1Wd9f-nQycpQ_O9evCIkPoZYs5szrkuzVbVpPCOJRYgTcOh_eeqOSaZ55=w122-h92-k-no | K11: https://ssl.gstatic.com/local/servicebusiness/default_user.png | L11: "Delicious | M11: vegetarian food | N11: in a relaxing place."
A12: https://www.google.com/maps/place/Chay+Rau+C%E1%BB%A7+N%E1%BA%A5m+Vegan+L%C3%AA+V%C4%83n+L%C6%B0%C6%A1ng/data=!4m7!3m6!1s0x31752fb422f81a2f:0xd0f8a1aabe1bf6f6!8m2!3d10.7339125!4d106.7020228!16s%2Fg%2F11r9vj06bw!19sChIJLxr4IrQvdTER9vYbvqqh-NA?authuser=0&hl=en&rclk=1 | B12: Chay Rau Củ Nấm Vegan Lê Văn Lương | C12: 4.6 | D12: -420 | E12: Restaurant | F12: · | G12: 557 Lê Văn Lương | H12: Closed | I12: · Opens 8:30 AM | J12: https://lh3.googleusercontent.com/gps-cs-s/APNQkAFZXMNfPx1xSipq305JJppwcXo7xXSt-8mddt4I4dgilyqcgoRg9PJ7Ts3FLM4kRzkrM6Q5StpL5OwmlHRy9jwUCcY_ZTR9JMXQGhMteD4_2u4pr668amFcSVmkVUQgEP2tl3unHn_fHgo=w122-h92-k-no | K12: https://ssl.gstatic.com/local/servicebusiness/default_user.png | L12: "We enjoyed a super tasty | M12: vegan | N12: hotpot for 210k VND ($8) for 3 people." | O12: · | P12: ₫100–200K
A13: https://www.google.com/maps/place/Green+%26+Greener+Vegetarian/data=!4m7!3m6!1s0x31752f8f7661799f:0xd011f7d60643435c!8m2!3d10.7333627!4d106.7068561!16s%2Fg%2F11xzt2d1s1!19sChIJn3lhdo8vdTERXENDBtb3EdA?authuser=0&hl=en&rclk=1 | B13: Green & Greener Vegetarian | C13: 5 | D13: -6 | E13: Vegetarian | F13: · | G13: 46 Nội Khu Hưng Gia 2 | H13: Open | I13: · Closes 9 PM | J13: https://lh3.googleusercontent.com/gps-cs-s/APNQkAEuv6DGkBHFJDJe_JXS9M1g9gDJT27iPapRqcBXCTJIp74BsJezHCPYDLLlLSRLZy7CKW78nzq2WgMvEpc3y7wy3X6C1M-7D7cT3acYB0KhvhK6VOJ2IbX4ZW8nKj_PP-X1Tz9lq3rfFNI9=w122-h92-k-no | K13: https://ssl.gstatic.com/local/servicebusiness/default_user.png | L13: "Incredible friggin | M13: food | N13: !"
A14: https://www.google.com/maps/place/B%C3%BAn+%26+Cu%E1%BB%91n+Thu%E1%BA%A7n+Chay/data=!4m7!3m6!1s0x317525ccee0bf6bf:0x8f22126334df46e!8m2!3d10.7045066!4d106.7360413!16s%2Fg%2F11svwcy_yg!19sChIJv_YL7swldTERbvRNMyYh8gg?authuser=0&hl=en&rclk=1 | B14: Bún & Cuốn Thuần Chay | C14: 4.6 | D14: -10 | E14: Vegan | F14: · | G14: · | H14: Open | I14: · Closes 12 PM | J14: https://lh3.googleusercontent.com/gps-cs-s/APNQkAH1dibzYFExSwNBr0jbVZ3CT3GGKtoZ4a0ktHwEWrC5if0eMpEwurGdNBrmMzUHWA-ITZlcsUor859HX51ija8AaIoNdatzEpLyFM1xFJ3CeC83-9H0fZOj_W_cYiJ1BczDPeFfAA=w80-h106-k-no | L14: Dine-in | M14: Drive-through | N14: No-contact delivery | Q14:  | R14: 49/3 Phạm Hữu Lầu
A15: https://www.google.com/maps/place/Qu%C3%A1n+chay+Thi%E1%BB%87n+Quang/data=!4m7!3m6!1s0x31752f9ab2e0ba17:0xac92afc83a4ddbf9!8m2!3d10.7517413!4d106.7139471!16s%2Fg%2F11jgzdg7ll!19sChIJF7rgspovdTER-dtNOsivkqw?authuser=0&hl=en&rclk=1 | B15: Quán chay Thiện Quang | C15: 4.9 | D15: -53 | E15: Vegan | F15: · | G15: 281 Đ. Trần Xuân Soạn | H15: Open | I15: · Closes 10 PM | J15: https://lh3.googleusercontent.com/gps-cs-s/APNQkAH49sprRofSR_5I-PIC22jPtd-IEtje6-y_rodeHWWDMIF6AP0d0BPUhOgUiw67LK8S3GUs0qYVJ39F6o4Pw-bEAcqasXxfjyT89CdID62RBs6JzF0K7oEzV1DDHU7Ihx-3ftdF=w122-h92-k-no | K15: https://ssl.gstatic.com/local/servicebusiness/default_user.png | L15: "I opted for a | M15: vegan | N15: Bun thai chay for take away." | O15: · | P15: ₫1–100,000
A16: https://www.google.com/maps/place/C%C6%A1m+chay+Li%C3%AAn+Hoa+2/data=!4m7!3m6!1s0x31752fedde94274f:0xf45641430d4694f!8m2!3d10.7516213!4d106.7081845!16s%2Fg%2F11x08kvs58!19sChIJTyeU3u0vdTERT2nUMBRkRQ8?authuser=0&hl=en&rclk=1 | B16: Cơm chay Liên Hoa 2 | C16: 4.9 | D16: -53 | E16: Vegan | F16: · | G16: 439 Đ. Trần Xuân Soạn | H16: Open | I16: · Closes 8:30 PM | J16: https://lh3.googleusercontent.com/gps-cs-s/APNQkAFTREDn-WPi507QZM-h_6aT1LgE0A7YI82m_T-RmezdVjMmLVwyzrN7g3BL3Dy6h-qSsFxXyTzsMRsV7WFI4iE_k1H3KYZXwK0WqjHRYwX-AmM8Qur2GGm3o5_ZvQE_9nrjfKkJWxCR8iWB=w122-h92-k-no | K16: https://ssl.gstatic.com/local/servicebusiness/default_user.png | L16: "Open aired and clean all | M16: vegan | N16: Vietnamese | O16: · | P16: ₫1–100,000
A17: https://www.google.com/maps/place/Qu%E1%BA%ADn+Chay+Ph%C6%B0oc+Tri/data=!4m7!3m6!1s0x31752f007c37d74d:0x27855865e57c53b2!8m2!3d10.7531154!4d106.6999528!16s%2Fg%2F11vy32hwn7!19sChIJTdc3fAAvdTERslN85WVYhSc?authuser=0&hl=en&rclk=1 | B17: Quận Chay Phưoc Tri | C17: 5 | D17: -1 | E17: Vegan | F17: · | G17: 199 Tôn Thất Thuyết | H17: Open | I17: · Closes 12 PM | J17: https://lh3.googleusercontent.com/gps-cs-s/APNQkAGCLBYGOlkbWPtXPl34HKfHsl-EbvI2bITp9dkuleow5HAUzU9dl-GEBMUUFLE1uiSI2_jwHgbPQsPdUqAKJKVVt-SspIzn0cSwa44pDNtFX3D939zn5iJyyF13ewyYXNVp9KBv=w122-h92-k-no | K17: https://ssl.gstatic.com/local/servicebusiness/default_user.png | L17: "No space for motorbike parking but they seem to do quite a bit of takeaway."
A18: https://www.google.com/maps/place/Qu%C3%A1n+chay+T%C3%A2m+An/data=!4m7!3m6!1s0x31752f1b5248a7ed:0x2a22e770a5dd2ecc!8m2!3d10.7399271!4d106.7104926!16s%2Fg%2F11s4y3q9pl!19sChIJ7adIUhsvdTERzC7dpXDnIio?authuser=0&hl=en&rclk=1 | B18: Quán chay Tâm An | C18: 4.7 | D18: -38 | E18: Vegetarian | F18: · | G18: 65 Đường số 79 | H18: Open | I18: · Closes 8 PM | J18: https://lh3.googleusercontent.com/gps-cs-s/APNQkAHxMyAgglTZTP-EoRSOMjBrpU-lnKcHYAr4eb4glMpU3LIaUqe8QCB4T_QzWCHjvFAmYVOhFqnLwmIVYUYJiuRC6bVXeiyiQGX-_VIwye5gCfUeVM3wfFEd21nP4a9Arb_EcIVXNA=w80-h106-k-no | K18: https://ssl.gstatic.com/local/servicebusiness/default_user.png | L18: "Super kind owner and amazing | M18: food | N18: !" | O18: · | P18: ₫1–100,000
A19: https://www.google.com/maps/place/Ba%CC%81nh+Mi%CC%80+N%E1%BA%A5m+An+Nhi%C3%AAn+%28Vegan+food%29/data=!4m7!3m6!1s0x31752f19ccd2b9cb:0xebba8202e7daa362!8m2!3d10.754336!4d106.6832464!16s%2Fg%2F11l5pmn1h3!19sChIJy7nSzBkvdTERYqPa5wKCuus?authuser=0&hl=en&rclk=1 | B19: Bánh Mì Nấm An Nhiên (Vegan food) | C19: 4.2 | D19: -43 | E19: Vegetarian | F19: · | G19: 179 Cao Đạt | H19: Open | I19: · Closes 8:30 PM | J19: https://lh3.googleusercontent.com/gps-cs-s/APNQkAHiFGq_AiOhPHEEn8M7-TW4nLiVABmqJneKZvOZeiHq0YF6tiOofU7KaYTzB8bl2jhYzhLyoNc6OEUR-RqneYPaummBI18HjF5ezV6CkAqbXyycFUUlGlLFvs3qGt20-A3fd0tkQ6_8kvVH=w151-h92-k-no | K19: https://ssl.gstatic.com/local/servicebusiness/default_user.png | L19: "Banh Mi boy serves awesome | M19: vegan | N19: Bahn Mi!" | O19: · | P19: ₫1–100,000
A20: https://www.google.com/maps/place/Nh%C3%A0+H%C3%A0ng+Sushi+Chay+TOJY/data=!4m7!3m6!1s0x31752f005e9f2a5f:0x727521e0d6107b87!8m2!3d10.7494948!4d106.7050264!16s%2Fg%2F11vx4fgthv!19sChIJXyqfXgAvdTERh3sQ1uAhdXI?authuser=0&hl=en&rclk=1 | B20: Nhà Hàng Sushi Chay TOJY | C20: 4.9 | D20: -686 | E20: Vegan | F20: · | G20: 113 Lê Văn Lương | H20: Closed | I20: · Opens 11 AM | J20: https://lh3.googleusercontent.com/gps-cs-s/APNQkAFpD2yAPop0Ly4XtG2gh_iDvSvn09op2nEAUb2INhubGUhngoRSyAMW55ffzw_v_IcZ_TIuasSvqHkg1Ciy6h2engFhymcUISLcUcBZapvEbfxRU_RZQph2qZu410z9ktqUIccKTA=w122-h92-k-no | K20: https://ssl.gstatic.com/local/servicebusiness/default_user.png | L20: "Everybody was very nice and the | M20: vegan | N20: options are amazing." | O20: · | P20: ₫100–200K
A21: https://www.google.com/maps/place/Chay+Hu+Tiu-+Nui/data=!4m7!3m6!1s0x31752500281aa525:0xab328b5836ea0dbb!8m2!3d10.7380213!4d106.7304498!16s%2Fg%2F11m6gchbn7!19sChIJJaUaKAAldTERuw3qNliLMqs?authuser=0&hl=en&rclk=1 | B21: Chay Hu Tiu- Nui | C21: 5 | D21: -2 | E21: Vegan | F21: · | G21: 453 Huỳnh Tấn Phát | H21: Open | I21: · Closes 10 PM | J21: https://lh3.googleusercontent.com/gps-cs-s/APNQkAH7Knn7yJYZzU0cJsXBgnYKtmSMT0IPG3qFwwBTeF0586_63uo34xoj9CBGuXIY7-0wSiJevqLEGHdTR08hYjKId1JL1sNDXoZnrJaKZmJlzK8_DJDovaUuj3h6uXwNeKn7n9an=w80-h106-k-no | K21: https://ssl.gstatic.com/local/servicebusiness/default_user.png | L21: "The mum came out and prepared me a | M21: vegan | N21: Bun thai for take away."
A22: https://www.google.com/maps/place/The+Vegan+Garden+-+Nh%C3%A0+H%C3%A0ng+Chay+Qu%E1%BA%ADn+7/data=!4m7!3m6!1s0x31752fed34d4ddcf:0xe422b5198d38893b!8m2!3d10.7180448!4d106.7297147!16s%2Fg%2F11gvt72p1d!19sChIJz93UNO0vdTERO4k4jRm1IuQ?authuser=0&hl=en&rclk=1 | B22: The Vegan Garden - Nhà Hàng Chay Quận 7 | C22: 4.2 | D22: -276 | E22: Vegan | F22: · | G22: · | H22: Opens soon | I22: · 8 AM | J22: https://lh3.googleusercontent.com/gps-cs-s/APNQkAGxPEI2Yjluorn8IvE5GAMMFAadlo9Fcq1hNuGYaboh9UPYgMvC2ixpNrQCsaQu3MpWSK1OCUoaHrkLjcgkTs1fv62DmhLUSTsOIYKJ0ls1RrX55YGKk48oJyGvyaBagZs9tIUgwHsB8jHM=w122-h92-k-no | K22: https://ssl.gstatic.com/local/servicebusiness/default_user.png | L22: "I learned that it was | M22: vegan | N22: and prepared in-house which was enough for me." | O22: · | P22: ₫100–200K | Q22:  | R22: Shop 3SB1-9 Số 2 Mỹ Viên Chung Cư Mỹ Viên P
A23: https://www.google.com/maps/place/Kashew+Cheese+Ph%C3%BA+M%E1%BB%B9+H%C6%B0ng/data=!4m7!3m6!1s0x317525b363cf29bb:0xd82702b9e55d2ff8!8m2!3d10.7208017!4d106.7272066!16s%2Fg%2F11txv99yl7!19sChIJuynPY7MldTER-C9d5bkCJ9g?authuser=0&hl=en&rclk=1 | B23: Kashew Cheese Phú Mỹ Hưng | C23: 4.7 | D23: -226 | E23: Vegan | F23: · | G23: The Ascentia, Khu Phố Mỹ Thái 2 | H23: Closed | I23: · Opens 8:30 AM | J23: https://lh3.googleusercontent.com/gps-cs-s/APNQkAGzkgswRJRixqVeXAYbTKlyiRpJYuGwCNje2pr66QW9f5WicSwzmrGaXE_3cFWW6XORsSOfnnp8VPXm3r1Y4nUWHEXBexquYWIm2-63O3ZiKHsRLvzkJ0IylbFTvEYLFu7ROSkwvftEUhBK=w80-h99-k-no | K23: https://ssl.gstatic.com/local/servicebusiness/default_user.png | L23: "Delicious | M23: vegan food | N23: and wonderful environment." | O23: · | P23: ₫200–300K
A24: https://www.google.com/maps/place/Nho%C3%A0n+-+Nh%C3%A0+h%C3%A0ng+chay+%2F+Cafe/data=!4m7!3m6!1s0x31752772508925a3:0xb8011424a00696cd!8m2!3d10.808991!4d106.753609!16s%2Fg%2F11vlhzkhxp!19sChIJoyWJUHIndTERzZYGoCQUAbg?authuser=0&hl=en&rclk=1 | B24: Nhoàn - Nhà hàng chay / Cafe | C24: 4.9 | D24: -333 | E24: Vegetarian restaurant | F24: · | G24: 4 Đặng Tiến Đông | H24: Closed | I24: · Opens 9 AM | J24: https://lh3.googleusercontent.com/p/AF1QipNUurZ69UR_ApupjfjIOZwXHm_Y7mD6O3IwyUJR=w80-h92-p-k-no | K24: https://ssl.gstatic.com/images/icons/material/system_gm/2x/done_gm_green700_24dp.png | L24: Dine-in | M24: Delivery
A25: https://www.google.com/maps/place/V%C6%AF%E1%BB%9CN+CHAY+GI%C3%81C+DUY%C3%8AN+-+BUFFET+L%E1%BA%A8U+CHAY%7C+BUFFET+CHAY+QU%E1%BA%ACN+1/data=!4m7!3m6!1s0x317529004ab4712f:0x7b9164eaa75b743e!8m2!3d10.7926748!4d106.6911361!16s%2Fg%2F11x8fcjl0p!19sChIJL3G0SgApdTERPnRbp-pkkXs?authuser=0&hl=en&rclk=1 | B25: VƯỜN CHAY GIÁC DUYÊN - BUFFET LẨU CHAY| BUFFET CHAY QUẬN 1 | C25: 4.8 | D25: -313 | E25: Vegan | F25: · | G25: 19 Trần Khắc Chân | H25: Closed | I25: · Opens 9:30 AM | J25: https://lh3.googleusercontent.com/gps-cs-s/APNQkAHIaO6fKK8cTnMG3JlcOfL5iSkphHrDt3mHjHV44vBXVtOIwzLQzkHu27RzJ3QFs35R4zvk_RnJqsB-W8ZMI5eiICmPIcdes2uV_hTmbFirkH_A01A6xOrHU4w7yUD2Ze835khl=w122-h92-k-no | K25: https://ssl.gstatic.com/local/servicebusiness/default_user.png | L25: "Overall, a wholesome and delicious | M25: vegan | N25: experience." | O25: · | P25: ₫100–200K
A26: https://www.google.com/maps/place/Qu%C3%A1n+Chay+Li%C3%AAn+T%E1%BB%8Fa+-+Vegetarian/data=!4m7!3m6!1s0x31752f6591337af7:0x31fec20c0e25f8ee!8m2!3d10.7850596!4d106.700441!16s%2Fg%2F11w4fzfj0l!19sChIJ93ozkWUvdTER7vglDgzC_jE?authuser=0&hl=en&rclk=1 | B26: Quán Chay Liên Tỏa - Vegetarian | C26: 4.7 | D26: -133 | E26: Restaurant | F26: · | G26: 17C Nguyễn Thị Minh Khai | H26: Closed | I26: · Opens 10 AM | J26: https://lh3.googleusercontent.com/gps-cs-s/APNQkAHrwgmM0FaLKkfQ28RHANegSPwgWJuiiV8tHkD-yCaSuw-0y56X-1YdDedfonFlDySksBph8ASSYLfJPkamodHNUkJGmF-KWyLoz7mNgeU0pHSGYNOGFTgSFQ_Ih_d1ejx7NeXkYQ=w122-h92-k-no | K26: https://ssl.gstatic.com/local/servicebusiness/default_user.png | L26: "A beautiful | M26: restaurant | N26: with | O26: · | P26: ₫100–200K
A27: https://www.google.com/maps/place/Nh%C3%A0+h%C3%A0ng+thu%E1%BA%A7n+chay+Ngon+Vegan+Dining+%26+Cafe+-+Tr%E1%BA%A7n+Cao+V%C3%A2n/data=!4m7!3m6!1s0x31752f005f2a10c3:0xe910019d74900f91!8m2!3d10.7844858!4d106.6975065!16s%2Fg%2F11yb67g06h!19sChIJwxAqXwAvdTERkQ-QdJ0BEOk?authuser=0&hl=en&rclk=1 | B27: Nhà hàng thuần chay Ngon Vegan Dining & Cafe - Trần Cao Vân | C27: 4.8 | D27: -809 | E27: Vegan | F27: · | G27: · | H27: Closed | I27: · Opens 10 AM | J27: https://lh3.googleusercontent.com/gps-cs-s/APNQkAFpI5tfcuPwi1764gWMn7Xek3S8o-PS4QVJtB3JF73iKHJmoClZRvOzM13jWbCNCC4DO7K6f2bJLzgwq7IuBmYrVR0UjS8MPXygEU5gglrzwjutiF2vK9S_hDgLY17YYJrAzb4To0A8pGk=w122-h92-k-no | K27: https://ssl.gstatic.com/local/servicebusiness/default_user.png | L27: "Great | M27: vegetarian food | N27: , a really cozy atmosphere, and very generous portions." | Q27:  | R27: 16 Trần Cao Vân
A28: https://www.google.com/maps/place/H%C6%B0%C6%A1ng+B%E1%BB%91n+M%C3%B9a+Coffee/data=!4m7!3m6!1s0x31752f92ee2dc7df:0x2415fa6a33541a3a!8m2!3d10.7868864!4d106.6922142!16s%2Fg%2F11kj8p4vb8!19sChIJ38ct7pIvdTEROhpUM2r6FSQ?authuser=0&hl=en&rclk=1 | B28: Hương Bốn Mùa Coffee | C28: 4.5 | D28: -69 | E28: Vegan | F28: · | G28: Đ. Trương Quyền | H28: Open | I28: · Closes 7:30 PM | J28: https://lh3.googleusercontent.com/gps-cs-s/APNQkAF8YjKMYi5wtwObXi0-Sh3HEy8wvZaIICa8TYaIZL1Rl6vouzW3bV_BWPObNVZhk9lqdfu6q1tMVzRr-nlP4NudNNU_3xx8BZvkj8FSuGWxHBWKTO-ejYANppl5AkTAthW6Hv0Nig=w112-h92-k-no | K28: https://ssl.gstatic.com/local/servicebusiness/default_user.png | L28: "The taste was incredible—I could hardly believe it was plant-based!" | O28: · | P28: ₫1–100,000
A29: https://www.google.com/maps/place/Ph%E1%BB%9F+Chay+Nh%C6%B0/data=!4m7!3m6!1s0x31752f33a1d4c2a9:0x99175b5e20d2bce8!8m2!3d10.787003!4d106.6923163!16s%2Fg%2F1thw46ty!19sChIJqcLUoTMvdTER6LzSIF5bF5k?authuser=0&hl=en&rclk=1 | B29: Phở Chay Như | C29: 4.3 | D29: -608 | E29: Vegan | F29: · | G29: · | H29: Open | I29: · Closes 8 PM | J29: https://lh3.googleusercontent.com/gps-cs-s/APNQkAHi5uWQEEv6EKDZ1-fJI9__u1n7sUK5MPNrDr0tUKHRAhbinsUunz2e13_IORtSsaiQCLSTwlxv_iWj7JmjJSFk2wqBgB_TJm-Zwh40aBEos74VqHjM3PoYbleEO4htBnDaUF8__A=w92-h92-k-no | K29: https://ssl.gstatic.com/local/servicebusiness/default_user.png | L29: "Crazy good | M29: vegan food | N29: , very good value, and | O29: · | P29: ₫1–100,000 | Q29:  | R29: 54 Đ. Trương Quyền
A30: https://www.google.com/maps/place/San+May+Cafe+%26+Vegetarian+Restaurant/data=!4m7!3m6!1s0x31752f351f00d393:0x2a4665bbd901d58f!8m2!3d10.7889806!4d106.6982583!16s%2Fg%2F1q6h_yzwz!19sChIJk9MAHzUvdTERj9UB2btlRio?authuser=0&hl=en&rclk=1 | B30: San May Cafe & Vegetarian Restaurant | C30: 4.3 | D30: -1061 | E30: Vegetarian | F30: · | G30: · | H30: Opens soon | I30: · 8 AM | J30: https://lh3.googleusercontent.com/gps-cs-s/APNQkAFt3jwkS7JqoLNYu5HpqOpB1jOzqSmoJ1OOvOzDIoxHOUr6_lhYT9LGQ-K9PofKfSuiQ8zYmkJqZU76ocfxIg9MiUhsEaHDLpv-dKJbwemox9EzduItjw_7NPCllHjoXmRrmOav=w122-h92-k-no | K30: https://ssl.gstatic.com/local/servicebusiness/default_user.png | L30: "Delicious | M30: vegetarian food | N30: with lots of different and interesting options." | O30: · | P30: ₫100–200K | Q30:  | R30: 155 Nguyễn Văn Thủ
A31: https://www.google.com/maps/place/C%C6%A1m+chay+Tr%C3%BAc+S%C6%A1n/data=!4m7!3m6!1s0x31752fd47345f86f:0x260fbfa5c85f60ab!8m2!3d10.7882261!4d106.6965514!16s%2Fg%2F11jz2htr2p!19sChIJb_hFc9QvdTERq2BfyKW_DyY?authuser=0&hl=en&rclk=1 | B31: Cơm chay Trúc Sơn | C31: 4.9 | D31: -15 | E31: Vegan | F31: · | G31: 86/1 Mạc Đĩnh Chi | H31: Closed | I31: · Opens 11 AM | J31: https://lh3.googleusercontent.com/gps-cs-s/APNQkAFn8hK_ktsf2sHZLWyzOYEMa_wywIHjMRChsNYAUrHmNjq4qDLKJ7kXgDybSoiA6noGWxaK9o_yEUlJXUd3VcW3XfqZ-GpMro6vZyQ5hb9mgzx2hDzO993k_53i9ZUbl4UkqiCd=w122-h92-k-no | L31: Dine-in | M31: Takeout | O31: · | P31: ₫1–100,000
A32: https://www.google.com/maps/place/Qu%C3%A1n+chay+L%C3%A1+%7C+Vegetarian+Restaurant/data=!4m7!3m6!1s0x31752f4e4d07f6c5:0xff498675a1cc48c6!8m2!3d10.7864414!4d106.6923565!16s%2Fg%2F11sv_2sb0j!19sChIJxfYHTU4vdTERxkjMoXWGSf8?authuser=0&hl=en&rclk=1 | B32: Quán chay Lá | Vegetarian Restaurant | C32: 4.5 | D32: -662 | E32: Vegetarian | F32: · | G32: · | H32: Closed | I32: · Opens 10:30 AM | J32: https://lh3.googleusercontent.com/gps-cs-s/APNQkAGUJRKLetWTvVImRYXaX74Dv_Csy14IOzfLmu9NfJF3RONd_frlOhWFF_VQtHvsO7U0-HgBpvtmuvR4-oO1Y2V2-cJPDY8HWx1-aF8kK6v1RW9EmvQv1F-eUxMf3wnOokiIXm2nxWx2ZUA=w163-h92-k-no | K32: https://ssl.gstatic.com/local/servicebusiness/default_user.png | L32: "Delicious | M32: vegetarian food | N32: and for an unbeatable price!!" | O32: · | P32: ₫1–100,000 | Q32:  | R32: 66/10 Phạm Ngọc Thạch
A33: https://www.google.com/maps/place/Tumaru.HCM/data=!4m7!3m6!1s0x31752fc4b7791925:0xf6933d880281a13c!8m2!3d10.7916298!4d106.6902393!16s%2Fg%2F11w3tbk1t_!19sChIJJRl5t8QvdTERPKGBAog9k_Y?authuser=0&hl=en&rclk=1 | B33: Tumaru.HCM | C33: 4.8 | D33: -136 | E33: Sushi | F33: · | G33: 153A Trần Quang Khải | H33: Closed | I33: · Opens 11 AM | J33: https://lh3.googleusercontent.com/gps-cs-s/APNQkAFZnz2mwnxPWhsO-XqivnG1DYI3f04XbRtdopACLVLXOQuas9yBNCa-UitKKLq0Q5saCz4JnJ-GL8gnY0Pus4Y-iVEpT-hQED42A2pKs1PDwZPUwRiWC9u3W93lXwNxtzJAMCVuZfKX6uoW=w80-h106-k-no | K33: https://ssl.gstatic.com/local/servicebusiness/default_user.png | L33: "The | M33: food | N33: is nicely prepared with a good sense of presentation."
A34: https://www.google.com/maps/place/Nh%C3%A0+H%C3%A0ng+Thu%E1%BA%A7n+Chay+Gi%C3%A1c+Duy%C3%AAn/data=!4m7!3m6!1s0x3175291a195516b9:0x33af64f812639c05!8m2!3d10.7908538!4d106.6968248!16s%2Fg%2F11rpd9l40f!19sChIJuRZVGRopdTERBZxjEvhkrzM?authuser=0&hl=en&rclk=1 | B34: Nhà Hàng Thuần Chay Giác Duyên | C34: 4.1 | D34: -104 | E34: Vegetarian | F34: · | G34: 133 Đinh Tiên Hoàng | H34: Open | I34: · Closes 11 PM | J34: https://lh3.googleusercontent.com/gps-cs-s/APNQkAEBuAdRHNi8YjT7Lh65lPCx4IjuWTAYfddvaKQF_xjZKsD7Apsqw5h3ncvZubO1GgdkS6Kfju936j_AXaDe97wouYrXjMTSDo2mDl25EBnRXrMzUV7raI4PgIUZXhm_dLTS7dNOZYLFQuVC=w122-h92-k-no | K34: https://ssl.gstatic.com/local/servicebusiness/default_user.png | L34: "wonderful how such scrumptious good can be made with just vegie" | O34: · | P34: ₫1–100,000
A35: https://www.google.com/maps/place/M%C3%8A+RAU+Vegetarian+-+Buffet+L%E1%BA%A9u+Rau+N%E1%BA%A5m/data=!4m7!3m6!1s0x31752f0001fe0033:0x3a0e0448b5313e8a!8m2!3d10.7871204!4d106.6960532!16s%2Fg%2F11vz620fyq!19sChIJMwD-AQAvdTERij4xtUgEDjo?authuser=0&hl=en&rclk=1 | B35: MÊ RAU Vegetarian - Buffet Lẩu Rau Nấm | C35: 4.3 | D35: -642 | E35: Vegetarian | F35: · | G35: 174 Nguyễn Văn Thủ | H35: Closed | I35: · Opens 10:30 AM | J35: https://lh3.googleusercontent.com/gps-cs-s/APNQkAHC-2DGKwwKqZ56B1yOoUCVqAR4YA1sj0nyYi3FONy3bFSiqA1B1ZVM3pGDr3V5vOT97HGB1HVOS4jSuEeQLkEPmIeMFjxmxvn1mmNFQIOIeA35GUzLPUcbCsqoxy3O2FeROEzpaUAItepp=w122-h92-k-no | K35: https://ssl.gstatic.com/local/servicebusiness/default_user.png | L35: "It comes with tons of veggie, tofu, and broth selection." | O35: · | P35: ₫100–200K
A36: https://www.google.com/maps/place/Tib+-+Hue+Restaurant/data=!4m7!3m6!1s0x31752f34773a47e3:0x62842bc6c1157c15!8m2!3d10.7858338!4d106.6942744!16s%2Fg%2F1vpq4c2m!19sChIJ40c6dzQvdTERFXwVwcYrhGI?authuser=0&hl=en&rclk=1 | B36: Tib - Hue Restaurant | C36: 4.3 | D36: -916 | E36: Vietnamese | F36: · | G36: 187 Ter Hai Bà Trưng | H36: Closed | I36: · Opens 11 AM | J36: https://lh3.googleusercontent.com/gps-cs-s/APNQkAGeOtRdYOpsq0GEFcaVVWfv1q7YOS0C7XEm46b3b8ofkxGag3zUoQzb37Bdszjrb4tWlJVT7Ct84yz3V1cBep1xeRpfelZB_xJdEd1z_iXCEfiaCYHBLVPH4I5SuFAgch6Kn3k=w163-h92-k-no | K36: https://ssl.gstatic.com/local/servicebusiness/default_user.png | L36: "Amazing place in folk style, found a | M36: vegetarian | N36: delicious menu, recommend" | O36: · | P36: $$
A37: https://www.google.com/maps/place/Qu%C3%A1n+Chay+Th%C3%B4i+K%E1%BB%87+L%E1%BA%A1c+An/data=!4m7!3m6!1s0x3175290038671725:0x40e93a655ada71f7!8m2!3d10.7904632!4d106.6906548!16s%2Fg%2F11y408y4hw!19sChIJJRdnOAApdTER93HaWmU66UA?authuser=0&hl=en&rclk=1 | B37: Quán Chay Thôi Kệ Lạc An | C37: 4.2 | D37: -6 | E37: Vegan | F37: · | G37: 72a Nguyễn Hữu Cầu | H37: Open | I37: · Closes 1 PM | J37: https://lh3.googleusercontent.com/gps-cs-s/APNQkAG4tPLku5RVir5kreKPL5DK4N8AlQTabACLWtxIlMaQAY50HycnbsGis22j0iZz5shgJb9KEoz0vtIwfHmhXiZ6kjblTdqqB7MPWRk86ZrHi1BcifOfFR_A92N53aev_LajOKD6-g=w147-h92-k-no | L37: Dine-in | M37: Drive-through | N37: No-contact delivery | O37: · | P37: ₫1–100,000
A38: https://www.google.com/maps/place/Qu%C3%A1n+M%C3%AC+Qu%E1%BA%A3ng+Ngon+Phan+Thi%E1%BA%BFt/data=!4m7!3m6!1s0x317528b57f128da3:0x21d56bb96d215aa7!8m2!3d10.7919119!4d106.7002651!16s%2Fg%2F1ptzvp0b2!19sChIJo40Sf7UodTERp1ohbblr1SE?authuser=0&hl=en&rclk=1 | B38: Quán Mì Quảng Ngon Phan Thiết | C38: 4.1 | D38: -32 | E38: Vegan | F38: · | G38: 52 Nguyễn Bỉnh Khiêm | H38: Open | I38: · Closes 9 PM | J38: https://lh3.googleusercontent.com/gps-cs-s/APNQkAGYzo8rSkxQqv47oEkoNwFu2URVh-PT5uqB5AbSq1yRDzOOl2QrPHagoae_QkSmL_Szs_sPI9_ZlL1N5pJISyu2zjbXyff1ZR2LlY9wuoHErUhAmsF8oqOQuqezgvbYqZz_0_e6lslZu3iQ=w80-h106-k-no | K38: https://ssl.gstatic.com/local/servicebusiness/default_user.png | L38: "It was so good"
A39: https://www.google.com/maps/place/%EC%8C%80%EA%B5%AD%EC%88%98+%EB%A7%9B%EC%A7%91/data=!4m7!3m6!1s0x31752f0d13a68def:0xfc82b2ecea775cd8!8m2!3d10.7879877!4d106.7026631!16s%2Fg%2F11l719sh7d!19sChIJ742mEw0vdTER2Fx36uyygvw?authuser=0&hl=en&rclk=1 | B39: 쌀국수 맛집 | C39: 3 | D39: -2 | E39: Vegetarian | F39: · | G39: 12 Nguyễn Thị Minh Khai | J39: https://streetviewpixels-pa.googleapis.com/v1/thumbnail?panoid=3yAJAkXA6T3hWOi8yK7ABg&cb_client=search.gws-prod.gps&w=80&h=92&yaw=322.82822&pitch=0&thumbfov=100 | L39: Dine-in | M39: Takeout
A40: https://www.google.com/maps/place/Ch%C3%A1o+Tr%E1%BA%AFng/data=!4m7!3m6!1s0x317528cc560be5c3:0xe8a8ae25bbd75ebe!8m2!3d10.7924606!4d106.6913927!16s%2Fg%2F11j00s3jp5!19sChIJw-ULVswodTERvl7XuyWuqOg?authuser=0&hl=en&rclk=1 | B40: Cháo Trắng | C40: 4 | D40: -10 | E40: Vegetarian | F40: · | G40: 10 Trần Khắc Chân | H40: Open | I40: · Closes 9:30 PM | J40: https://lh3.googleusercontent.com/gps-cs-s/APNQkAH5wcNKlHLjcrNB8O-c5GRiakUF6tmw5R8bYXp04XWtXN4Bg88os0XUAcZaZIwEUbVkTnAU2syXCeOBg49Ch2iY1hfq1RvfrJyLvL2bg0Ft0cauSZz6wiV6H7NGAaEa6adiF3gM=w163-h92-k-no | K40: https://ssl.gstatic.com/local/servicebusiness/default_user.png | L40: "Good price, good porridge, salted eggs ..."
A41: https://www.google.com/maps/place/N%E1%BA%A5m+%C4%90%C3%A1+S%C3%A0i+G%C3%B2n+-+G%C3%B3c+Chay+Thu%E1%BA%A7n+Tu%C3%BD/data=!4m7!3m6!1s0x317529b1b03911af:0x5b8fe270db7a30a9!8m2!3d10.7910566!4d106.6937269!16s%2Fg%2F11l1c5syzl!19sChIJrxE5sLEpdTERqTB623Dij1s?authuser=0&hl=en&rclk=1 | B41: Nấm Đá Sài Gòn - Góc Chay Thuần Tuý | C41: 3 | D41: -1 | E41: Vegan | F41: · | G41: 33/13 Lý Văn Phức | H41: Opens soon | I41: · 8 AM | J41: https://lh3.googleusercontent.com/gps-cs-s/APNQkAEEaZOW8f2PEHUHJcjpBfTHlMy8wWE5I52QEUnQJq17-UITJTVYLNeZwQ92LykmRE34G4FDd0CRwhnNcSdCOe33f8pyGAj_eO9kqBXTMQ-KuA5uT4UND9AXC8g8gk9wR-ao7E0m=w138-h92-k-no | L41: Dine-in | M41: Takeout | N41: No-contact delivery
A42: https://www.google.com/maps/place/Chaystation/data=!4m7!3m6!1s0x317528e841a795c1:0xd648bb148a2df42e!8m2!3d10.7860907!4d106.6990476!16s%2Fg%2F11bwkptcnf!19sChIJwZWnQegodTERLvQtihS7SNY?authuser=0&hl=en&rclk=1 | B42: Chaystation | C42: 4.6 | D42: -46 | E42: Vegetarian | F42: · | G42: 26/18B Đ. Lê Văn Duyệt | J42: https://lh3.googleusercontent.com/gps-cs-s/APNQkAHixIZ6HSfjXmEbaOI7vGibgVLDyhytLMI5uPSJg7xCx7ku1JwPdtXs026KtiB-MGZ40zn621v9XhX485OqF-LepCqouKDYDaL_qJl_Y0dHe5ZmRlmj1RRJo5TicKJkIlgzwpi_=w122-h92-k-no
A43: https://www.google.com/maps/place/Gotama+Buffet+Chay+%28Vegetarian+buffet+50k%29/data=!4m7!3m6!1s0x31752f682a188d09:0x22717d29bc8714e1!8m2!3d10.7876178!4d106.702848!16s%2Fg%2F11wr9wf3qd!19sChIJCY0YKmgvdTER4RSHvCl9cSI?authuser=0&hl=en&rclk=1 | B43: Gotama Buffet Chay (Vegetarian buffet 50k) | C43: 4.8 | D43: -26 | E43: Restaurant | F43: · | G43: 7A Nguyễn Thị Minh Khai | J43: https://lh3.googleusercontent.com/gps-cs-s/APNQkAE_rlmAZZerszR7uVRfOKtlTZpIXV0-7Jfk-VDVHhZCkGm9P0rRWNUb8Wf0Tseuhv-HfvRqabFXYPmcJqFAE6Y5kbSQQnDXPp5w7sezuz6U7J0yr7RiMIiK2wIp0oL3DNJDK2vZRw=w163-h92-k-no | K43: https://ssl.gstatic.com/local/servicebusiness/default_user.png | L43: "Very fresh, delicious flavours & a good variety of proteins & veg & soup!" | O43: · | P43: ₫1–100,000
A44: https://www.google.com/maps/place/C%C3%B4+Th%E1%BA%A3o+Vegetarian+Restaurant/data=!4m7!3m6!1s0x31752f09caa62d41:0x88b3e7e94ee3307a!8m2!3d10.7849579!4d106.6989365!16s%2Fg%2F11tp6q55xm!19sChIJQS2mygkvdTERejDjTunns4g?authuser=0&hl=en&rclk=1 | B44: Cô Thảo Vegetarian Restaurant | C44: 5 | D44: -18 | E44: Health Food | F44: · | G44: 37/3 Mạc Đĩnh Chi | J44: https://lh3.googleusercontent.com/gps-cs-s/APNQkAGfu3bc92fxlOgiT0pNlrHfTH_PjjkhKBxh1_Q2kW7Ii4I8A4RgspZS_VPAfBFz8LreX5yLESEg2ec4Az4NzU7mE_pDOEC7Z-_y-ZraHUEwl9Xn_HVD3ujwoGHx8I45w4uoFUtW9A=w87-h92-k-no

Sheet Dist 2
A1: hfpxzc href | B1: qBF1Pd | C1: MW4etd | D1: UY7F9 | E1: W4Efsd | F1: W4Efsd 2 | G1: W4Efsd 3 | H1: W4Efsd 4 | I1: W4Efsd 5 | J1: FQ2IWe src | K1: Jn12ke src | L1: ah5Ghc | M1: ah5Ghc 2 | N1: ah5Ghc 3 | O1: AJB7ye | P1: AJB7ye 2 | Q1: doJOZc | R1: W4Efsd 6
A4: https://www.google.com/maps/place/N%C3%9AC+Kitchen+%26+Bar/data=!4m7!3m6!1s0x317527b719420b0b:0x6caea65e9539b641!8m2!3d10.801888!4d106.7354722!16s%2Fg%2F11sv3mb2d2!19sChIJCwtCGbcndTERQbY5lV6mrmw?authuser=0&hl=en&rclk=1 | B4: NÚC Kitchen & Bar | C4: 4.9 | D4: -525 | E4: Restaurant | F4: · | G4: 08 Nguyễn Đăng Giai | H4: Open | I4: · Closes 10:30 PM | J4: https://lh3.googleusercontent.com/gps-cs-s/APNQkAFhTe5k5V2_ZnJ1y1kKFhkWVNvS7T2mR7O3nKOtOYugDfqKq3k18G6JtdWHVxGa64rIEkSGVGWPo7Kck-zvToSo8pij-rqoSroY1RXqigmR5DbcKu86wkm4TKpR8vjc1MTlsZ96JqaLp6s=w80-h106-k-no | K4: https://ssl.gstatic.com/local/servicebusiness/default_user.png | L4: "Delicious nutritious | M4: food | N4: , reasonable prices, enthusiastic staff" | P4: ₫200–300K
A5: https://www.google.com/maps/place/METTA+Vegetarian+Restaurant/data=!4m7!3m6!1s0x31752f3301a24a0f:0x1d144e41c931f0e0!8m2!3d10.797603!4d106.7415085!16s%2Fg%2F11d_71jz5w!19sChIJD0qiATMvdTER4PAxyUFOFB0?authuser=0&hl=en&rclk=1 | B5: METTA Vegetarian Restaurant | C5: 4.4 | D5: -712 | E5: Vegan | F5: · | G5: · | H5: Open | I5: · Closes 9 PM | J5: https://lh3.googleusercontent.com/gps-cs-s/APNQkAEJkjkXycfLEyq2Pa97UMh_pRH7ec4P4bpaIHwhlErGRZ3z7iX3wwBxl5W5GIac0DJHkvR5k6stgAWHsTOTPemwshD_e6rfbfqbWcHyomCWQ-kPM8SNkDLIKuu82xXnBgncfUVxuw=w143-h92-k-no | K5: https://ssl.gstatic.com/local/servicebusiness/default_user.png | L5: "Taste is good, wide variety and options are healthy." | O5: · | P5: ₫100–200K | Q5:  | R5: Số 6 Đ. Số 19
A6: https://www.google.com/maps/place/Chi+Cao+Vegetarian+Restaurant/data=!4m7!3m6!1s0x3175275a60e9c18b:0x362730d2bb93bcdb!8m2!3d10.7961531!4d106.7310219!16s%2Fg%2F11s7p7hkyq!19sChIJi8HpYFondTER27yTu9IwJzY?authuser=0&hl=en&rclk=1 | B6: Chi Cao Vegetarian Restaurant | C6: 4.6 | D6: -394 | E6: Vegan | F6: · | G6: 58A Trần Não | H6: Closed | I6: · Opens 9 AM | J6: https://lh3.googleusercontent.com/gps-cs-s/APNQkAEclnt39Es2iuBs3Mgq-3wSG_7jj6igQFyuiHhdg0bNx7LfcFlKnCYGad1i4OSWXXwUpUwAPvAhTkbQIM9KecoJFSCiVwItUS1xp2HCclnqJ2RUVNNdDlbZ_QuMr20QHBCk2LkW=w80-h106-k-no | K6: https://ssl.gstatic.com/local/servicebusiness/default_user.png | L6: "My fav | M6: vegan | N6: spot in An Phu, nurturing | O6: · | P6: ₫1–100,000
A7: https://www.google.com/maps/place/Nh%C3%A0+h%C3%A0ng+chay+Ph%E1%BA%A1m+Nghi%C3%AAm+Trai+-+Bongensai+Vegetarian/data=!4m7!3m6!1s0x3175271f0dc6ba31:0x42dc32368dfee0b!8m2!3d10.802349!4d106.7371597!16s%2Fg%2F11smbkhjv9!19sChIJMbrGDR8ndTERC-7faCPDLQQ?authuser=0&hl=en&rclk=1 | B7: Nhà hàng chay Phạm Nghiêm Trai - Bongensai Vegetarian | C7: 4.8 | D7: -629 | E7: Japanese | F7: · | G7: 49 Nguyễn Đăng Giai | H7: Closed | I7: · Opens 9 AM | J7: https://lh3.googleusercontent.com/gps-cs-s/APNQkAHKENkTkF8znaseeM6UJPbVi-SxDMpG135jlX9u0Iyib9a1xt6rvjHvXB4U3DvZrPQOnBIcytmv34m8nQH0HsS7qCHDF93TsKBUcAu_UJjHURfFtXO-yakS-vQzXkI3mANw-qWCdrw_nN5o=w122-h92-k-no | K7: https://ssl.gstatic.com/local/servicebusiness/default_user.png | L7: "Quiet, peaceful and interesting | M7: vegan | N7: takes on Japanese | P7: ₫200–300K
A8: https://www.google.com/maps/place/CHAY+GARDEN+Xu%C3%A2n+Th%E1%BB%A7y+-+Vegetarian+Restaurant+%26+Tea+House/data=!4m7!3m6!1s0x317527baef2e86b7:0x74d3ba96e8dbab1!8m2!3d10.8029541!4d106.7312266!16s%2Fg%2F11sttt9pwl!19sChIJt4Yu77ondTERsbqNbqk7TQc?authuser=0&hl=en&rclk=1 | B8: CHAY GARDEN Xuân Thủy - Vegetarian Restaurant & Tea House | C8: 4.8 | D8: -1644 | E8: Vegetarian | F8: · | G8: 52 Xuân Thủy | H8: Closed | I8: · Opens 10:30 AM | J8: https://lh3.googleusercontent.com/gps-cs-s/APNQkAHn_88E-8quJamy0I__0wVt7vn-o2F6nUMR6er__5jN_FvzvNO-mgmvkyLIUUZ5mUekEgPVjQSFDTrwxaeV3eWytqrInJTSEYH6HDdDV90QgMwyxgOL74Hu01GjtPRx5oqg1F6E3iEVPA9t=w92-h92-k-no | K8: https://ssl.gstatic.com/local/servicebusiness/default_user.png | L8: "delicious | M8: vegan food | N8: , good space and service, worth the experience" | O8: · | P8: ₫200–300K
A9: https://www.google.com/maps/place/Ch%C3%A2n+Nh%C6%B0+Vegetarian+Bistro/data=!4m7!3m6!1s0x317527489c8d0e6d:0x281c35153dcc3ed2!8m2!3d10.7921758!4d106.745538!16s%2Fg%2F11v_91zzs_!19sChIJbQ6NnEgndTER0j7MPRU1HCg?authuser=0&hl=en&rclk=1 | B9: Chân Như Vegetarian Bistro | C9: 5 | D9: -63 | E9: Vegetarian | F9: · | G9: 252 Nguyễn Hoàng | H9: Open | I9: · Closes 2:30 PM · Reopens 4:30 PM | J9: https://lh3.googleusercontent.com/gps-cs-s/APNQkAGKiVFEgEJYdIgAsO8wA_GMgr49UiQvcYMqfRRpol8B3NfFNYV8ItH-dmz-CO-poI1HU0E9ahD4Eo2BOhoQpEHvVRHjzIi0vTxB1EFBFS7KHDqS7ZW1ZcjLQSzzNdP_bktCHMS2=w80-h106-k-no | K9: https://ssl.gstatic.com/local/servicebusiness/default_user.png | L9: "I can recommend bun hue chay" | O9: · | P9: ₫1–100,000
A10: https://www.google.com/maps/place/AMAVI+KOM+%26+VEGAN/data=!4m7!3m6!1s0x317527c7b7e831c1:0x3d9981b0a6e32f4e!8m2!3d10.8065373!4d106.7308124!16s%2Fg%2F11ln2xr59y!19sChIJwTHot8cndTERTi_jprCBmT0?authuser=0&hl=en&rclk=1 | B10: AMAVI KOM & VEGAN | C10: 4.8 | D10: -308 | E10: Vegan | F10: · | G10: 61-63 Quốc Hương | H10: Open | I10: · Closes 8:30 PM | J10: https://lh3.googleusercontent.com/gps-cs-s/APNQkAEW4n_L1jZLc3gDARUp4NCF7OUZbntaHwsYQsJ2otP1LkbCA8LeG9XJOj1VM4u-uFzYH7UbU7Phe5bEyp8U1-JIBiPkywFHLMZrPlmKKUc_v8E2EcMZyDSbAgDSXTf8ZzNmUw_DO5V6T57Z=w122-h92-k-no | K10: https://ssl.gstatic.com/local/servicebusiness/default_user.png | L10: "We loved our | M10: vegan | N10: meals, fabulous kombucha and very attentive staff." | O10: · | P10: ₫100–200K
A11: https://www.google.com/maps/place/Vegete+Vegetarian+ramen+%EF%BC%86+cafe/data=!4m7!3m6!1s0x3175279414e96b99:0x51b499a47f6e025!8m2!3d10.8030413!4d106.7323303!16s%2Fg%2F11z0wzz1rm!19sChIJmWvpFJQndTERJeD2R5pJGwU?authuser=0&hl=en&rclk=1 | B11: Vegete Vegetarian ramen ＆ cafe | C11: 5 | D11: -4 | E11: Vegan | F11: · | G11: 01, Lô B/64 Xuân Thủy | H11: Closed | I11: · Opens 9 AM Wed | J11: https://lh3.googleusercontent.com/gps-cs-s/APNQkAGiqN1jrc_rGFRLwdiyX8v21ydGoasF_zPuyz-MlHEd1sAoqZ6g9zWkRa6N3U_t1v4zBQm-1qMqUrG4jPZunD4EsMT0DlKAKKGkDJ7HvHf9ireCQco2PyGbDdanAh2i6Pl7bA07U-jKyE0=w131-h92-k-no | O11: · | P11: ₫100–200K
A12: https://www.google.com/maps/place/Zeroism+Vegan+-+Caf%C3%A9+%26+Sourdough+Bakery/data=!4m7!3m6!1s0x317527d5334c31fd:0x37eddea14d7f67f9!8m2!3d10.8038578!4d106.7284153!16s%2Fg%2F11jbkcnttl!19sChIJ_TFMM9UndTER-Wd_TaHe7Tc?authuser=0&hl=en&rclk=1 | B12: Zeroism Vegan - Café & Sourdough Bakery | C12: 4.6 | D12: -462 | E12: Vegan | F12: · | G12: 50 Đ. Nguyễn Cừ | H12: Closed | I12: · Opens 8 AM | J12: https://lh3.googleusercontent.com/gps-cs-s/APNQkAF09s-D6Me_akrn2AwsyDfPaf0Gfo6pDMMMyXd7hF3kjUsAI-2-Fh3L1jYRI1BhwsKS2xjImx4Bzrfxi0sPLL0s78nzN2dl-jm-hoUs-pTSi2tME9i5734cHOpqoT1zt4IZH2Y=w138-h92-k-no | K12: https://ssl.gstatic.com/local/servicebusiness/default_user.png | L12: "Amazing | M12: restaurant | N12: a big variety of | O12: · | P12: ₫100–200K
A13: https://www.google.com/maps/place/Home+vegan+-+%C4%91%E1%BB%93+%C4%83n+chay+online+restaurant.+Giao+h%C3%A0ng+t%E1%BA%ADn+n%C6%A1i/data=!4m7!3m6!1s0x317527519da9bb41:0x3e74156dccba257e!8m2!3d10.8015544!4d106.7293157!16s%2Fg%2F11vz7jcqwr!19sChIJQbupnVEndTERfiW6zG0VdD4?authuser=0&hl=en&rclk=1 | B13: Home vegan - đồ ăn chay online restaurant. Giao hàng tận nơi | C13: 4.6 | D13: -28 | E13: Delivery Restaurant | F13: · | G13: 32 Đường số 54 | J13: https://lh3.googleusercontent.com/gps-cs-s/APNQkAGrGYOYFyvPiItMZV_qn-aT2fEp9aLxZmnDdd6__hKV1biZu1M7s_r80lFnKKUtUkh5LLWh3wood2CTrNMm_4VYtoqMqUe3zxDvTzIO_1HWeRRS2fniDCVGL8vAZWT8-5hCmMPMaQ=w80-h142-k-no | K13: https://ssl.gstatic.com/local/servicebusiness/default_user.png | L13: "Really delicious, healthy and affordable | M13: vegetarian food | N13: !" | P13: ₫100–200K
A14: https://www.google.com/maps/place/Laang+Saigon/data=!4m7!3m6!1s0x317527734c0cb41d:0x7673bae0668d9e03!8m2!3d10.8032012!4d106.7364045!16s%2Fg%2F11h4ms7v8y!19sChIJHbQMTHMndTERA56NZuC6c3Y?authuser=0&hl=en&rclk=1 | B14: Laang Saigon | C14: 4.6 | D14: -1051 | E14: Vegan | F14: · | G14: · | H14: Open | I14: · Closes 11 PM | J14: https://lh3.googleusercontent.com/gps-cs-s/APNQkAERxiEcDlm269dEiWo_5O4626DEkMhut4CWDnnLwPDLH_vtwFjmTWGoJ1tV4N5Iv-ZlHg1YhN788kGCdh6QVkE6Jq5-4VRiG5BxdZpmHdR-xrVVjvoid8Wtbp5HIBWcl5Qa82RD=w138-h92-k-no | K14: https://ssl.gstatic.com/local/servicebusiness/default_user.png | L14: "Really tasty | M14: vegetarian | N14: options too!" | P14: ₫200–300K | Q14:  | R14: 22 Đặng Hữu Phổ
A15: https://www.google.com/maps/place/Shelley%27s+Vegetarian+Comfort+Food/data=!4m7!3m6!1s0x317527b319afd4c5:0x10501fb041bc80c1!8m2!3d10.8064393!4d106.7349425!16s%2Fg%2F11hzz6_719!19sChIJxdSvGbMndTERwYC8QbAfUBA?authuser=0&hl=en&rclk=1 | B15: Shelley's Vegetarian Comfort Food | C15: 4.8 | D15: -36 | E15: Vegetarian | F15: · | G15: 71 Thảo Điền | H15: Closed | I15: · Opens 8 AM | J15: https://lh3.googleusercontent.com/gps-cs-s/APNQkAHmpQF8InLgGGK_b8Yr9KCPUvJm52iqW6r05kHY1y7PNfdksPmqgXItI11ijPXFgTnt265ZgG6y6FdT6Xnr2XnlaN5QszSBSDztA4LifdhMODVI73-iSkaVhAurg_xzft0MBo59uuBbT87x=w80-h106-k-no | K15: https://ssl.gstatic.com/local/servicebusiness/default_user.png | L15: "They have a very large | M15: vegetarian | N15: menu." | O15: · | P15: ₫200–300K
A16: https://www.google.com/maps/place/Dieu+Thien+Vegetarian+Restaurant/data=!4m7!3m6!1s0x3175270013f751cd:0x998aab24678048d3!8m2!3d10.7940178!4d106.741034!16s%2Fg%2F11y42gs8gy!19sChIJzVH3EwAndTER00iAZySripk?authuser=0&hl=en&rclk=1 | B16: Dieu Thien Vegetarian Restaurant | C16: 4.5 | D16: -78 | E16: Vegan | F16: · | G16: 130 Trần Lựu | H16: Open | I16: · Closes 8 PM | J16: https://lh3.googleusercontent.com/gps-cs-s/APNQkAF3nnsLiWkmQzwvhyNZ6BKO7PHJnUmVMq9VB242HaJIh2R_t_LOhyJ2KqDXDYivw_7jklOU_09k161GfPI0xDj0sPIO8x0SeZIh27W7SRUYPIECtX6Q9x9BHCDBxlsfcjvDba_zL2FuVIlB=w122-h92-k-no | K16: https://ssl.gstatic.com/local/servicebusiness/default_user.png | L16: "Healthy, rich, diverse, delicious and very cheap :)" | O16: · | P16: ₫1–100,000
A17: https://www.google.com/maps/place/Zero+Plant-based+Th%E1%BA%A3o+%C4%90i%E1%BB%81n+-+Eatery+%26+Caf%C3%A9/data=!4m7!3m6!1s0x3175278ac38574c5:0x8ea96d82eee93f17!8m2!3d10.8041995!4d106.7436151!16s%2Fg%2F11x1fcy3g6!19sChIJxXSFw4ondTERFz_p7oJtqY4?authuser=0&hl=en&rclk=1 | B17: Zero Plant-based Thảo Điền - Eatery & Café | C17: 4.8 | D17: -53 | E17: Vegetarian cafe and deli | F17: · | G17: 36 Đ. Số 10 | H17: Open | I17: · Closes 10:30 PM | J17: https://lh3.googleusercontent.com/gps-cs-s/APNQkAFkG-B35RpFX-Rkuz4eD_7ZLfNkKk7OOvgu3oWs4vcpFjl7TUacK4doUaFDSybdjHKhg7WFgpBZc-4WnzEm6UtqbBmTXst5yp3OdqcKt40KYAP9Z4H-ad2W5iXOyyStCaaYBsNfUz7LTOPX=w137-h92-k-no | K17: https://ssl.gstatic.com/local/servicebusiness/default_user.png | L17: "Service was fast, | M17: food | N17: was delicious and all | O17: · | P17: ₫1–100,000
A18: https://www.google.com/maps/place/Hum+Garden+-+Healthy+Veggies+Delights/data=!4m7!3m6!1s0x317526146200ff4b:0xe3bd3251a80b0465!8m2!3d10.8042095!4d106.7440478!16s%2Fg%2F11d_v9rggx!19sChIJS_8AYhQmdTERZQQLqFEyveM?authuser=0&hl=en&rclk=1 | B18: Hum Garden - Healthy Veggies Delights | C18: 4.6 | D18: -1504 | E18: Restaurant | F18: · | G18: · | H18: Closed | I18: · Opens 10 AM | J18: https://lh3.googleusercontent.com/gps-cs-s/APNQkAFphvPqUvyFsbu2lJcVnx5PAXKRdQq_NMn5ZnqmeyRGr-3kQCCgG0TrP6diNdL9MoFgjo6u9uoI6hg8gGmRrP5ZFtQIKI6GJD5Ax_zGRh6YGTksOeGQVZxyXMkV_0QAEr3JvxqEyg=w122-h92-k-no | K18: https://ssl.gstatic.com/local/servicebusiness/default_user.png | L18: "Delicious | M18: vegetarian food | N18: in a beautiful garden-like setting." | O18: · | P18: ₫200–300K | Q18:  | R18: 32 Đ. Số 10
A19: https://www.google.com/maps/place/Green+Monkey+Saigon+Choose+Your+Mood+%F0%9F%90%92:+FUEL+%7C+GLOW+%7C+TREAT/data=!4m7!3m6!1s0x317527f6e11d1ec3:0x7cfd7ecaff7469f7!8m2!3d10.803062!4d106.7292159!16s%2Fg%2F11s1qxcxzm!19sChIJwx4d4fYndTER92l0_8p-_Xw?authuser=0&hl=en&rclk=1 | B19: Green Monkey Saigon Choose Your Mood 🐒: FUEL | GLOW | TREAT | C19: 4.8 | D19: -142 | E19: Vegan | F19: · | G19: 4 Đ. Đỗ Quang | H19: Closed | I19: · Opens 8 AM Sat | J19: https://lh3.googleusercontent.com/gps-cs-s/APNQkAGJx3TU3l8-oRSh3yQn8w9lCdBOBuBRsUxkbQsW529Jl7CCwsiZz2KbjzGzQuXPWBRlcRfqdvRaJaxvtwEln9AxHyOSwxjreeyMZInKWnOngpsn3YNUcZ3M3Cg5LFtMs3aFfACuEBDFph4=w80-h106-k-no | K19: https://ssl.gstatic.com/local/servicebusiness/default_user.png | L19: "Delicious and healthy | M19: food | N19: with big enough sizes." | O19: · | P19: ₫100–200K
A20: https://www.google.com/maps/place/Kashew+Cheese+Deli/data=!4m7!3m6!1s0x3175274ee9f5fb59:0x6c9e640fb0838eee!8m2!3d10.80339!4d106.7392438!16s%2Fg%2F11h40yrh_w!19sChIJWfv16U4ndTER7o6DsA9knmw?authuser=0&hl=en&rclk=1 | B20: Kashew Cheese Deli | C20: 4.7 | D20: -828 | E20: Vegan | F20: · | G20: 14 Trần Ngọc Diện | H20: Closed | I20: · Opens 9 AM | J20: https://lh3.googleusercontent.com/gps-cs-s/APNQkAF7NAX-hnF7vpBfv3-CEl-N4hgJV40HLNaIKuS2WOjDOCfCP_QECPb_nZ3PhLdcuzWuuv0gR10HiR06qiNkJ0a46KbTZHD4Uy8k24VkQk27X1mLa3_PqAaaRl_IBP8RFHLdSKc=w122-h92-k-no | K20: https://ssl.gstatic.com/local/servicebusiness/default_user.png | L20: "The aubergine tomato and cheese pasta is the best | M20: vegan | N20: pasta I've ever had." | O20: · | P20: ₫100–200K
A21: https://www.google.com/maps/place/Nh%C3%A0+H%C3%A0ng+Chay+B%E1%BB%93+%C4%90%E1%BB%81+T%E1%BB%8Bnh+T%C3%A2m+Qu%E1%BA%ADn+2/data=!4m7!3m6!1s0x317525fdfb805777:0xe52be0166135deaa!8m2!3d10.7919215!4d106.730317!16s%2Fg%2F1yj4k3l0g!19sChIJd1eA-_0ldTERqt41YRbgK-U?authuser=0&hl=en&rclk=1 | B21: Nhà Hàng Chay Bồ Đề Tịnh Tâm Quận 2 | C21: 4 | D21: -870 | E21: Vegetarian | F21: · | G21: 160 Trần Não | H21: Open | I21: · Closes 9 PM | J21: https://lh3.googleusercontent.com/gps-cs-s/APNQkAEyMXKEbDXsXOCNdaocouw6XD6X1kuSm5exJad0sJQWSf8ZlLSEkZbF3mXXFQmKkLRevSzQmbGgz3jVQy8LOyz2TpJ9fxvTtODd4GzjsJNRTrn8zyPC6lPhBWTezBCIvMaIZVlO=w163-h92-k-no | K21: https://ssl.gstatic.com/local/servicebusiness/default_user.png | L21: "A large range of | M21: vegetarian | N21: dishes and delicious drinks to choose from." | O21: · | P21: ₫100–200K
A22: https://www.google.com/maps/place/%28Qu%E1%BA%ADn+2%29+Qu%C3%A1n+Chay+-+%E1%BA%A8m+Th%E1%BB%B1c+Chay+T%C3%A2m+An+-+Vietnamese+Vegetarian+Bistro/data=!4m7!3m6!1s0x3175278a10adcaf3:0xd137f0f63549c38!8m2!3d10.7895584!4d106.7436764!16s%2Fg%2F11x2gc920d!19sChIJ88qtEIondTEROJxUYw9_Ew0?authuser=0&hl=en&rclk=1 | B22: (Quận 2) Quán Chay - Ẩm Thực Chay Tâm An - Vietnamese Vegetarian Bistro | C22: 4.5 | D22: -27 | E22: Vegetarian | F22: · | G22: · | H22: Open | I22: · Closes 2 PM | J22: https://lh3.googleusercontent.com/gps-cs-s/APNQkAFkuZjlKgSQZPTwdOWclLwsf-TkxJ6W2VWuvYfnSWBWK3kik6smUWyM5TtwCdfz4EbZNwrkKf9lO76z6-dwGtUlq4KmrhQQx4vLbWnkAUjgzs0PJzQmjOJn1bDXqHOzquO6lncTwG-HSW4f=w92-h92-k-no | L22: Dine-in | M22: Drive-through | N22: No-contact delivery | P22: ₫100–200K | Q22:  | R22: 311 M1, Đ. Số 7
A23: https://www.google.com/maps/place/Papadums+Indian+Cuisine-+Box+Oi/data=!4m7!3m6!1s0x3175277d8366766f:0x9234e20b36ed8afc!8m2!3d10.8044683!4d106.7395548!16s%2Fg%2F11w95w6tg2!19sChIJb3Zmg30ndTER_IrtNgviNJI?authuser=0&hl=en&rclk=1 | B23: Papadums Indian Cuisine- Box Oi | C23: 4.8 | D23: -33 | E23: Modern Indian restaurant | F23: · | G23: Address: 19 Đ. Trần Ngọc Diện, Thảo Điền, Quận 2, 19 Trần Ngọc Diện | H23: Closed | I23: · Opens 11:30 AM | J23: https://lh3.googleusercontent.com/gps-cs-s/APNQkAHE3NzWH6LctDy8IiPrJ7X-MpZXjZs9zduK35CWMTe8rfHOdcTfEe2IRUQFPdV3jl2O5yDefFKcgNdUJKKxgZm-RQLDlQms7OWJInH3zlR_xiBrgvmsREv_rxd_M8fKT62nb_kU=w80-h106-k-no | K23: https://ssl.gstatic.com/local/servicebusiness/default_user.png | L23: "Very healthy yet super delicious, coming from high quality ingredients." | O23: · | P23: ₫100–200K
A24: https://www.google.com/maps/place/ChanChan+Vegan+Noodle/data=!4m7!3m6!1s0x3175274bf6f32151:0x1a7edc796d12db41!8m2!3d10.8041987!4d106.7335668!16s%2Fg%2F11y37b7__5!19sChIJUSHz9ksndTERQdsSbXncfho?authuser=0&hl=en&rclk=1 | B24: ChanChan Vegan Noodle | C24: 4.5 | D24: -1219 | E24: Vegan | F24: · | G24: 25A Ngô Quang Huy | H24: Closed | I24: · Opens 11 AM | J24: https://lh3.googleusercontent.com/gps-cs-s/APNQkAE8Y6-ETNIHzAJcoW71iMf40EZPeYVKFScVr2xEDyn_awLgcmHyzvbmUAeENzpHmHgEmqV2zfTb9IwEjm0JN-C4HiP2S1PsqsbcPZnOfOOqU60P9eDbqp99ySBH51bkhBTbkYYnLNgbmUcU=w107-h92-k-no | K24: https://ssl.gstatic.com/local/servicebusiness/default_user.png | L24: "100% | M24: vegan | N24: , unique dishes, super fast service, great prices." | O24: · | P24: ₫100–200K
A25: https://www.google.com/maps/place/Nho%C3%A0n+-+Nh%C3%A0+h%C3%A0ng+chay+%2F+Cafe/data=!4m7!3m6!1s0x31752772508925a3:0xb8011424a00696cd!8m2!3d10.8089914!4d106.7536086!16s%2Fg%2F11vlhzkhxp!19sChIJoyWJUHIndTERzZYGoCQUAbg?authuser=0&hl=en&rclk=1 | B25: Nhoàn - Nhà hàng chay / Cafe | C25: 4.9 | D25: -334 | E25: Vegetarian | F25: · | G25: 4 Đặng Tiến Đông | H25: Closed | I25: · Opens 9 AM | J25: https://lh3.googleusercontent.com/gps-cs-s/APNQkAEeIAL0qDG_3Htjka4mn3OoUpjoVyDES4oq7jocNYRj5Ye6cm7Za6Tyz5uDh5OLjZGO2KOqPVW6MM3PrLBsdgEfzPbE6pKN8efuuv_MLzvz2aR1Q2MmkkvHI1Nw82_P7AROYXRMbw=w122-h92-k-no | K25: https://ssl.gstatic.com/local/servicebusiness/default_user.png | L25: "I recently dined at this | M25: vegetarian restaurant | N25: (2 times) and was impressed." | O25: · | P25: ₫100–200K
A26: https://www.google.com/maps/place/Soha+plant-based/data=!4m7!3m6!1s0x3175270047d02f4f:0x177c4be4e72781ba!8m2!3d10.8060957!4d106.7407594!16s%2Fg%2F11yd9wnxp4!19sChIJTy_QRwAndTERuoEn5-RLfBc?authuser=0&hl=en&rclk=1 | B26: Soha plant-based | C26: 4.9 | D26: -169 | E26: Vegan | F26: · | G26: 39 Trần Ngọc Diện | H26: Closed | I26: · Opens 9:30 AM | J26: https://lh3.googleusercontent.com/gps-cs-s/APNQkAF6gkJ7TkReEAZhR68X1Po-XeZiO2LLI9j39t2JhBg4mi7pwTk1eZ0d9IkHe5FVWaiUkkTlFD_KhG0PUnzoYE_5OsAIL66vAcUA6YbAVeuCujTXaBC9EeLbhK8dVaLACKXPc0qOIDaOrfWA=w138-h92-k-no | K26: https://ssl.gstatic.com/local/servicebusiness/default_user.png | L26: "soooo yummy and healthy, great service, and atmosphere." | O26: · | P26: ₫200–300K
A27: https://www.google.com/maps/place/Chay+Thi%E1%BB%87n+T%C3%A2m/data=!4m7!3m6!1s0x3175270f8c4bb741:0x4bc3e54828fae12d!8m2!3d10.8042184!4d106.7285822!16s%2Fg%2F11s2hgrnvp!19sChIJQbdLjA8ndTERLeH6KEjlw0s?authuser=0&hl=en&rclk=1 | B27: Chay Thiện Tâm | C27: 5 | D27: -167 | E27: Vegetarian | F27: · | G27: 45b Đ. Đỗ Quang | H27: Closed | I27: · Opens 9 AM | J27: https://lh3.googleusercontent.com/gps-cs-s/APNQkAFAQRNLSkJxLNRqo0ocyJDR4qXbGNaYfCgZmNkmWyWu-Hpo-QYxdMquaVH-2jN3FQzpIlwPTL_1vwI_QkDoUVGfRX2WziGUOh_3Go_-PvuOJMrkNA4xeFMH6iFFZJ_3iMQeKQkIFsTWhaP0=w80-h106-k-no | K27: https://ssl.gstatic.com/local/servicebusiness/default_user.png | L27: "It’s literally the most delicious | M27: vegan food | N27: I had in weeks!!" | O27: · | P27: ₫1–100,000
A28: https://www.google.com/maps/place/GBomb+Cuisine+-+Vegan+Thu%E1%BA%A7n+Chay/data=!4m7!3m6!1s0x317529d705e9553b:0xf3d465855b494436!8m2!3d10.7888411!4d106.7150518!16s%2Fg%2F11l6rzxw03!19sChIJO1XpBdcpdTERNkRJW4Vl1PM?authuser=0&hl=en&rclk=1 | B28: GBomb Cuisine - Vegan Thuần Chay | C28: 4.6 | D28: -55 | E28: Vegan | F28: · | G28: 36 Nguyễn Hữu Cảnh | H28: Closed | I28: · Opens 10 AM | J28: https://lh3.googleusercontent.com/gps-cs-s/APNQkAGGQIV8n5_BsYHOp7hu6ALAUjJxY7CeVYbGz8IzBz1bo4CaWzU1qrTM_rmcF-w80g0BAJZzDO7tdsj-eYi6bSLgAbt9ugBCnSu4EWRZZEdlCzhaPGd3CUqm35VAEc0BwM-DsLWZ2urjbCtr=w80-h106-k-no | K28: https://ssl.gstatic.com/local/servicebusiness/default_user.png | L28: "Honestly the best | M28: vegan | N28: Döner and Wrap that we ever had." | O28: · | P28: ₫1–100,000
A29: https://www.google.com/maps/place/Nh%C3%A0+H%C3%A0ng+Chay+KIM+SA+-+Chi+Nh%C3%A1nh+Th%E1%BA%A3o+%C4%90i%E1%BB%81n+Premium+%28KIM+SA+Vegetarian+%26+Garden+Restaurant%29/data=!4m7!3m6!1s0x31752782fe504de9:0xc450699a0c319eab!8m2!3d10.8086875!4d106.7287477!16s%2Fg%2F11w2jtpvff!19sChIJ6U1Q_oIndTERq54xDJppUMQ?authuser=0&hl=en&rclk=1 | B29: Nhà Hàng Chay KIM SA - Chi Nhánh Thảo Điền Premium (KIM SA Vegetarian & Garden Restaurant) | C29: 4.9 | D29: -1008 | E29: Vegan | F29: · | G29: · | H29: Closed | I29: · Opens 10 AM | J29: https://lh3.googleusercontent.com/gps-cs-s/APNQkAHAbeVNQFdDvhB-pxt3EGqllLCOnRFp4F4KJYFrQZZHGzhl2RH04mwmOv0m1hMfbYAg1GSTNND_wIxdMHsNBRqtFusYxH4S8LZ1Lv68VTywnYb0mlFclTVOdssezIykTyG1exJle-PXt1o=w122-h92-k-no | K29: https://ssl.gstatic.com/local/servicebusiness/default_user.png | L29: "Delicious | M29: vegetarian food | N29: with a very zen and relaxing garden to dine in!" | O29: · | P29: ₫1–100,000 | Q29:  | R29: 27 Đường Số 59
A30: https://www.google.com/maps/place/Rawberry/data=!4m7!3m6!1s0x31752749687d03d3:0xed2869141b09c7c8!8m2!3d10.8047387!4d106.7285675!16s%2Fg%2F11kkb3h35d!19sChIJ0wN9aEkndTERyMcJGxRpKO0?authuser=0&hl=en&rclk=1 | B30: Rawberry | C30: 4.8 | D30: -135 | E30: Vegan | F30: · | G30: 52 Đ. Đỗ Quang | H30: Closed | I30: · Opens 9 AM | J30: https://lh3.googleusercontent.com/gps-cs-s/APNQkAGMkyel44UyWeHdzwsqQ-bsjOkQ-FRsAioijdZg9xjckioiMzb6o9PZXE6DN8NTUeDfeMoI77TyvXk5cRHZUE2uH-ckbKa9zd2xrk8BGmfCvg1Iv3CFle2b45jvZaRkwfeW4HZ98V_Oyko=w80-h106-k-no | K30: https://ssl.gstatic.com/local/servicebusiness/default_user.png | L30: "Cute interior, good quality | M30: vegan | N30: cakes, friendly staff, small menu" | O30: · | P30: ₫100–200K
A31: https://www.google.com/maps/place/Tu%E1%BB%87+Minh+Vegan+Food+%26+Drinks+%7C+Qu%C3%A1n+Chay+Ngon+B%C3%ACnh+Th%E1%BA%A1nh/data=!4m7!3m6!1s0x317529007b12be85:0xdb6ab139bfcbcc1c!8m2!3d10.790118!4d106.7112413!16s%2Fg%2F11y50t524s!19sChIJhb4SewApdTERHMzLvzmxats?authuser=0&hl=en&rclk=1 | B31: Tuệ Minh Vegan Food & Drinks | Quán Chay Ngon Bình Thạnh | C31: 4.8 | D31: -333 | E31: Restaurant | F31: · | G31: 76C-76D Phạm Viết Chánh | H31: Closed | I31: · Opens 10:30 AM | J31: https://lh3.googleusercontent.com/gps-cs-s/APNQkAGITNJYyo1b5q_RsZJQLBFrsUvNnUlt0LTq5vdMdLyiyhz4AxlBlCwuw2UFWsOanRNuYWI3euieP7uoMTVid-5uXVLsZjhZHyuH0e7XndKVmX5FSVIBk1K-11VPcH6kUeXXeMiIFjcU-IcC=w163-h92-k-no | K31: https://ssl.gstatic.com/local/servicebusiness/default_user.png | L31: "Delicious | M31: vegan food | N31: , which is also tasty for people who usually like meat." | O31: · | P31: ₫100–200K
A32: https://www.google.com/maps/place/Lim+Veggie+Bistro/data=!4m7!3m6!1s0x317529bb1656f27d:0xc74b19bde30c8bc0!8m2!3d10.7810504!4d106.7061501!16s%2Fg%2F11kb92ssq9!19sChIJffJWFrspdTERwIsM470ZS8c?authuser=0&hl=en&rclk=1 | B32: Lim Veggie Bistro | C32: 4.9 | D32: -664 | E32: Vegetarian | F32: · | G32: 07 Ngô Văn Năm | H32: Closed | I32: · Opens 9 AM | J32: https://lh3.googleusercontent.com/gps-cs-s/APNQkAHunKOtAwdl9ioe1SSQIakwRsr2tzHaG7CeTpLOWLX7QsDqjVxHokkNNkYxwfD5HT4hvgYy9a3ix1WhwxLbmPC2pQATpubPTkd41P7HyM1lR-U7n2oV45Ays1zQtoCz8egJcnnD=w80-h106-k-no | K32: https://ssl.gstatic.com/local/servicebusiness/default_user.png | L32: "Exceptional | M32: vegan food | N32: and atmosphere." | O32: · | P32: ₫100–200K
A33: https://www.google.com/maps/place/L%C3%AA+An+vegetarian/data=!4m7!3m6!1s0x3175299a5b54e267:0x2c5aed119c2b2a6!8m2!3d10.7983324!4d106.7131962!16s%2Fg%2F11w427gzpj!19sChIJZ-JUW5opdTERprLCGdGuxQI?authuser=0&hl=en&rclk=1 | B33: Lê An vegetarian | C33: 5 | D33: -2 | E33: Vegetarian | F33: · | G33: Block E1 Chung cư Mỹ Đức, Xô Viết Nghệ Tĩnh | H33: Open | I33: · Closes 7 PM | J33: https://lh3.googleusercontent.com/gps-cs-s/APNQkAFt6eCcel1HjcykhHDWr9brV6dfC2tTAOEtpuvKnq0Hx5VmzL7Xwgi88ZYPocxQXOznbARi2GVW573_NR3cKiQLosjIcqz4R7uwQ1bmqlryFCYag1vDzlmQykZ4JcyFl5GkhMIi=w132-h92-k-no | L33: Dine-in | M33: Curbside pickup | N33: No-contact delivery | P33: ₫100–200K
A34: https://www.google.com/maps/place/Nh%C3%A0+h%C3%A0ng+chay+Du+Y%C3%AAn+Vegetarian+-+Th%E1%BA%A3o+%C4%90i%E1%BB%81n+Qu%E1%BA%ADn+2/data=!4m7!3m6!1s0x3175275451ca0d6b:0xa3313f7edee87dad!8m2!3d10.8042665!4d106.7443254!16s%2Fg%2F11v3mhc2b7!19sChIJaw3KUVQndTERrX3o3n4_MaM?authuser=0&hl=en&rclk=1 | B34: Nhà hàng chay Du Yên Vegetarian - Thảo Điền Quận 2 | C34: 4.5 | D34: -513 | E34: Vegan | F34: · | G34: 26B Đ. Số 10 | H34: Closed | I34: · Opens 9 AM | J34: https://lh3.googleusercontent.com/gps-cs-s/APNQkAHkApJ1jcKEGi-sstXT-c6buqm_S3AkniN1tcV3ZmSB_OKXnZNphtcYmq_RHTseVk7p1f6PVl3VXaj5yCqY3oNV1qEEyCTotBxRx9lyWzXvBF4HVtcHxcLytI5w0RhQMpAE3my-j4WGDAGI=w138-h92-k-no | K34: https://ssl.gstatic.com/local/servicebusiness/default_user.png | L34: "Actual excellence in | M34: vegan food | N34: , service, decor." | P34: ₫100–200K
A35: https://www.google.com/maps/place/Santorino+coffee+%26+veggies/data=!4m7!3m6!1s0x3175294056ebc581:0x4844703a35afacdd!8m2!3d10.7886858!4d106.7087982!16s%2Fg%2F11h37m7rc_!19sChIJgcXrVkApdTER3ayvNTpwREg?authuser=0&hl=en&rclk=1 | B35: Santorino coffee & veggies | C35: 4.7 | D35: -344 | E35: Vegan | F35: · | G35: · | H35: Opens soon | I35: · 7:45 AM | J35: https://lh3.googleusercontent.com/gps-cs-s/APNQkAETTMMMK3UYj5S-Io9Xhl1JO4uoAG1hztHqxCRsf1xMFVcTffbCDguMYhbuXtsE2Z3Rp7Tu29jqfYIOQkvc_zkzvru9hOiC1aFnSL3ldtOwpYLc-du65xB-bNQP_iC9ZI_4ODo=w122-h92-k-no | K35: https://ssl.gstatic.com/local/servicebusiness/default_user.png | L35: "Friendly staff, SO MANY | M35: vegan | N35: options and really cute vibes inside!" | O35: · | P35: ₫100–200K | Q35:  | R35: 74 Nguyễn Ngọc Phương
A36: https://www.google.com/maps/place/Th%E1%BB%B1c+ph%E1%BA%A9m+chay+-+L%C3%B2+%C4%91%E1%BA%ADu+h%C5%A9+n%C3%B3ng+B%E1%BA%AFc+Ninh/data=!4m7!3m6!1s0x317527006aacef9f:0xb1583578c21e8c71!8m2!3d10.7942357!4d106.7344837!16s%2Fg%2F11vqdd86cb!19sChIJn--sagAndTERcYwewng1WLE?authuser=0&hl=en&rclk=1 | B36: Thực phẩm chay - Lò đậu hũ nóng Bắc Ninh | C36: 4 | D36: -1 | E36: Vegan | F36: · | G36: 41 Đ. Số 7 | J36: https://streetviewpixels-pa.googleapis.com/v1/thumbnail?panoid=Tv3Q6vnzX06zh068rKmW6A&cb_client=search.gws-prod.gps&w=80&h=92&yaw=142.42044&pitch=0&thumbfov=100 | L36: Dine-in | M36: Takeout | P36: ₫1–100,000
A37: https://www.google.com/maps/place/Green+Box+%7C+%C4%90.+L%C3%AA+V%C4%83n+Mi%E1%BA%BFn+%7C+Th%E1%BA%A3o+%C4%90i%E1%BB%81n/data=!4m7!3m6!1s0x31752f3e15bc4c0b:0x29925267cd357e85!8m2!3d10.804643!4d106.732175!16s%2Fg%2F11jmzky2v3!19sChIJC0y8FT4vdTERhX41zWdSkik?authuser=0&hl=en&rclk=1 | B37: Green Box | Đ. Lê Văn Miến | Thảo Điền | C37: 4.6 | D37: -147 | E37: Restaurant | F37: · | G37: 6 Lê Văn Miến | H37: Closed | I37: · Opens 9 AM | J37: https://lh3.googleusercontent.com/gps-cs-s/APNQkAFCPceYLM25JeVSujoO5fONst8iVIS0wSLRXRxCl-yR2cX-TBz2CYcC2Z5BLBWdvKuwNfUyBfOrXAJMN7FKJLre0UIHmJpONjJ9z7ejJKn1Cfn7cN2j3kje-SSFf0k-bIMEnzituQ=w80-h99-k-no | K37: https://ssl.gstatic.com/local/servicebusiness/default_user.png | L37: "Accommodating, exceptional attention to detail and great healthy variety." | O37: · | P37: ₫100–200K
A38: https://www.google.com/maps/place/Hoang%E2%80%99s+Kitchen+-+Vietnamese+cuisine+%26+vegan+food+4/data=!4m7!3m6!1s0x31752f000b681f0b:0x4ac289fc569a9d84!8m2!3d10.7813151!4d106.7055893!16s%2Fg%2F11yqvldd8l!19sChIJCx9oCwAvdTERhJ2aVvyJwko?authuser=0&hl=en&rclk=1 | B38: Hoang’s Kitchen - Vietnamese cuisine & vegan food 4 | C38: 4.9 | D38: -621 | E38: Vegan | F38: · | G38: · | H38: Closed | I38: · Opens 10:30 AM | J38: https://lh3.googleusercontent.com/gps-cs-s/APNQkAHlA3b-Bw2gEbXwIqUvvh-gzMqj539dS0Te9ifqzfIG43MXC1P1CXG5iVfqJ6Sl_4ePycjy2xMvtcVqtjjqF1uGuV2XXqkXew7DSnPV3ldHghpivjFRw3gO24ofcY026lzAVR5V_G77nqiE=w137-h92-k-no | K38: https://ssl.gstatic.com/local/servicebusiness/default_user.png | L38: "lovely meal , very | M38: vegetarian | N38: friendly and great staff !" | O38: · | P38: ₫200–300K | Q38:  | R38: 13/1 Lê Thánh Tôn
A39: https://www.google.com/maps/place/Qu%C3%A1n+Thu%E1%BA%A7n+Chay+Happy+Veggies/data=!4m7!3m6!1s0x31752712f1564c51:0xeb680e81b4d47c9e!8m2!3d10.8040027!4d106.7309875!16s%2Fg%2F11h9bhpztr!19sChIJUUxW8RIndTERnnzUtIEOaOs?authuser=0&hl=en&rclk=1 | B39: Quán Thuần Chay Happy Veggies | C39: 4 | D39: -124 | E39: Vegan | F39: · | G39: 33/12 Quốc Hương | H39: Opens soon | I39: · 7:30 AM | J39: https://lh3.googleusercontent.com/gps-cs-s/APNQkAFBTopqo9vJB5bS93qdayQGmCR3eNUk_zXSk9M5SYtSiweIAv3je9QXSCq58i_c78_XQL1jgg_mdsG04SVYASNvo6C3btlt7mxtFl93tCgSj_1UyCddhQnGSOF3VmjRPOpwZg7WZA=w122-h92-k-no | K39: https://ssl.gstatic.com/local/servicebusiness/default_user.png | L39: "Really tasty | M39: vegan | N39: phở and very friendly staff." | O39: · | P39: ₫1–100,000
A40: https://www.google.com/maps/place/Khai+T%C3%A2m+Vegetarian+Food/data=!4m7!3m6!1s0x3175270ee41ece0f:0xc449e97f9fa6da21!8m2!3d10.8060956!4d106.7510874!16s%2Fg%2F11y3_yv7sb!19sChIJD84e5A4ndTERIdqmn3_pScQ?authuser=0&hl=en&rclk=1 | B40: Khai Tâm Vegetarian Food | C40: 4.5 | D40: -28 | E40: Vegetarian | F40: · | G40: 28 Đường số 13 | H40: Open | I40: · Closes 7 PM | J40: https://lh3.googleusercontent.com/gps-cs-s/APNQkAE73R-pvwrF1d7aG3UQuDvaSt9ptSC27TK629uDBc19D_WyilK1fQLv4cMzPTNkWOPB8IZv6O6RfxiI5V3RmXmiUd0MdKOk5ktd0nsV0q0RRicpqZfTmXCIMbtEiydMh62fw28K=w122-h92-k-no | K40: https://ssl.gstatic.com/local/servicebusiness/default_user.png | L40: "Exept the Curry, everything Else is actually | M40: vegan | N40: ." | O40: · | P40: ₫1–100,000
A41: https://www.google.com/maps/place/Roots+%26+Rise/data=!4m7!3m6!1s0x3175270016f0c36d:0xf3263f08ab6aacf1!8m2!3d10.8120476!4d106.7348551!16s%2Fg%2F11wxpdc7xv!19sChIJbcPwFgAndTER8axqqwg_JvM?authuser=0&hl=en&rclk=1 | B41: Roots & Rise | C41: 4.9 | D41: -19 | E41: Vegan | F41: · | G41: 215H1C, Nguyễn Văn Hưởng | H41: Closed | I41: · Opens 8:30 AM | J41: https://lh3.googleusercontent.com/gps-cs-s/APNQkAEu7ltMN2hc0S40FN7w8U_W8Nubr4zWtu8vj1KtLBDmR9R_3SXCVpC9mhmo3DLZ0TI8gNKbmWviS1LnH5H4AKg0GofvBQPGccx8c7BqBzYt9bUmtsCH40ZehVMZ3WnDfFyhfym-jYaEF3JZ=w80-h142-k-no | K41: https://ssl.gstatic.com/local/servicebusiness/default_user.png | L41: "Beautiful, serene little slice of | M41: vegan | N41: heaven." | P41: ₫200–300K
A42: https://www.google.com/maps/place/Baba%27s+Kitchen+Indian+Restaurant+-+Thao+Dien/data=!4m7!3m6!1s0x3175262237da0859:0x2e8c079ba024e026!8m2!3d10.8055277!4d106.733663!16s%2Fg%2F11dyz97wlm!19sChIJWQjaNyImdTERJuAkoJsHjC4?authuser=0&hl=en&rclk=1 | B42: Baba's Kitchen Indian Restaurant - Thao Dien | C42: 4.8 | D42: -2258 | E42: Indian | F42: · | G42: · | H42: Closed | I42: · Opens 11 AM | J42: https://lh3.googleusercontent.com/gps-cs-s/APNQkAGuntwPsWDf1ueQZGKHG8BGs6dAcRiHayTdAxvOLGjRgVZHIWz24kKdgFneGajT-yekbs2JLZ8-hyhTF5JoCIYSUPO6pFKcdpHepUc9iqwChf3SGAYk8llCXdIG-c1GTRbualrdzZ36hps=w163-h92-k-no | K42: https://ssl.gstatic.com/local/servicebusiness/default_user.png | L42: "The menu has a great variety of options, including plenty for vegetarians." | O42: · | P42: ₫200–300K | Q42:  | R42: 35 Lê Văn Miến
A43: https://www.google.com/maps/place/YUKINO+Foods+Japan/data=!4m7!3m6!1s0x317527d3f9101d23:0xef94ce47b61983e4!8m2!3d10.803137!4d106.736952!16s%2Fg%2F11h9g3fp15!19sChIJIx0Q-dMndTER5IMZtkfOlO8?authuser=0&hl=en&rclk=1 | B43: YUKINO Foods Japan | C43: 4.5 | D43: -59 | E43: Vegan | F43: · | G43: 39 Nguyễn Duy Hiệu | H43: Closed | I43: · Opens 8 AM | J43: https://lh3.googleusercontent.com/gps-cs-s/APNQkAE9ypDFVcTRaBXpC-IY5HaSj63qcQ4TCx8vqSkbfzewFDr1wugoXMvPjYT4RaHwQVKP-UESoBWMYuqy-WXD_5OaOaTgw9P1WmQ0R7QQtn9GVAmOUhEuYQe0lBuvTO5PNmJMJ2la=w138-h92-k-no | K43: https://ssl.gstatic.com/local/servicebusiness/default_user.png | L43: "They have | M43: vegan | N43: milk tea with pearls here and on their menu!" | O43: · | P43: ₫1–100,000
A44: https://www.google.com/maps/place/Be+An+Vegetarian+Bistro/data=!4m7!3m6!1s0x31752fc59340bdeb:0xdf3513c4d4fb4ba!8m2!3d10.7844192!4d106.6977993!16s%2Fg%2F11kjf2bthm!19sChIJ671Ak8UvdTERurRPTTxR8w0?authuser=0&hl=en&rclk=1 | B44: Be An Vegetarian Bistro | C44: 4.8 | D44: -1365 | E44: Vegetarian | F44: · | G44: 11B Trần Cao Vân | H44: Closed | I44: · Opens 10 AM | J44: https://lh3.googleusercontent.com/gps-cs-s/APNQkAHibsuIfirO7OLUDGTjST_hWVMzcyZKpxEmpD7lS4SdtgE84_rnYJ-IciglT3hxX2rUccdr0WWIpVboZlcxdCLCX2VliXTjiAriKuIupCTuS4aoynMzYEm0zzWUb9VwoVWVBMg51iK8PrFV=w122-h92-k-no | K44: https://ssl.gstatic.com/local/servicebusiness/default_user.png | L44: "Amazing | M44: vegan food | N44: , calming atmosphere" | P44: ₫200–300K
A45: https://www.google.com/maps/place/CHAY+GARDEN+Nguy%E1%BB%85n+Th%E1%BB%8B+Minh+Khai+-+Vegetarian+Restaurant+%26+Space/data=!4m7!3m6!1s0x31752ffb64ae97c9:0xc6fb1c069a9e660d!8m2!3d10.7851375!4d106.6999919!16s%2Fg%2F11ypknpdb2!19sChIJyZeuZPsvdTERDWaemgYc-8Y?authuser=0&hl=en&rclk=1 | B45: CHAY GARDEN Nguyễn Thị Minh Khai - Vegetarian Restaurant & Space | C45: 4.8 | D45: -393 | E45: Vegetarian | F45: · | G45: 20 Nguyễn Thị Minh Khai | H45: Closed | I45: · Opens 10:30 AM | J45: https://lh3.googleusercontent.com/gps-cs-s/APNQkAH4S9HlEUKCUFH0Q1ooB66OOtr4eeHK6701xw7dsVL-8G7KiD6Z4rovvFUrJ4thOo7BWDN_yQH2mXsQ1nozs_TohVYyrE1t5rPZABa6fdMZS2osMeVur3_BvhfXAHW6_IQTX02mTOmwsruc=w122-h92-k-no | K45: https://ssl.gstatic.com/local/servicebusiness/default_user.png | L45: "Very good | M45: vegetarian food | N45: , kind service and nice atmosphere." | P45: ₫200–300K
A46: https://www.google.com/maps/place/L%C3%A9gumes+Vietnam+-+Healthy+Groceries,+Juice,+Acai,+Smoothie+Bar/data=!4m7!3m6!1s0x3175277f33c4dabf:0xc2c4ce7c68a6ae4e!8m2!3d10.8035862!4d106.7284826!16s%2Fg%2F11h1z1t6x8!19sChIJv9rEM38ndTERTq6maHzOxMI?authuser=0&hl=en&rclk=1 | B46: Légumes Vietnam - Healthy Groceries, Juice, Acai, Smoothie Bar | C46: 4.8 | D46: -649 | E46: Vegan | F46: · | G46: · | H46: Open | I46: · Closes 9:30 PM | J46: https://lh3.googleusercontent.com/gps-cs-s/APNQkAHY2cFebmI17I7PpSMWpCu6MUBLEwSnyyfX4XkD9bHj_6-yJI3fx4b47UmDzlpqeKL3UmAwoBs_h1Q1P2NIR276owJgiy3rzkthgEaoQCdRnrtkn87XaIsXW-9sPNWds_9ICNA=w138-h92-k-no | K46: https://ssl.gstatic.com/local/servicebusiness/default_user.png | L46: "The | M46: food | N46: is good, and they have so many | P46: ₫200–300K | Q46:  | R46: 40 Đ. Nguyễn Cừ
A47: https://www.google.com/maps/place/Atithi+Indian+Vegetarian+Restaurant/data=!4m7!3m6!1s0x31752f623b8c0c27:0x7526c3936d0827bc!8m2!3d10.7721026!4d106.6941655!16s%2Fg%2F11yqspzhpd!19sChIJJwyMO2IvdTERvCcIbZPDJnU?authuser=0&hl=en&rclk=1 | B47: Atithi Indian Vegetarian Restaurant | C47: 4.9 | D47: -611 | E47: Restaurant | F47: · | G47: 246 Lý Tự Trọng | H47: Closed | I47: · Opens 8 AM | J47: https://lh3.googleusercontent.com/gps-cs-s/APNQkAFNYvaBbmoWfnZ_17muTTsdS02XlufisLWRr27aoJb0eemYXpr0ezCUu2u8aY9ddkuUD6kmGH7-0pjpONjt3bo6ZfSmCC8maViJ6PXrrtBbpllXh_czXJIHAqYJT1cEGsegXBYn1ss2QC0O=w122-h92-k-no | K47: https://ssl.gstatic.com/local/servicebusiness/default_user.png | L47: "Fresh and healthy | M47: food | N47: , sitting very comfortable, reasonable prices" | P47: ₫200–300K
A48: https://www.google.com/maps/place/C%C6%A1m+chay+thi%E1%BB%87n+t%C3%A2m/data=!4m7!3m6!1s0x317527004d9add45:0x237d2450581cfa2e!8m2!3d10.7938659!4d106.7351801!16s%2Fg%2F11xnmgytmb!19sChIJRd2aTQAndTERLvocWFAkfSM?authuser=0&hl=en&rclk=1 | B48: Cơm chay thiện tâm | C48: 5 | D48: -2 | E48: Vegetarian | F48: · | G48: 15 Đ. Vành Đai Tây | J48: https://lh3.googleusercontent.com/gps-cs-s/APNQkAFmpyabZix3ofMci2w7avzKUhYlefEz_IHEdKgHvmxijsphnmEGY_sj46J5V7YYu60shsK8j9blT01m699QOL1tr1FV4lfpvdNoFm_vUodwvZiNzMDcQ16gNypMCAW7dvBx4YlfBYrFph59=w80-h177-k-no | K48: https://ssl.gstatic.com/local/servicebusiness/default_user.png | L48: "Super super delicious, many traditional dishes of Vietnam for break fast." | P48: ₫1–100,000
A49: https://www.google.com/maps/place/Xanh+vegan+and+vegetarian/data=!4m7!3m6!1s0x317529262821a143:0x65f789063aa8afae!8m2!3d10.7919385!4d106.7195364!16s%2Fg%2F11jgq4cmvc!19sChIJQ6EhKCYpdTERrq-oOgaJ92U?authuser=0&hl=en&rclk=1 | B49: Xanh vegan and vegetarian | C49: 4.1 | D49: -43 | E49: Vegetarian | F49: · | G49: hẻm 132 132/41 Nguyễn Hữu Cảnh | H49: Open | I49: · Closes 11:30 PM | J49: https://lh3.googleusercontent.com/gps-cs-s/APNQkAHqZJDXMmj0xEJA9ytrK8VHsa1wVXGriJY-YPOjF4EcTjUODQszCysjUh6hIbPHhXZYtLtTURPc_o7qH3TqobjZBFjoQp4QwyaoWYeYKt94izED3IxUvlyzIW1vIaxcIRAdyn7O=w80-h106-k-no | K49: https://ssl.gstatic.com/local/servicebusiness/default_user.png | L49: "Very good | M49: food | N49: , eco friendly packaging, generous portions and good price." | O49: · | P49: ₫100–200K
A50: https://www.google.com/maps/place/Be+An+Vegetarian+Bistro/data=!4m7!3m6!1s0x31752ffbfbe36a49:0x9c10bfad0d4fdd69!8m2!3d10.7733531!4d106.7038615!16s%2Fg%2F11fs2zs_3d!19sChIJSWrj-_svdTERad1PDa2_EJw?authuser=0&hl=en&rclk=1 | B50: Be An Vegetarian Bistro | C50: 4.8 | D50: -2220 | E50: Vegetarian | F50: · | G50: · | H50: Closed | I50: · Opens 10 AM | J50: https://lh3.googleusercontent.com/gps-cs-s/APNQkAEU1CqIqin57XcidGk6ah6PF6CGC-B3sucxTGQPlDvQtCGR9f4MwBn15EvfHqBnCpx6kV3PNPsYxR_DvuRe3NpMir62Bp-XCyGmtIafAK_TToiTkRQFokcJ8tGs9ZQl2-zsWg7gxA=w163-h92-k-no | K50: https://ssl.gstatic.com/local/servicebusiness/default_user.png | L50: "Gorgeous | M50: restaurant | N50: , lovely staff and the most delicious | P50: ₫200–300K | Q50:  | R50: Saigon Garden, 99 Nguyễn Huệ
A51: https://www.google.com/maps/place/Roots+Plant-based+Cafe+-+Ben+Thanh/data=!4m7!3m6!1s0x31752f2c5b5c23f9:0x37dd5beb607c8cff!8m2!3d10.7741206!4d106.6975015!16s%2Fg%2F11xcvlc9qw!19sChIJ-SNcWywvdTER_4x8YOtb3Tc?authuser=0&hl=en&rclk=1 | B51: Roots Plant-based Cafe - Ben Thanh | C51: 4.9 | D51: -1407 | E51: Brunch | F51: · | G51: 113-115 Lý Tự Trọng | H51: Closed | I51: · Opens 8 AM | J51: https://lh3.googleusercontent.com/gps-cs-s/APNQkAHTJcpS-PMu0ii59IXZeIxuwa8iNlC2SA9SS9qm0NQ5NUgGcBMryRvrISQUSfwICILQ_6W0we_ar9fT_bEWSQbzdmmptjMJqLNnRZLvrXGDu06-9rGUzZ863bBDfe3G9vpsu0RajPvQI8fg=w80-h106-k-no | K51: https://ssl.gstatic.com/local/servicebusiness/default_user.png | L51: "Great | M51: vegan food | N51: in a calm stylish setting." | O51: · | P51: ₫100–200K
A52: https://www.google.com/maps/place/Casablanca+Moroccan+Flavors/data=!4m7!3m6!1s0x317527946c479a99:0xdd72205dc9cb9018!8m2!3d10.8044683!4d106.7395548!16s%2Fg%2F11yw2tslws!19sChIJmZpHbJQndTERGJDLyV0gct0?authuser=0&hl=en&rclk=1 | B52: Casablanca Moroccan Flavors | C52: 5 | D52: -10 | E52: Vegan | F52: · | G52: 19 Trần Ngọc Diện | H52: Closed | I52: · Opens 9 AM | J52: https://lh3.googleusercontent.com/gps-cs-s/APNQkAHk9TbIcsW9eMDe-jLfdH9U87QI2MaC8WC1yKR0218yR_2E1yIPbg_nrduNer7BDb193qHlI6DvCIT9okPY_93i3AsiDQmS049upOH_DPI4bYkA5jHrzBsdMv6QamLlyDzmx98iEJ-CMKUv=w80-h106-k-no | K52: https://ssl.gstatic.com/local/servicebusiness/default_user.png | L52: "The portion for each dish is huge, needs at least 2 people to finish." | O52: · | P52: ₫100–200K
A53: https://www.google.com/maps/place/T%C3%A2m+T%C3%A2m+Vegetarian+%26+Coffee/data=!4m7!3m6!1s0x31752f0039cee3fd:0x3ac1c8aab080479b!8m2!3d10.7797526!4d106.6855053!16s%2Fg%2F11y8mw3gjz!19sChIJ_ePOOQAvdTERm0eAsKrIwTo?authuser=0&hl=en&rclk=1 | B53: Tâm Tâm Vegetarian & Coffee | C53: 4.9 | D53: -420 | E53: Health Food | F53: · | G53: 49C Tú Xương | H53: Closed | I53: · Opens 10 AM | J53: https://lh3.googleusercontent.com/gps-cs-s/APNQkAHf_mLZcwanuyzcupEHDV7EoLbqDKeXVvNQuCPL9R7gfY-46O9fJVLYGfSnck9S1p7ttfkuo8uGD5a6ui1-lTDFCEPwezAs0BnOWbbqgAO3VFueF6P_gOy-2Qui-4kLBAkybq3Da9TH5Ow=w122-h92-k-no | K53: https://ssl.gstatic.com/local/servicebusiness/default_user.png | L53: "Delicious | M53: vegan food | N53: and great service" | P53: ₫100–200K
A54: https://www.google.com/maps/place/OM+Eatery+-+Vegetarian+%26+Vegan+Food/data=!4m7!3m6!1s0x31752f38023fcab5:0x2352c23a411e03d6!8m2!3d10.7890301!4d106.6908913!16s%2Fg%2F11vhczg2kr!19sChIJtco_AjgvdTER1gMeQTrCUiM?authuser=0&hl=en&rclk=1 | B54: OM Eatery - Vegetarian & Vegan Food | C54: 4.8 | D54: -634 | E54: Vegan | F54: · | G54: 80 Đinh Công Tráng | H54: Closed | I54: · Opens 9 AM | J54: https://lh3.googleusercontent.com/gps-cs-s/APNQkAE7QqUav8a-aes7seT4veYvW1qWddmSWQboh8IbQcPLepnkWckVaeY4iCaamU28xfk0OeRu2BonmN4New9bnuKGSKj7VneWP4IlF_l3tpXtlxk2f-O0g4vZtv8mJtIfALuUSy4Slrxejlk=w122-h92-k-no | K54: https://ssl.gstatic.com/local/servicebusiness/default_user.png | L54: "It’s both satisfying and guilt-free — a great balance of health and taste." | P54: ₫200–300K
A55: https://www.google.com/maps/place/Bon%E2%80%99s+Vegan+Bistro+-+B%C3%A1nh+M%C3%AC+%26+Coffee/data=!4m7!3m6!1s0x31752fac15ce84d1:0xb3ae51a8927c2cb!8m2!3d10.7702529!4d106.7020348!16s%2Fg%2F11j72t29ws!19sChIJ0YTOFawvdTERy8IniRrlOgs?authuser=0&hl=en&rclk=1 | B55: Bon’s Vegan Bistro - Bánh Mì & Coffee | C55: 4.9 | D55: -834 | E55: Vegan | F55: · | G55: 89/8 Hàm Nghi | H55: Closed | I55: · Opens 8 AM | J55: https://lh3.googleusercontent.com/gps-cs-s/APNQkAFxWFaxzpAxn7CuO0QjWwcTOVrEzl5mqwefvAoRlvt5NQIvmiP1XRHk4qOCyDiZN4SmJ5_Uv9UBANL0Y3uS-MzC4b9epGxIAyOYeAD1FWU9jf4BHq7iiL0j6-qLu8WrwOVUpRiybROyJ7R_=w122-h92-k-no | K55: https://ssl.gstatic.com/local/servicebusiness/default_user.png | L55: "Delicious | M55: vegan food | N55: , the loveliest service and a beautiful environment." | O55: · | P55: ₫100–200K
A56: https://www.google.com/maps/place/We+Desi+Tadka+pure+vegetarian+Indian+restaurant/data=!4m7!3m6!1s0x31752fa42f902c89:0x2986500e958c8491!8m2!3d10.768231!4d106.693986!16s%2Fg%2F11wx6w9klh!19sChIJiSyQL6QvdTERkYSMlQ5Qhik?authuser=0&hl=en&rclk=1 | B56: We Desi Tadka pure vegetarian Indian restaurant | C56: 4.8 | D56: -124 | E56: Vegan | F56: · | G56: 185/30 Phạm Ngũ Lão | H56: Open 24 hours | J56: https://lh3.googleusercontent.com/gps-cs-s/APNQkAERwz5kxpWhOMExAeswSZhV69pdqX3Hunwttl5LlZrOJ35a_rUtmmEcVpQLwpX_FtbJhGVwcQByUG7PzlEtKz7a2d50YOsFNDsusPX-gX0XssoFNG7UwJb8KdxEHDNGm0vz2l_MZ19JMXVH=w122-h92-k-no | K56: https://ssl.gstatic.com/local/servicebusiness/default_user.png | L56: "Delicious | M56: vegetarian food | N56: , top-notch service, 👍🏻and outstanding ambiance." | O56: · | P56: ₫100–200K
A57: https://www.google.com/maps/place/Thien+Duyen+Vegetarian+Restaurant/data=!4m7!3m6!1s0x317527f623e2f729:0xb4a0fe4c5a87ee5e!8m2!3d10.8031576!4d106.752121!16s%2Fg%2F11q4h7ld4x!19sChIJKffiI_YndTERXu6HWkz-oLQ?authuser=0&hl=en&rclk=1 | B57: Thien Duyen Vegetarian Restaurant | C57: 4.5 | D57: -265 | E57: Vegetarian | F57: · | G57: · | H57: Closed | I57: · Opens 9 AM | J57: https://lh3.googleusercontent.com/gps-cs-s/APNQkAH84SdWDiPLOnpIfL5YQM2T_Gbw6s6rBD4Lp8J5myi08q9U0GOX2GMZm85ZRmEc56ktDeyUDuhzY90ePGxN-N4cs6sm-4EqVldKFXKw9TR4vR8pUWqf8XTJS27eWwgjVlEKeNE-=w122-h92-k-no | K57: https://ssl.gstatic.com/local/servicebusiness/default_user.png | L57: "Southern | M57: vegan food | N57: is great... a large space." | O57: · | P57: ₫100–200K | Q57:  | R57: 505B Võ Nguyên Giáp
A58: https://www.google.com/maps/place/The+Joi+Factory+%28Vegetarian+Caf%C3%A9+Restaurant%29/data=!4m7!3m6!1s0x31752f3b61a1c881:0x22eb580f5f5488d0!8m2!3d10.7653559!4d106.6866134!16s%2Fg%2F11jg89cc0w!19sChIJgcihYTsvdTER0IhUXw9Y6yI?authuser=0&hl=en&rclk=1 | B58: The Joi Factory (Vegetarian Café Restaurant) | C58: 4.6 | D58: -1067 | E58: Bistro | F58: · | G58: Hẻm 212/2B1 Nguyễn Trãi | H58: Open | I58: · Closes 9:30 PM | J58: https://lh3.googleusercontent.com/gps-cs-s/APNQkAG96jZJ0s7jsvQ6IliAls7WbT5uoEFCbl0Uzwg9pPJmnaA-mt-JdSZkSYvXAJW2s-gRpO4hDOmuPfGYw5nKmvxHLPJIhpVfrwAh4zm2tBgv4Q6fAt_H_O5khp3-ZLGzXn7YsV7TTZH7_0UV=w122-h92-k-no | K58: https://ssl.gstatic.com/local/servicebusiness/default_user.png | L58: "Relaxing ambiance, great staff, delicious | M58: vegan food | N58: !" | O58: · | P58: ₫100–200K
A59: https://www.google.com/maps/place/21Grams+Vegetarian/data=!4m7!3m6!1s0x31752f616c7ba2f3:0xf25f36475c2b39b3!8m2!3d10.774103!4d106.7041327!16s%2Fg%2F11ty14p2l3!19sChIJ86J7bGEvdTERszkrXEc2X_I?authuser=0&hl=en&rclk=1 | B59: 21Grams Vegetarian | C59: 4.9 | D59: -1857 | E59: Vegetarian | F59: · | G59: 42 Nguyễn Huệ | H59: Closed | I59: · Opens 10 AM | J59: https://lh3.googleusercontent.com/gps-cs-s/APNQkAFkngcmz2-xmSd449CxhPMaYeLzwEElt_gp94-28vwbZv90Yl7QfLdGaGDAlNH_KRqidrLJ6gPP58XzpzZo3DWZ4yIM5_7eUcQJ-Q0DPpgvdLaDcAjSe2QgXFkNtOsI0oNpo5YZR_dbBas=w122-h92-k-no | K59: https://ssl.gstatic.com/local/servicebusiness/default_user.png | L59: "All | M59: vegetarian restaurant | N59: with | O59: · | P59: ₫100–200K
A60: https://www.google.com/maps/place/La+Moi+plant-based+Restaurant/data=!4m7!3m6!1s0x31752fb36bbd2f47:0x35c6b390bd1bdfcf!8m2!3d10.778431!4d106.699046!16s%2Fg%2F11k4qvqc29!19sChIJRy-9a7MvdTERz98bvZCzxjU?authuser=0&hl=en&rclk=1 | B60: La Moi plant-based Restaurant | C60: 4.7 | D60: -910 | E60: Vegan | F60: · | G60: 84 Nguyễn Du | H60: Closed | I60: · Opens 8 AM | J60: https://lh3.googleusercontent.com/gps-cs-s/APNQkAE04LC-88q8eRp257HX27lq04tmuV6V3aPyb08aHoYxINfkj6PbdJsNrCp9CN1fN8y7oWH7TTq6iy__bG96OmyzNtcHGPy6hTv6Im8RRAu8XCAg_SP54rTvLSTuj0x-uEZ1gJLvzepaILU=w80-h106-k-no | K60: https://ssl.gstatic.com/local/servicebusiness/default_user.png | L60: "The Pad Thai was a flavor explosion, setting a high bar for | M60: vegan | N60: cuisine." | O60: · | P60: ₫200–300K
A61: https://www.google.com/maps/place/B%E1%BA%BFp+Chay+%26+Cafe+NH%C3%80+M%E1%BA%A4Y+D%C3%8C/data=!4m7!3m6!1s0x3175298fe06f3bbd:0xcf0b8de597c559c!8m2!3d10.795483!4d106.7101379!16s%2Fg%2F11sw0vlbpy!19sChIJvTtv4I8pdTERnFV8Wd648Aw?authuser=0&hl=en&rclk=1 | B61: Bếp Chay & Cafe NHÀ MẤY DÌ | C61: 4.5 | D61: -169 | E61: Vegetarian | F61: · | G61: 80 Xô Viết Nghệ Tĩnh | H61: Closed | I61: · Opens 10 AM | J61: https://lh3.googleusercontent.com/gps-cs-s/APNQkAGasCU95XDbC2UNRmdsPJB76EgtedeHQQ6704IA7rVlwGsVTBqWSqg_8jZlujvq9RO8tSA-tGFQfI5dN0qALucsP4V599UEvTiLzio5qrbXzs6d6lWFRk6cDW2Idaauc88TMS0H=w80-h106-k-no | K61: https://ssl.gstatic.com/local/servicebusiness/default_user.png | L61: "Great | M61: vegan | N61: place on the water, cool view and tasty dishes" | O61: · | P61: ₫100–200K
A62: https://www.google.com/maps/place/Hum+Lounge+-+Healthy+Veggies+Delights/data=!4m7!3m6!1s0x31752f78f8ad36e9:0x6b9f0dd3b56322e5!8m2!3d10.7786114!4d106.6920676!16s%2Fg%2F11vqs4_p8x!19sChIJ6Tat-HgvdTER5SJjtdMNn2s?authuser=0&hl=en&rclk=1 | B62: Hum Lounge - Healthy Veggies Delights | C62: 4.8 | D62: -314 | E62: Vegetarian | F62: · | G62: 34 Võ Văn Tần | H62: Closed | I62: · Opens 10 AM | J62: https://lh3.googleusercontent.com/gps-cs-s/APNQkAEihJqg8vJko8hFo-5cc_G3C5_1BocZ7CYSCW-OKK4Y7nlClYupdkOij-ERQLgsfrfoiPSOuIOkTxBYmwHE1KUU9t0XuqpzY6zqXj_YWiIWDWCldH7LmKH3dVwvPh_-m9u2DNBV=w122-h92-k-no | K62: https://ssl.gstatic.com/local/servicebusiness/default_user.png | L62: "Refreshing and delicious | M62: vegetarian | N62: dishes with friendly staff." | P62: ₫200–300K
A63: https://www.google.com/maps/place/Tanishq+Indian+Vegetarian+Restaurant/data=!4m7!3m6!1s0x31752f005cdd2991:0x5e8b095e1f1ff220!8m2!3d10.7719456!4d106.6939273!16s%2Fg%2F11w9kmg0rf!19sChIJkSndXAAvdTERIPIfH14Ji14?authuser=0&hl=en&rclk=1 | B63: Tanishq Indian Vegetarian Restaurant | C63: 4.9 | D63: -2810 | E63: Indian | F63: · | G63: 258 Lý Tự Trọng | H63: Closed | I63: · Opens 8 AM | J63: https://lh3.googleusercontent.com/gps-cs-s/APNQkAFNoNjojfojUoi_qdrHv96Ejls4hgZV2uGACIbH5YDtYZNI517fD7oOIURCtDdXp2sWJZ7oFskMtQY-lL3OkgS0EopkZxkxVnT69IH3cj20gp6wVM4uIf0aMxePXOP1blqxzVxJm72a8_fC=w163-h92-k-no | K63: https://ssl.gstatic.com/local/servicebusiness/default_user.png | L63: "We are | M63: vegan | N63: and left completely full and happy." | P63: ₫200–300K
A64: https://www.google.com/maps/place/Nho%C3%A0n+-+Nh%C3%A0+h%C3%A0ng+chay+%2F+Cafe/data=!4m7!3m6!1s0x31752772508925a3:0xb8011424a00696cd!8m2!3d10.808991!4d106.753609!16s%2Fg%2F11vlhzkhxp!19sChIJoyWJUHIndTERzZYGoCQUAbg?authuser=0&hl=en&rclk=1 | B64: Nhoàn - Nhà hàng chay / Cafe | C64: 4.9 | D64: -333 | E64: Vegetarian restaurant | F64: · | G64: 4 Đặng Tiến Đông | H64: Closed | I64: · Opens 9 AM | J64: https://lh3.googleusercontent.com/p/AF1QipNUurZ69UR_ApupjfjIOZwXHm_Y7mD6O3IwyUJR=w80-h92-p-k-no | K64: https://ssl.gstatic.com/images/icons/material/system_gm/2x/done_gm_green700_24dp.png | L64: Dine-in | M64: Delivery | P64: ₫200–300K
A65: https://www.google.com/maps/place/Nho%C3%A0n+-+Nh%C3%A0+h%C3%A0ng+chay+%2F+Cafe/data=!4m7!3m6!1s0x31752772508925a3:0xb8011424a00696cd!8m2!3d10.808991!4d106.753609!16s%2Fg%2F11vlhzkhxp!19sChIJoyWJUHIndTERzZYGoCQUAbg?authuser=0&hl=en&rclk=1 | B65: Nhoàn - Nhà hàng chay / Cafe | C65: 4.9 | D65: -333 | E65: Vegetarian restaurant | F65: · | G65: 4 Đặng Tiến Đông | H65: Closed | I65: · Opens 9 AM | J65: https://lh3.googleusercontent.com/p/AF1QipNUurZ69UR_ApupjfjIOZwXHm_Y7mD6O3IwyUJR=w80-h92-p-k-no | K65: https://ssl.gstatic.com/images/icons/material/system_gm/2x/done_gm_green700_24dp.png | L65: Dine-in | M65: Delivery | P65: ₫200–300K
A66: https://www.google.com/maps/place/B%C3%BAn+ri%C3%AAu+chay+mi%E1%BB%85n+ph%C3%AD/data=!4m7!3m6!1s0x3175279c4a82bcc7:0x7070ae1b8db4769b!8m2!3d10.8028135!4d106.7304438!16s%2Fg%2F11plg4shkm!19sChIJx7yCSpwndTERm3a0jRuucHA?authuser=0&hl=en&rclk=1 | B66: Bún riêu chay miễn phí | C66: 5 | D66: -1 | E66: Vegetarian | F66: · | G66: 44 Xuân Thủy | J66: https://lh3.googleusercontent.com/gps-cs-s/APNQkAGBIjPY4W3BShBk7DQjppHMOawihyvyUPpAR9YgfSLJk20CS8U-wDPW62rSKQubZcMxKvR9bggrvV3tY-cRU6GF6T_4VgnQAFHCBq_fPnJSk08xrnb2eXFnPli0WSYNiKGBwF9Z=w122-h92-k-no | L66: Dine-in | P66: ₫1–100,000
A67: https://www.google.com/maps/place/IVEGAN+SUPERSHOP+BEN+THANH+-+HEALTHY+PLANT+BASED+CAFE/data=!4m7!3m6!1s0x317527178384a5e9:0x6bd0b476886d57!8m2!3d10.7716643!4d106.6950738!16s%2Fg%2F11kqq40qrz!19sChIJ6aWEgxcndTERV22IdrTQawA?authuser=0&hl=en&rclk=1 | B67: IVEGAN SUPERSHOP BEN THANH - HEALTHY PLANT BASED CAFE | C67: 4.9 | D67: -1419 | E67: Vegan | F67: · | G67: 29 Lê Anh Xuân | H67: Closed | I67: · Opens 8:30 AM | J67: https://lh3.googleusercontent.com/gps-cs-s/APNQkAHvN7yMO2aOrkk636VjUsjsCUuEoovgG8Fpg8kriJhyAmLmCU3Sq1V9Zv995oJF8a4dSoj6OZi2FbCX_-W6Od5W8ztgPl7qTZr4QLh7NM5s6btaBCA_dk6LmP-rOzy9tE1R8UmmqFBsP0od=w80-h106-k-no | K67: https://ssl.gstatic.com/local/servicebusiness/default_user.png | L67: "Delicious | M67: vegan food | N67: , cute cozy space and nice staff." | O67: · | P67: ₫100–200K
A68: https://www.google.com/maps/place/Com+Tam+Chay+Thanh+Cao/data=!4m7!3m6!1s0x31752f007b740a89:0x3b2cdb5ba567ffd6!8m2!3d10.7589212!4d106.7011623!16s%2Fg%2F11ynzgv4n1!19sChIJiQp0ewAvdTER1v9npVvbLDs?authuser=0&hl=en&rclk=1 | B68: Com Tam Chay Thanh Cao | C68: 5 | D68: -20 | E68: Vegan | F68: · | G68: 56 Đ. Số 41 | H68: Open | I68: · Closes 8 PM | J68: https://lh3.googleusercontent.com/gps-cs-s/APNQkAG7qAwe2PdW3XVLFEm0rQoJ8klCVjf0IMATEmJCehCBQbhNQKsOMD4D0bLrppsQCIzUV5nI1ELrx90aAt67ClUfIcOJCbXCFDVPfRL-QxXiP7BaUxZJdYQPhZs1yJdF7hm3LOlweNeD-5l7=w80-h106-k-no | K68: https://ssl.gstatic.com/local/servicebusiness/default_user.png | L68: "Delicious | M68: vegetarian food | N68: and the service is super nice!" | O68: · | P68: ₫1–100,000
A69: https://www.google.com/maps/place/Nh%C3%A0+h%C3%A0ng+chay+Di%E1%BB%87u+H%E1%BA%A1nh+-+The+Galleria/data=!4m7!3m6!1s0x31752f890ac8c581:0x541310e9f21336d8!8m2!3d10.7789753!4d106.7136966!16s%2Fg%2F11kq85n65_!19sChIJgcXICokvdTER2DYT8ukQE1Q?authuser=0&hl=en&rclk=1 | B69: Nhà hàng chay Diệu Hạnh - The Galleria | C69: 4.5 | D69: -146 | E69: Vegetarian | F69: · | G69: 20 Nguyễn Thiện Thành | H69: Closed | I69: · Opens 8 AM | J69: https://lh3.googleusercontent.com/gps-cs-s/APNQkAFEHgLzXI0Kco6Dvo-1oS8r_2M0hmxCFt3L8cIwfIRINbMQVMNaZtU96GlX7dnbeHgk0-xRLlvi7EzKEJqTCsfmdfklJkNvCRKlDWZt0tkKGE1nIov1B6CFombGjOkZZHqyIPYiKYwH1eb1=w122-h92-k-no | K69: https://ssl.gstatic.com/local/servicebusiness/default_user.png | L69: "All the menu items are | M69: vegetarian | N69: and extremely tasty." | O69: · | P69: ₫100–200K
A70: https://www.google.com/maps/place/Amitaba+Vegetarian+Restaurant/data=!4m7!3m6!1s0x31752f15039af52b:0xa72c4e69add2cb72!8m2!3d10.7650756!4d106.6973781!16s%2Fg%2F11f40028wt!19sChIJK_WaAxUvdTERcsvSrWlOLKc?authuser=0&hl=en&rclk=1 | B70: Amitaba Vegetarian Restaurant | C70: 4.4 | D70: -453 | E70: Vegetarian | F70: · | G70: · | H70: Open | I70: · Closes 2 PM · Reopens 4 PM | J70: https://lh3.googleusercontent.com/gps-cs-s/APNQkAETy8c8pOGT1p5CjqVTFy2iM0Am3Zx8G5geX5smpOiCq0gDf3CdIUXPhJ4XyI7HDL1DjSpDUyO75dmpw_2SihG_cYDvnMGUlFSZ4-ZfjX0y96bo-yrXlg2XBGmpqQphrsuG6bQxxcnzkiXL=w80-h106-k-no | K70: https://ssl.gstatic.com/local/servicebusiness/default_user.png | L70: "Delicious | M70: vegan food | N70: for a great price." | O70: · | P70: ₫100–200K | Q70:  | R70: 40 Nguyễn Thái Học
A71: https://www.google.com/maps/place/V%C6%B0%E1%BB%9Dn+chay+Di%E1%BB%87u+Gi%C3%A1c/data=!4m7!3m6!1s0x317527b8afd0ed1b:0xa654d445efedaed7!8m2!3d10.7885877!4d106.7301262!16s%2Fg%2F11xlr9b7cf!19sChIJG-3Qr7gndTER167t70XUVKY?authuser=0&hl=en&rclk=1 | B71: Vườn chay Diệu Giác | C71: 3.7 | D71: -28 | E71: Vegan | F71: · | G71: 181 Trần Não | H71: Open | I71: · Closes 8:30 PM | J71: https://lh3.googleusercontent.com/gps-cs-s/APNQkAGdIIvBN7tGQv20UxN2lohlHFZm3RUL8bnwAz7s_st8BUTqlkXxUsogpG6BRm3N5uCgZa9qeZZWBX42sut1ZGM2NGCqR6bTxBeGN-MgqYWaAB0jXhrun9Msi6-wwqfM6iWwi8dJ_mLZA3jZ=w80-h106-k-no | K71: https://ssl.gstatic.com/local/servicebusiness/default_user.png | L71: "I was pleasantly surprised at how delicious and affordable the meals are!" | O71: · | P71: ₫1–100,000
A72: https://www.google.com/maps/place/Heal+and+Celeb+Vegan+Restaurant/data=!4m7!3m6!1s0x317529dc13f3f3b9:0xffd3cac3c0af494c!8m2!3d10.793559!4d106.686756!16s%2Fg%2F11t0rzqfyp!19sChIJufPzE9wpdTERTEmvwMPK0_8?authuser=0&hl=en&rclk=1 | B72: Heal and Celeb Vegan Restaurant | C72: 4.9 | D72: -2355 | E72: Vegan | F72: · | G72: · | H72: Closed | I72: · Opens 9:30 AM | J72: https://lh3.googleusercontent.com/gps-cs-s/APNQkAF72KOk2IbqJh_TDp3x1tDExky9otZFhKr_d61hF0KHg0CD8dr5cZi6bQCz6Nvk8mQ5Zh_RNyui-b-WXGhuJcpb_wjNlQ45vAuqMRa2OxlrUrsd5b2v3LxbBP3TlS8sDQSVIipSYS0s14qc=w138-h92-k-no | K72: https://ssl.gstatic.com/local/servicebusiness/default_user.png | L72: "Every dish was bursting with flavor, showcasing the best of | M72: vegan | N72: cuisine." | O72: · | P72: ₫100–200K | Q72:  | R72: 27/1 Nguyễn Văn Nguyễn
A73: https://www.google.com/maps/place/Filthy+Vegan/data=!4m7!3m6!1s0x31752f666798070d:0x89f2c77331d1e65f!8m2!3d10.7649171!4d106.6947502!16s%2Fg%2F11hzyv036d!19sChIJDQeYZ2YvdTERX-bRMXPH8ok?authuser=0&hl=en&rclk=1 | B73: Filthy Vegan | C73: 4.8 | D73: -641 | E73: Vegan | F73: · | G73: · | H73: Closed | I73: · Opens 11 AM | J73: https://lh3.googleusercontent.com/gps-cs-s/APNQkAF-wd2xUiJ-_n3fTqQTnjbttxIriy9lq3S5lrHRSvlP_OKLOBwKsr3_LnrsBI7vDHue1wu3ULFPKiXryTBOtOM-sJew86ZmBv-pyN6paTZGPTz498ZCr0j_37Vs0vyCBqPbwA3F=w80-h106-k-no | K73: https://ssl.gstatic.com/local/servicebusiness/default_user.png | L73: "Delicious | M73: vegan | N73: comfort | O73: · | P73: ₫100–200K | Q73:  | R73: 86 Cô Bắc
A74: https://www.google.com/maps/place/Rau+%C6%A0i+%E2%80%93+Nh%C3%A0+H%C3%A0ng+Chay/data=!4m7!3m6!1s0x3175297d2bf39315:0x18fbc9763da5630!8m2!3d10.768589!4d106.698074!16s%2Fg%2F11rhsyn223!19sChIJFZPzK30pdTERMFbaY5e8jwE?authuser=0&hl=en&rclk=1 | B74: Rau Ơi – Nhà Hàng Chay | C74: 4.7 | D74: -977 | E74: Vegan | F74: · | G74: · | H74: Closed | I74: · Opens 8 AM | J74: https://lh3.googleusercontent.com/gps-cs-s/APNQkAHxmnbyOnGDGNX2X5tjhZ1bHEX-JWZJGM10jiU1rxOOgunQiRnGOevhNwidbT2my13H8lQXaNXFRv-5NoK5hC1i6-MxeFHqTaqPRLZudPcMdpg4tkqors8jz9EjsXJiapdj_OmznqPQZX6e=w122-h92-k-no | K74: https://ssl.gstatic.com/local/servicebusiness/default_user.png | L74: "Amazing | M74: vegetarian/vegan restaurant | N74: with kind and friendly staff." | O74: · | P74: ₫100–200K | Q74:  | R74: 55/15 Lê Thị Hồng Gấm
